Workbook
Name Classical: Genres!$K$2:$K$1048576
Name Country: Genres!$L$2:$L$1048576
Name Electronic: Genres!$M$2:$M$1048576
Name Hip_Hop: Genres!$N$2:$N$1048576
Name International: Genres!$O$2:$O$1048576
Name Jazz: Genres!$P$2:$P$1048576
Name Metal: Genres!$Q$2:$Q$1048576
Name Other: Genres!$V$2:$V$1048576
Name Parent_Genre: Genres!$J$2:$J$1048576
Name Pop: Genres!$R$2:$R$1048576
Name R_B: Genres!$S$2:$S$1048576
Name Rap: Genres!$T$2:$T$1048576
Name Rock: Genres!$U$2:$U$1048576

Sheet Da Rules
A1: The Consitution of MPE Moosic
A5: Bill of Rights | G5: Rules
A6: 1 | B6: Right to vote | G6: 1 | H6: The user shall post a song every work day
A7: 2 | B7: Right to post any song | G7: 2 | H7: The user shall vote for the previous day before posting
A8: 3 | G8: 3 | H8: The user shall listen to each song until the song ends or for at least 6 minutes, whichever comes first
A9: 4 | G9: 4 | H9: The user shall be truthful with the votes
A10: 5 | G10: 5 | H10: The user shall not repeat a song
A11: 6 | G11: 6 | H11: The user shall announce the theme by Tuesday COB
A12: 7 | G12: 7 | H12: The user shall vote for the theme by noon on Wednesday
A13: 8 | G13: 8 | H13: Non-Proliferation Treaty
A14: 9 | G14: 9
A15: 10 | G15: 10
A16: Amendments | G16: Proposed Rules | M16: Joe | N16: Daniel | O16: Heran | P16: Sam | Q16: Logan
A17: 1 | B17: Right to veto a theme | G17: 1 | H17: The user shall vote each day by 3pm unless otherwise planned. | M17: N | N17: Y | O17: Y | P17: Y | Q17: y
A18: 2 | G18: 2 | H18: If a user doesn't submit a vote within 2 business days, their votes shall be determined by an RNG | N18: y
A19: 3 | G19: 3 | H19: A user can change their song entry as long as there are less than 3 songs posted for the day. | M19: Y | N19: Y | O19: Y | Q19: Y
A20: 4 | G20: 4 | H20: If a user doesn't submit their votes within 3 business days, they have to give themselves a 5 for that day. | M20: N | N20: Y | O20: Y | P20: Y | Q20: Y
A21: 5 | G21: 5
A22: 6 | G22: 6
A23: 7 | G23: 7
A24: 8 | G24: 8
A25: 9 | G25: 9
A26: 10 | G26: 10
A27: 11 | G27: 11
A28: 12 | G28: 12
A29: 13 | G29: 13
A30: 14 | G30: 14
A31: 15 | G31: 15
G32: If rules have been proposed, votes will be cast in this document. If the rule was proposed before noon, a vote will be held and a ruling will be made by the end of the same work day. Otherwise, a vote and ruling will be held the following work day. A unanimous vote is needed to pass.

Sheet Rankings
A1: Date | B1: Cover Art | C1: Winner of the day | D1: Date | E1: Poster | F1: Average | G1: STDEV | H1: Song Title | I1: Artist | J1: alappatjoe | K1: danram | L1: loganworsdell | M1: samuelbattista | N1: currydestroyer27 | O1: Plays | P1: Parent Genre | Q1: Sub-Genre | R1: Day Rank | S1: W Rank | T1: Winner | U1: Notes
A2: 45455 | C2: {=_xlfn.LET(_xlpm.matches, _xlfn._xlws.FILTER(Data[Poster], (Data[Date]=A2)*(Data[Winner]=TRUE)), IF(ROWS(_xlpm.matches)>1, "TIE", _xlpm.matches))} -> danram | D2: =A2 -> 45455 | E2: =$J$1 -> alappatjoe | F2: =IFERROR(AVERAGE(Data[[#This Row],[alappatjoe]:[currydestroyer27]]), "TBD") -> 2.8 | G2: =IFERROR(_xlfn.STDEV.P(Data[[#This Row],[alappatjoe]:[currydestroyer27]]), "TBD") -> 1.3266499 | H2: Training Season | I2: Dua Lipa | J2: 1 | K2: 5 | L2: 3 | M2: 2 | N2: 3 | P2: Pop | Q2: Dance Pop | R2: =IF(SUM(Data[[#This Row],[alappatjoe]:[currydestroyer27]])>0, COUNTIFS(Data[Date], Data[[#This Row],[Date]], Data[Average], "<"&Data[[#This Row],[Average]]) + COUNTIFS(Data[Date], Data[[#This Row],[Date]], Data[Average], Data[[#This Row],[Average]], Data[STDEV], "<"&Data[[#This Row],[STDEV]])+1, "TBD") -> 2 | S2: 1 | T2: =Data[[#This Row],[Day Rank]]=Data[[#This Row],[W Rank]] -> FALSE
D3: =D2 -> 45455 | E3: =$K$1 -> danram | F3: =IFERROR(AVERAGE(Data[[#This Row],[alappatjoe]:[currydestroyer27]]), "TBD") -> 2.2 | G3: =IFERROR(_xlfn.STDEV.P(Data[[#This Row],[alappatjoe]:[currydestroyer27]]), "TBD") -> 0.74833148 | H3: Mosquito | I3: PinkPantheress | J3: 3 | K3: 1 | L3: 2 | M3: 3 | N3: 2 | P3: Pop | Q3: UK Garage | R3: =IF(SUM(Data[[#This Row],[alappatjoe]:[currydestroyer27]])>0, COUNTIFS(Data[Date], Data[[#This Row],[Date]], Data[Average], "<"&Data[[#This Row],[Average]]) + COUNTIFS(Data[Date], Data[[#This Row],[Date]], Data[Average], Data[[#This Row],[Average]], Data[STDEV], "<"&Data[[#This Row],[STDEV]])+1, "TBD") -> 1 | S3: 1 | T3: =Data[[#This Row],[Day Rank]]=Data[[#This Row],[W Rank]] -> TRUE
D4: =D2 -> 45455 | E4: =$L$1 -> loganworsdell | F4: =IFERROR(AVERAGE(Data[[#This Row],[alappatjoe]:[currydestroyer27]]), "TBD") -> 3.2 | G4: =IFERROR(_xlfn.STDEV.P(Data[[#This Row],[alappatjoe]:[currydestroyer27]]), "TBD") -> 1.1661904 | H4: Earthquake | I4: Ferdous | J4: 4 | K4: 3 | L4: 1 | M4: 4 | N4: 4 | P4: Electronic | Q4: Dance/Electronic | R4: =IF(SUM(Data[[#This Row],[alappatjoe]:[currydestroyer27]])>0, COUNTIFS(Data[Date], Data[[#This Row],[Date]], Data[Average], "<"&Data[[#This Row],[Average]]) + COUNTIFS(Data[Date], Data[[#This Row],[Date]], Data[Average], Data[[#This Row],[Average]], Data[STDEV], "<"&Data[[#This Row],[STDEV]])+1, "TBD") -> 4 | S4: 1 | T4: =Data[[#This Row],[Day Rank]]=Data[[#This Row],[W Rank]] -> FALSE
D5: =D2 -> 45455 | E5: =$M$1 -> samuelbattista | F5: =IFERROR(AVERAGE(Data[[#This Row],[alappatjoe]:[currydestroyer27]]), "TBD") -> 2.8 | G5: =IFERROR(_xlfn.STDEV.P(Data[[#This Row],[alappatjoe]:[currydestroyer27]]), "TBD") -> 1.4696938 | H5: No Problems | I5: Ginger Root | J5: 2 | K5: 2 | L5: 4 | M5: 1 | N5: 5 | P5: Pop | Q5: Indie Pop | R5: =IF(SUM(Data[[#This Row],[alappatjoe]:[currydestroyer27]])>0, COUNTIFS(Data[Date], Data[[#This Row],[Date]], Data[Average], "<"&Data[[#This Row],[Average]]) + COUNTIFS(Data[Date], Data[[#This Row],[Date]], Data[Average], Data[[#This Row],[Average]], Data[STDEV], "<"&Data[[#This Row],[STDEV]])+1, "TBD") -> 3 | S5: 1 | T5: =Data[[#This Row],[Day Rank]]=Data[[#This Row],[W Rank]] -> FALSE
D6: =D2 -> 45455 | E6: =$N$1 -> currydestroyer27 | F6: =IFERROR(AVERAGE(Data[[#This Row],[alappatjoe]:[currydestroyer27]]), "TBD") -> 4 | G6: =IFERROR(_xlfn.STDEV.P(Data[[#This Row],[alappatjoe]:[currydestroyer27]]), "TBD") -> 1.5491933 | H6: Fly Away | I6: TheFatRat, Anjulie | J6: 5 | K6: 4 | L6: 5 | M6: 5 | N6: 1 | P6: Electronic | Q6: EDM | R6: =IF(SUM(Data[[#This Row],[alappatjoe]:[currydestroyer27]])>0, COUNTIFS(Data[Date], Data[[#This Row],[Date]], Data[Average], "<"&Data[[#This Row],[Average]]) + COUNTIFS(Data[Date], Data[[#This Row],[Date]], Data[Average], Data[[#This Row],[Average]], Data[STDEV], "<"&Data[[#This Row],[STDEV]])+1, "TBD") -> 5 | S6: 1 | T6: =Data[[#This Row],[Day Rank]]=Data[[#This Row],[W Rank]] -> FALSE
A7: 45456 | C7: {=_xlfn.LET(_xlpm.matches, _xlfn._xlws.FILTER(Data[Poster], (Data[Date]=A7)*(Data[Winner]=TRUE)), IF(ROWS(_xlpm.matches)>1, "TIE", _xlpm.matches))} -> alappatjoe | D7: =A7 -> 45456 | E7: =$J$1 -> alappatjoe | F7: =IFERROR(AVERAGE(Data[[#This Row],[alappatjoe]:[currydestroyer27]]), "TBD") -> 2.2 | G7: =IFERROR(_xlfn.STDEV.P(Data[[#This Row],[alappatjoe]:[currydestroyer27]]), "TBD") -> 0.74833148 | H7: Illusion - Extended | I7: Dua Lipa | J7: 1 | K7: 2 | L7: 2 | M7: 3 | N7: 3 | P7: Pop | Q7: Dance Pop | R7: =IF(SUM(Data[[#This Row],[alappatjoe]:[currydestroyer27]])>0, COUNTIFS(Data[Date], Data[[#This Row],[Date]], Data[Average], "<"&Data[[#This Row],[Average]]) + COUNTIFS(Data[Date], Data[[#This Row],[Date]], Data[Average], Data[[#This Row],[Average]], Data[STDEV], "<"&Data[[#This Row],[STDEV]])+1, "TBD") -> 1 | S7: 1 | T7: =Data[[#This Row],[Day Rank]]=Data[[#This Row],[W Rank]] -> TRUE
D8: =D7 -> 45456 | E8: =$K$1 -> danram | F8: =IFERROR(AVERAGE(Data[[#This Row],[alappatjoe]:[currydestroyer27]]), "TBD") -> 4.6 | G8: =IFERROR(_xlfn.STDEV.P(Data[[#This Row],[alappatjoe]:[currydestroyer27]]), "TBD") -> 0.8 | H8: Took Em Down | I8: BredGawd, LAZER DIM 700 | J8: 5 | K8: 3 | L8: 5 | M8: 5 | N8: 5 | P8: Rap | Q8: Rap | R8: =IF(SUM(Data[[#This Row],[alappatjoe]:[currydestroyer27]])>0, COUNTIFS(Data[Date], Data[[#This Row],[Date]], Data[Average], "<"&Data[[#This Row],[Average]]) + COUNTIFS(Data[Date], Data[[#This Row],[Date]], Data[Average], Data[[#This Row],[Average]], Data[STDEV], "<"&Data[[#This Row],[STDEV]])+1, "TBD") -> 5 | S8: 1 | T8: =Data[[#This Row],[Day Rank]]=Data[[#This Row],[W Rank]] -> FALSE
D9: =D7 -> 45456 | E9: =$L$1 -> loganworsdell | F9: =IFERROR(AVERAGE(Data[[#This Row],[alappatjoe]:[currydestroyer27]]), "TBD") -> 2.2 | G9: =IFERROR(_xlfn.STDEV.P(Data[[#This Row],[alappatjoe]:[currydestroyer27]]), "TBD") -> 1.4696938 | H9: Top 10 staTues tHat CriEd bloOd | I9: Bring Me The Horizon | J9: 4 | K9: 1 | L9: 1 | M9: 1 | N9: 4 | P9: Metal | Q9: Metalcore | R9: =IF(SUM(Data[[#This Row],[alappatjoe]:[currydestroyer27]])>0, COUNTIFS(Data[Date], Data[[#This Row],[Date]], Data[Average], "<"&Data[[#This Row],[Average]]) + COUNTIFS(Data[Date], Data[[#This Row],[Date]], Data[Average], Data[[#This Row],[Average]], Data[STDEV], "<"&Data[[#This Row],[STDEV]])+1, "TBD") -> 2 | S9: 1 | T9: =Data[[#This Row],[Day Rank]]=Data[[#This Row],[W Rank]] -> FALSE
D10: =D7 -> 45456 | E10: =$M$1 -> samuelbattista | F10: =IFERROR(AVERAGE(Data[[#This Row],[alappatjoe]:[currydestroyer27]]), "TBD") -> 2.6 | G10: =IFERROR(_xlfn.STDEV.P(Data[[#This Row],[alappatjoe]:[currydestroyer27]]), "TBD") -> 1.0198039 | H10: RATATATA | I10: BABYMETAL, Electric Callboy | J10: 3 | K10: 4 | L10: 3 | M10: 2 | N10: 1 | P10: International | Q10: J-Metal | R10: =IF(SUM(Data[[#This Row],[alappatjoe]:[currydestroyer27]])>0, COUNTIFS(Data[Date], Data[[#This Row],[Date]], Data[Average], "<"&Data[[#This Row],[Average]]) + COUNTIFS(Data[Date], Data[[#This Row],[Date]], Data[Average], Data[[#This Row],[Average]], Data[STDEV], "<"&Data[[#This Row],[STDEV]])+1, "TBD") -> 3 | S10: 1 | T10: =Data[[#This Row],[Day Rank]]=Data[[#This Row],[W Rank]] -> FALSE
D11: =D7 -> 45456 | E11: =$N$1 -> currydestroyer27 | F11: =IFERROR(AVERAGE(Data[[#This Row],[alappatjoe]:[currydestroyer27]]), "TBD") -> 3.4 | G11: =IFERROR(_xlfn.STDEV.P(Data[[#This Row],[alappatjoe]:[currydestroyer27]]), "TBD") -> 1.2 | H11: Blue Skies - Revoke Remix | I11: Lenka, REVOKE | J11: 2 | K11: 5 | L11: 4 | M11: 4 | N11: 2 | P11: Pop | Q11: Alternative Pop | R11: =IF(SUM(Data[[#This Row],[alappatjoe]:[currydestroyer27]])>0, COUNTIFS(Data[Date], Data[[#This Row],[Date]], Data[Average], "<"&Data[[#This Row],[Average]]) + COUNTIFS(Data[Date], Data[[#This Row],[Date]], Data[Average], Data[[#This Row],[Average]], Data[STDEV], "<"&Data[[#This Row],[STDEV]])+1, "TBD") -> 4 | S11: 1 | T11: =Data[[#This Row],[Day Rank]]=Data[[#This Row],[W Rank]] -> FALSE
A12: 45460 | C12: {=_xlfn.LET(_xlpm.matches, _xlfn._xlws.FILTER(Data[Poster], (Data[Date]=A12)*(Data[Winner]=TRUE)), IF(ROWS(_xlpm.matches)>1, "TIE", _xlpm.matches))} -> danram | D12: =A12 -> 45460 | E12: =$J$1 -> alappatjoe | F12: =IFERROR(AVERAGE(Data[[#This Row],[alappatjoe]:[currydestroyer27]]), "TBD") -> 4 | G12: =IFERROR(_xlfn.STDEV.P(Data[[#This Row],[alappatjoe]:[currydestroyer27]]), "TBD") -> 1.2649111 | H12: Not My Fault | I12: Renee Rapp, Megan Thee Stallion | J12: 2 | K12: 5 | L12: 5 | M12: 5 | N12: 3 | P12: Pop | Q12: Pop | R12: =IF(SUM(Data[[#This Row],[alappatjoe]:[currydestroyer27]])>0, COUNTIFS(Data[Date], Data[[#This Row],[Date]], Data[Average], "<"&Data[[#This Row],[Average]]) + COUNTIFS(Data[Date], Data[[#This Row],[Date]], Data[Average], Data[[#This Row],[Average]], Data[STDEV], "<"&Data[[#This Row],[STDEV]])+1, "TBD") -> 5 | S12: 1 | T12: =Data[[#This Row],[Day Rank]]=Data[[#This Row],[W Rank]] -> FALSE
D13: =D12 -> 45460 | E13: =$K$1 -> danram | F13: =IFERROR(AVERAGE(Data[[#This Row],[alappatjoe]:[currydestroyer27]]), "TBD") -> 2.2 | G13: =IFERROR(_xlfn.STDEV.P(Data[[#This Row],[alappatjoe]:[currydestroyer27]]), "TBD") -> 0.9797959 | H13: BIRDS OF A FEATHER | I13: Billie Eilish | J13: 1 | K13: 2 | L13: 4 | M13: 2 | N13: 2 | P13: Pop | Q13: Alternative Pop | R13: =IF(SUM(Data[[#This Row],[alappatjoe]:[currydestroyer27]])>0, COUNTIFS(Data[Date], Data[[#This Row],[Date]], Data[Average], "<"&Data[[#This Row],[Average]]) + COUNTIFS(Data[Date], Data[[#This Row],[Date]], Data[Average], Data[[#This Row],[Average]], Data[STDEV], "<"&Data[[#This Row],[STDEV]])+1, "TBD") -> 1 | S13: 1 | T13: =Data[[#This Row],[Day Rank]]=Data[[#This Row],[W Rank]] -> TRUE
D14: =D12 -> 45460 | E14: =$L$1 -> loganworsdell | F14: =IFERROR(AVERAGE(Data[[#This Row],[alappatjoe]:[currydestroyer27]]), "TBD") -> 3.4 | G14: =IFERROR(_xlfn.STDEV.P(Data[[#This Row],[alappatjoe]:[currydestroyer27]]), "TBD") -> 1.0198039 | H14: 2000 chevy malibu | I14: Channel Tres | J14: 3 | K14: 4 | L14: 2 | M14: 3 | N14: 5 | P14: R&B | Q14: Indie soul | R14: =IF(SUM(Data[[#This Row],[alappatjoe]:[currydestroyer27]])>0, COUNTIFS(Data[Date], Data[[#This Row],[Date]], Data[Average], "<"&Data[[#This Row],[Average]]) + COUNTIFS(Data[Date], Data[[#This Row],[Date]], Data[Average], Data[[#This Row],[Average]], Data[STDEV], "<"&Data[[#This Row],[STDEV]])+1, "TBD") -> 4 | S14: 1 | T14: =Data[[#This Row],[Day Rank]]=Data[[#This Row],[W Rank]] -> FALSE
D15: =D12 -> 45460 | E15: =$M$1 -> samuelbattista | F15: =IFERROR(AVERAGE(Data[[#This Row],[alappatjoe]:[currydestroyer27]]), "TBD") -> 2.6 | G15: =IFERROR(_xlfn.STDEV.P(Data[[#This Row],[alappatjoe]:[currydestroyer27]]), "TBD") -> 1.356466 | H15: Hollywood Baby | I15: 100 gecs | J15: 4 | K15: 1 | L15: 3 | M15: 1 | N15: 4 | P15: Pop | Q15: Hyperpop | R15: =IF(SUM(Data[[#This Row],[alappatjoe]:[currydestroyer27]])>0, COUNTIFS(Data[Date], Data[[#This Row],[Date]], Data[Average], "<"&Data[[#This Row],[Average]]) + COUNTIFS(Data[Date], Data[[#This Row],[Date]], Data[Average], Data[[#This Row],[Average]], Data[STDEV], "<"&Data[[#This Row],[STDEV]])+1, "TBD") -> 2 | S15: 1 | T15: =Data[[#This Row],[Day Rank]]=Data[[#This Row],[W Rank]] -> FALSE
D16: =D12 -> 45460 | E16: =$N$1 -> currydestroyer27 | F16: =IFERROR(AVERAGE(Data[[#This Row],[alappatjoe]:[currydestroyer27]]), "TBD") -> 2.8 | G16: =IFERROR(_xlfn.STDEV.P(Data[[#This Row],[alappatjoe]:[currydestroyer27]]), "TBD") -> 1.6 | H16: Bandit | I16: Don Toliver | J16: 5 | K16: 3 | L16: 1 | M16: 4 | N16: 1 | P16: Rap | Q16: Rap | R16: =IF(SUM(Data[[#This Row],[alappatjoe]:[currydestroyer27]])>0, COUNTIFS(Data[Date], Data[[#This Row],[Date]], Data[Average], "<"&Data[[#This Row],[Average]]) + COUNTIFS(Data[Date], Data[[#This Row],[Date]], Data[Average], Data[[#This Row],[Average]], Data[STDEV], "<"&Data[[#This Row],[STDEV]])+1, "TBD") -> 3 | S16: 1 | T16: =Data[[#This Row],[Day Rank]]=Data[[#This Row],[W Rank]] -> FALSE
A17: 45461 | C17: {=_xlfn.LET(_xlpm.matches, _xlfn._xlws.FILTER(Data[Poster], (Data[Date]=A17)*(Data[Winner]=TRUE)), IF(ROWS(_xlpm.matches)>1, "TIE", _xlpm.matches))} -> loganworsdell | D17: =A17 -> 45461 | E17: =$J$1 -> alappatjoe | F17: =IFERROR(AVERAGE(Data[[#This Row],[alappatjoe]:[currydestroyer27]]), "TBD") -> 3.4 | G17: =IFERROR(_xlfn.STDEV.P(Data[[#This Row],[alappatjoe]:[currydestroyer27]]), "TBD") -> 0.8 | H17: Standing Next to You | I17: Jung Kook | J17: 2 | K17: 4 | L17: 4 | M17: 4 | N17: 3 | P17: International | Q17: K-Pop | R17: =IF(SUM(Data[[#This Row],[alappatjoe]:[currydestroyer27]])>0, COUNTIFS(Data[Date], Data[[#This Row],[Date]], Data[Average], "<"&Data[[#This Row],[Average]]) + COUNTIFS(Data[Date], Data[[#This Row],[Date]], Data[Average], Data[[#This Row],[Average]], Data[STDEV], "<"&Data[[#This Row],[STDEV]])+1, "TBD") -> 4 | S17: 1 | T17: =Data[[#This Row],[Day Rank]]=Data[[#This Row],[W Rank]] -> FALSE
D18: =D17 -> 45461 | E18: =$K$1 -> danram | F18: =IFERROR(AVERAGE(Data[[#This Row],[alappatjoe]:[currydestroyer27]]), "TBD") -> 3.2 | G18: =IFERROR(_xlfn.STDEV.P(Data[[#This Row],[alappatjoe]:[currydestroyer27]]), "TBD") -> 0.9797959 | H18: Lonely Rolling Star | I18: Katamari Soundtrack | J18: 5 | K18: 3 | L18: 3 | M18: 3 | N18: 2 | P18: International | Q18: J-Pop | R18: =IF(SUM(Data[[#This Row],[alappatjoe]:[currydestroyer27]])>0, COUNTIFS(Data[Date], Data[[#This Row],[Date]], Data[Average], "<"&Data[[#This Row],[Average]]) + COUNTIFS(Data[Date], Data[[#This Row],[Date]], Data[Average], Data[[#This Row],[Average]], Data[STDEV], "<"&Data[[#This Row],[STDEV]])+1, "TBD") -> 3 | S18: 1 | T18: =Data[[#This Row],[Day Rank]]=Data[[#This Row],[W Rank]] -> FALSE
D19: =D17 -> 45461 | E19: =$L$1 -> loganworsdell | F19: =IFERROR(AVERAGE(Data[[#This Row],[alappatjoe]:[currydestroyer27]]), "TBD") -> 1.8 | G19: =IFERROR(_xlfn.STDEV.P(Data[[#This Row],[alappatjoe]:[currydestroyer27]]), "TBD") -> 0.74833148 | H19: Candle Flame | I19: Jungle, Erick the Architect | J19: 3 | K19: 1 | L19: 2 | M19: 2 | N19: 1 | P19: R&B | Q19: UK Contemporary R&B | R19: =IF(SUM(Data[[#This Row],[alappatjoe]:[currydestroyer27]])>0, COUNTIFS(Data[Date], Data[[#This Row],[Date]], Data[Average], "<"&Data[[#This Row],[Average]]) + COUNTIFS(Data[Date], Data[[#This Row],[Date]], Data[Average], Data[[#This Row],[Average]], Data[STDEV], "<"&Data[[#This Row],[STDEV]])+1, "TBD") -> 1 | S19: 1 | T19: =Data[[#This Row],[Day Rank]]=Data[[#This Row],[W Rank]] -> TRUE
D20: =D17 -> 45461 | E20: =$M$1 -> samuelbattista | F20: =IFERROR(AVERAGE(Data[[#This Row],[alappatjoe]:[currydestroyer27]]), "TBD") -> 2 | G20: =IFERROR(_xlfn.STDEV.P(Data[[#This Row],[alappatjoe]:[currydestroyer27]]), "TBD") -> 1.5491933 | H20: Fly as Me | I20: Silk Sonic | J20: 1 | K20: 2 | L20: 1 | M20: 1 | N20: 5 | P20: R&B | Q20: Neo Soul | R20: =IF(SUM(Data[[#This Row],[alappatjoe]:[currydestroyer27]])>0, COUNTIFS(Data[Date], Data[[#This Row],[Date]], Data[Average], "<"&Data[[#This Row],[Average]]) + COUNTIFS(Data[Date], Data[[#This Row],[Date]], Data[Average], Data[[#This Row],[Average]], Data[STDEV], "<"&Data[[#This Row],[STDEV]])+1, "TBD") -> 2 | S20: 1 | T20: =Data[[#This Row],[Day Rank]]=Data[[#This Row],[W Rank]] -> FALSE
D21: =D17 -> 45461 | E21: =$N$1 -> currydestroyer27 | F21: =IFERROR(AVERAGE(Data[[#This Row],[alappatjoe]:[currydestroyer27]]), "TBD") -> 4.6 | G21: =IFERROR(_xlfn.STDEV.P(Data[[#This Row],[alappatjoe]:[currydestroyer27]]), "TBD") -> 0.48989795 | H21: Ill Mind of Hopsin 8 | I21: Hopsin | J21: 4 | K21: 5 | L21: 5 | M21: 5 | N21: 4 | P21: Rap | Q21: Rap | R21: =IF(SUM(Data[[#This Row],[alappatjoe]:[currydestroyer27]])>0, COUNTIFS(Data[Date], Data[[#This Row],[Date]], Data[Average], "<"&Data[[#This Row],[Average]]) + COUNTIFS(Data[Date], Data[[#This Row],[Date]], Data[Average], Data[[#This Row],[Average]], Data[STDEV], "<"&Data[[#This Row],[STDEV]])+1, "TBD") -> 5 | S21: 1 | T21: =Data[[#This Row],[Day Rank]]=Data[[#This Row],[W Rank]] -> FALSE
A22: 45462 | C22: {=_xlfn.LET(_xlpm.matches, _xlfn._xlws.FILTER(Data[Poster], (Data[Date]=A22)*(Data[Winner]=TRUE)), IF(ROWS(_xlpm.matches)>1, "TIE", _xlpm.matches))} -> currydestroyer27 | D22: =A22 -> 45462 | E22: =$J$1 -> alappatjoe | F22: =IFERROR(AVERAGE(Data[[#This Row],[alappatjoe]:[currydestroyer27]]), "TBD") -> 3 | G22: =IFERROR(_xlfn.STDEV.P(Data[[#This Row],[alappatjoe]:[currydestroyer27]]), "TBD") -> 1.4142136 | H22: ラブ・ドラマティック (Funky Flag Version) | I22: Masayuki Suzuki, Rikka Ihara | J22: 1 | K22: 5 | L22: 2 | M22: 4 | N22: 3 | P22: International | Q22: J-Pop | R22: =IF(SUM(Data[[#This Row],[alappatjoe]:[currydestroyer27]])>0, COUNTIFS(Data[Date], Data[[#This Row],[Date]], Data[Average], "<"&Data[[#This Row],[Average]]) + COUNTIFS(Data[Date], Data[[#This Row],[Date]], Data[Average], Data[[#This Row],[Average]], Data[STDEV], "<"&Data[[#This Row],[STDEV]])+1, "TBD") -> 3 | S22: 1 | T22: =Data[[#This Row],[Day Rank]]=Data[[#This Row],[W Rank]] -> FALSE
D23: =D22 -> 45462 | E23: =$K$1 -> danram | F23: =IFERROR(AVERAGE(Data[[#This Row],[alappatjoe]:[currydestroyer27]]), "TBD") -> 4.2 | G23: =IFERROR(_xlfn.STDEV.P(Data[[#This Row],[alappatjoe]:[currydestroyer27]]), "TBD") -> 0.74833148 | H23: The Wave | I23: SE SO NEON | J23: 4 | K23: 4 | L23: 5 | M23: 3 | N23: 5 | P23: International | Q23: Korean Alternative | R23: =IF(SUM(Data[[#This Row],[alappatjoe]:[currydestroyer27]])>0, COUNTIFS(Data[Date], Data[[#This Row],[Date]], Data[Average], "<"&Data[[#This Row],[Average]]) + COUNTIFS(Data[Date], Data[[#This Row],[Date]], Data[Average], Data[[#This Row],[Average]], Data[STDEV], "<"&Data[[#This Row],[STDEV]])+1, "TBD") -> 5 | S23: 1 | T23: =Data[[#This Row],[Day Rank]]=Data[[#This Row],[W Rank]] -> FALSE
D24: =D22 -> 45462 | E24: =$L$1 -> loganworsdell | F24: =IFERROR(AVERAGE(Data[[#This Row],[alappatjoe]:[currydestroyer27]]), "TBD") -> 4 | G24: =IFERROR(_xlfn.STDEV.P(Data[[#This Row],[alappatjoe]:[currydestroyer27]]), "TBD") -> 0.89442719 | H24: Intentions | I24: Hudson Mohawke | J24: 5 | K24: 3 | L24: 3 | M24: 5 | N24: 4 | P24: Electronic | Q24: Purple Sound | R24: =IF(SUM(Data[[#This Row],[alappatjoe]:[currydestroyer27]])>0, COUNTIFS(Data[Date], Data[[#This Row],[Date]], Data[Average], "<"&Data[[#This Row],[Average]]) + COUNTIFS(Data[Date], Data[[#This Row],[Date]], Data[Average], Data[[#This Row],[Average]], Data[STDEV], "<"&Data[[#This Row],[STDEV]])+1, "TBD") -> 4 | S24: 1 | T24: =Data[[#This Row],[Day Rank]]=Data[[#This Row],[W Rank]] -> FALSE
D25: =D22 -> 45462 | E25: =$M$1 -> samuelbattista | F25: =IFERROR(AVERAGE(Data[[#This Row],[alappatjoe]:[currydestroyer27]]), "TBD") -> 2.4 | G25: =IFERROR(_xlfn.STDEV.P(Data[[#This Row],[alappatjoe]:[currydestroyer27]]), "TBD") -> 1.0198039 | H25: Good Luck, Babe! | I25: Chappell Roan | J25: 3 | K25: 1 | L25: 4 | M25: 2 | N25: 2 | P25: Pop | Q25: Indie Pop | R25: =IF(SUM(Data[[#This Row],[alappatjoe]:[currydestroyer27]])>0, COUNTIFS(Data[Date], Data[[#This Row],[Date]], Data[Average], "<"&Data[[#This Row],[Average]]) + COUNTIFS(Data[Date], Data[[#This Row],[Date]], Data[Average], Data[[#This Row],[Average]], Data[STDEV], "<"&Data[[#This Row],[STDEV]])+1, "TBD") -> 2 | S25: 1 | T25: =Data[[#This Row],[Day Rank]]=Data[[#This Row],[W Rank]] -> FALSE
D26: =D22 -> 45462 | E26: =$N$1 -> currydestroyer27 | F26: =IFERROR(AVERAGE(Data[[#This Row],[alappatjoe]:[currydestroyer27]]), "TBD") -> 1.4 | G26: =IFERROR(_xlfn.STDEV.P(Data[[#This Row],[alappatjoe]:[currydestroyer27]]), "TBD") -> 0.48989795 | H26: Holdin Out for a Hero | I26: Bonnie Tyler | J26: 2 | K26: 2 | L26: 1 | M26: 1 | N26: 1 | P26: Rock | Q26: Rock | R26: =IF(SUM(Data[[#This Row],[alappatjoe]:[currydestroyer27]])>0, COUNTIFS(Data[Date], Data[[#This Row],[Date]], Data[Average], "<"&Data[[#This Row],[Average]]) + COUNTIFS(Data[Date], Data[[#This Row],[Date]], Data[Average], Data[[#This Row],[Average]], Data[STDEV], "<"&Data[[#This Row],[STDEV]])+1, "TBD") -> 1 | S26: 1 | T26: =Data[[#This Row],[Day Rank]]=Data[[#This Row],[W Rank]] -> TRUE
A27: 45463 | C27: {=_xlfn.LET(_xlpm.matches, _xlfn._xlws.FILTER(Data[Poster], (Data[Date]=A27)*(Data[Winner]=TRUE)), IF(ROWS(_xlpm.matches)>1, "TIE", _xlpm.matches))} -> alappatjoe | D27: =A27 -> 45463 | E27: =$J$1 -> alappatjoe | F27: =IFERROR(AVERAGE(Data[[#This Row],[alappatjoe]:[currydestroyer27]]), "TBD") -> 1.8 | G27: =IFERROR(_xlfn.STDEV.P(Data[[#This Row],[alappatjoe]:[currydestroyer27]]), "TBD") -> 0.4 | H27: Espresso | I27: Sabrina Carpenter | J27: 1 | K27: 2 | L27: 2 | M27: 2 | N27: 2 | P27: Pop | Q27: Pop | R27: =IF(SUM(Data[[#This Row],[alappatjoe]:[currydestroyer27]])>0, COUNTIFS(Data[Date], Data[[#This Row],[Date]], Data[Average], "<"&Data[[#This Row],[Average]]) + COUNTIFS(Data[Date], Data[[#This Row],[Date]], Data[Average], Data[[#This Row],[Average]], Data[STDEV], "<"&Data[[#This Row],[STDEV]])+1, "TBD") -> 1 | S27: 1 | T27: =Data[[#This Row],[Day Rank]]=Data[[#This Row],[W Rank]] -> TRUE
D28: =D27 -> 45463 | E28: =$K$1 -> danram | F28: =IFERROR(AVERAGE(Data[[#This Row],[alappatjoe]:[currydestroyer27]]), "TBD") -> 3.4 | G28: =IFERROR(_xlfn.STDEV.P(Data[[#This Row],[alappatjoe]:[currydestroyer27]]), "TBD") -> 1.356466 | H28: Instant Crush | I28: Daft Punk, Julian Casablancas | J28: 4 | K28: 3 | L28: 5 | M28: 4 | N28: 1 | P28: Rock | Q28: Dance-Rock | R28: =IF(SUM(Data[[#This Row],[alappatjoe]:[currydestroyer27]])>0, COUNTIFS(Data[Date], Data[[#This Row],[Date]], Data[Average], "<"&Data[[#This Row],[Average]]) + COUNTIFS(Data[Date], Data[[#This Row],[Date]], Data[Average], Data[[#This Row],[Average]], Data[STDEV], "<"&Data[[#This Row],[STDEV]])+1, "TBD") -> 3 | S28: 1 | T28: =Data[[#This Row],[Day Rank]]=Data[[#This Row],[W Rank]] -> FALSE
D29: =D27 -> 45463 | E29: =$L$1 -> loganworsdell | F29: =IFERROR(AVERAGE(Data[[#This Row],[alappatjoe]:[currydestroyer27]]), "TBD") -> 3.8 | G29: =IFERROR(_xlfn.STDEV.P(Data[[#This Row],[alappatjoe]:[currydestroyer27]]), "TBD") -> 1.1661904 | H29: Genghis Khan | I29: Miike Snow | J29: 2 | K29: 5 | L29: 4 | M29: 3 | N29: 5 | P29: Rock | Q29: Indietornica | R29: =IF(SUM(Data[[#This Row],[alappatjoe]:[currydestroyer27]])>0, COUNTIFS(Data[Date], Data[[#This Row],[Date]], Data[Average], "<"&Data[[#This Row],[Average]]) + COUNTIFS(Data[Date], Data[[#This Row],[Date]], Data[Average], Data[[#This Row],[Average]], Data[STDEV], "<"&Data[[#This Row],[STDEV]])+1, "TBD") -> 5 | S29: 1 | T29: =Data[[#This Row],[Day Rank]]=Data[[#This Row],[W Rank]] -> FALSE
D30: =D27 -> 45463 | E30: =$M$1 -> samuelbattista | F30: =IFERROR(AVERAGE(Data[[#This Row],[alappatjoe]:[currydestroyer27]]), "TBD") -> 2.4 | G30: =IFERROR(_xlfn.STDEV.P(Data[[#This Row],[alappatjoe]:[currydestroyer27]]), "TBD") -> 1.7435596 | H30: Bangarang | I30: Skrillex | J30: 5 | K30: 1 | L30: 1 | M30: 1 | N30: 4 | P30: Electronic | Q30: EDM | R30: =IF(SUM(Data[[#This Row],[alappatjoe]:[currydestroyer27]])>0, COUNTIFS(Data[Date], Data[[#This Row],[Date]], Data[Average], "<"&Data[[#This Row],[Average]]) + COUNTIFS(Data[Date], Data[[#This Row],[Date]], Data[Average], Data[[#This Row],[Average]], Data[STDEV], "<"&Data[[#This Row],[STDEV]])+1, "TBD") -> 2 | S30: 1 | T30: =Data[[#This Row],[Day Rank]]=Data[[#This Row],[W Rank]] -> FALSE
D31: =D27 -> 45463 | E31: =$N$1 -> currydestroyer27 | F31: =IFERROR(AVERAGE(Data[[#This Row],[alappatjoe]:[currydestroyer27]]), "TBD") -> 3.6 | G31: =IFERROR(_xlfn.STDEV.P(Data[[#This Row],[alappatjoe]:[currydestroyer27]]), "TBD") -> 0.8 | H31: Spruce | I31: Tori Kelly, Kim Chaewon | J31: 3 | K31: 4 | L31: 3 | M31: 5 | N31: 3 | P31: Pop | Q31: Pop | R31: =IF(SUM(Data[[#This Row],[alappatjoe]:[currydestroyer27]])>0, COUNTIFS(Data[Date], Data[[#This Row],[Date]], Data[Average], "<"&Data[[#This Row],[Average]]) + COUNTIFS(Data[Date], Data[[#This Row],[Date]], Data[Average], Data[[#This Row],[Average]], Data[STDEV], "<"&Data[[#This Row],[STDEV]])+1, "TBD") -> 4 | S31: 1 | T31: =Data[[#This Row],[Day Rank]]=Data[[#This Row],[W Rank]] -> FALSE
A32: 45467 | C32: {=_xlfn.LET(_xlpm.matches, _xlfn._xlws.FILTER(Data[Poster], (Data[Date]=A32)*(Data[Winner]=TRUE)), IF(ROWS(_xlpm.matches)>1, "TIE", _xlpm.matches))} -> loganworsdell | D32: =A32 -> 45467 | E32: =$J$1 -> alappatjoe | F32: =IFERROR(AVERAGE(Data[[#This Row],[alappatjoe]:[currydestroyer27]]), "TBD") -> 3.8 | G32: =IFERROR(_xlfn.STDEV.P(Data[[#This Row],[alappatjoe]:[currydestroyer27]]), "TBD") -> 0.9797959 | H32: Sher Khul Gaye | I32: Benny Dayal, Shilpa Rao, & more | J32: 2 | K32: 4 | L32: 4 | M32: 5 | N32: 4 | P32: International | Q32: Bollywood | R32: =IF(SUM(Data[[#This Row],[alappatjoe]:[currydestroyer27]])>0, COUNTIFS(Data[Date], Data[[#This Row],[Date]], Data[Average], "<"&Data[[#This Row],[Average]]) + COUNTIFS(Data[Date], Data[[#This Row],[Date]], Data[Average], Data[[#This Row],[Average]], Data[STDEV], "<"&Data[[#This Row],[STDEV]])+1, "TBD") -> 5 | S32: 1 | T32: =Data[[#This Row],[Day Rank]]=Data[[#This Row],[W Rank]] -> FALSE
D33: =D32 -> 45467 | E33: =$K$1 -> danram | F33: =IFERROR(AVERAGE(Data[[#This Row],[alappatjoe]:[currydestroyer27]]), "TBD") -> 2.6 | G33: =IFERROR(_xlfn.STDEV.P(Data[[#This Row],[alappatjoe]:[currydestroyer27]]), "TBD") -> 1.356466 | H33: Virgen | I33: Adolescent's Orquesta | J33: 1 | K33: 2 | L33: 5 | M33: 2 | N33: 3 | P33: International | Q33: Salsa | R33: =IF(SUM(Data[[#This Row],[alappatjoe]:[currydestroyer27]])>0, COUNTIFS(Data[Date], Data[[#This Row],[Date]], Data[Average], "<"&Data[[#This Row],[Average]]) + COUNTIFS(Data[Date], Data[[#This Row],[Date]], Data[Average], Data[[#This Row],[Average]], Data[STDEV], "<"&Data[[#This Row],[STDEV]])+1, "TBD") -> 2 | S33: 1 | T33: =Data[[#This Row],[Day Rank]]=Data[[#This Row],[W Rank]] -> FALSE
D34: =D32 -> 45467 | E34: =$L$1 -> loganworsdell | F34: =IFERROR(AVERAGE(Data[[#This Row],[alappatjoe]:[currydestroyer27]]), "TBD") -> 2.2 | G34: =IFERROR(_xlfn.STDEV.P(Data[[#This Row],[alappatjoe]:[currydestroyer27]]), "TBD") -> 1.6 | H34: Everything Goes On | I34: Porter Robinson, League of Legends | J34: 5 | K34: 1 | L34: 1 | M34: 3 | N34: 1 | P34: Electronic | Q34: Complextro | R34: =IF(SUM(Data[[#This Row],[alappatjoe]:[currydestroyer27]])>0, COUNTIFS(Data[Date], Data[[#This Row],[Date]], Data[Average], "<"&Data[[#This Row],[Average]]) + COUNTIFS(Data[Date], Data[[#This Row],[Date]], Data[Average], Data[[#This Row],[Average]], Data[STDEV], "<"&Data[[#This Row],[STDEV]])+1, "TBD") -> 1 | S34: 1 | T34: =Data[[#This Row],[Day Rank]]=Data[[#This Row],[W Rank]] -> TRUE
D35: =D32 -> 45467 | E35: =$M$1 -> samuelbattista | F35: =IFERROR(AVERAGE(Data[[#This Row],[alappatjoe]:[currydestroyer27]]), "TBD") -> 3 | G35: =IFERROR(_xlfn.STDEV.P(Data[[#This Row],[alappatjoe]:[currydestroyer27]]), "TBD") -> 1.4142136 | H35: High Horse | I35: Kacey Musgraves | J35: 4 | K35: 3 | L35: 2 | M35: 1 | N35: 5 | P35: Country | Q35: Contemporary Country | R35: =IF(SUM(Data[[#This Row],[alappatjoe]:[currydestroyer27]])>0, COUNTIFS(Data[Date], Data[[#This Row],[Date]], Data[Average], "<"&Data[[#This Row],[Average]]) + COUNTIFS(Data[Date], Data[[#This Row],[Date]], Data[Average], Data[[#This Row],[Average]], Data[STDEV], "<"&Data[[#This Row],[STDEV]])+1, "TBD") -> 3 | S35: 1 | T35: =Data[[#This Row],[Day Rank]]=Data[[#This Row],[W Rank]] -> FALSE
D36: =D32 -> 45467 | E36: =$N$1 -> currydestroyer27 | F36: =IFERROR(AVERAGE(Data[[#This Row],[alappatjoe]:[currydestroyer27]]), "TBD") -> 3.4 | G36: =IFERROR(_xlfn.STDEV.P(Data[[#This Row],[alappatjoe]:[currydestroyer27]]), "TBD") -> 1.0198039 | H36: Same Old Love Remix | I36: Selena Gomez, Fetty Wap | J36: 3 | K36: 5 | L36: 3 | M36: 4 | N36: 2 | P36: Pop | Q36: Pop | R36: =IF(SUM(Data[[#This Row],[alappatjoe]:[currydestroyer27]])>0, COUNTIFS(Data[Date], Data[[#This Row],[Date]], Data[Average], "<"&Data[[#This Row],[Average]]) + COUNTIFS(Data[Date], Data[[#This Row],[Date]], Data[Average], Data[[#This Row],[Average]], Data[STDEV], "<"&Data[[#This Row],[STDEV]])+1, "TBD") -> 4 | S36: 1 | T36: =Data[[#This Row],[Day Rank]]=Data[[#This Row],[W Rank]] -> FALSE
A37: 45468 | C37: {=_xlfn.LET(_xlpm.matches, _xlfn._xlws.FILTER(Data[Poster], (Data[Date]=A37)*(Data[Winner]=TRUE)), IF(ROWS(_xlpm.matches)>1, "TIE", _xlpm.matches))} -> currydestroyer27 | D37: =A37 -> 45468 | E37: =$J$1 -> alappatjoe | F37: =IFERROR(AVERAGE(Data[[#This Row],[alappatjoe]:[currydestroyer27]]), "TBD") -> 3.4 | G37: =IFERROR(_xlfn.STDEV.P(Data[[#This Row],[alappatjoe]:[currydestroyer27]]), "TBD") -> 1.6248077 | H37: Brand New World | I37: D-51 | J37: 1 | K37: 4 | L37: 5 | M37: 5 | N37: 2 | P37: International | R37: =IF(SUM(Data[[#This Row],[alappatjoe]:[currydestroyer27]])>0, COUNTIFS(Data[Date], Data[[#This Row],[Date]], Data[Average], "<"&Data[[#This Row],[Average]]) + COUNTIFS(Data[Date], Data[[#This Row],[Date]], Data[Average], Data[[#This Row],[Average]], Data[STDEV], "<"&Data[[#This Row],[STDEV]])+1, "TBD") -> 5 | S37: 1 | T37: =Data[[#This Row],[Day Rank]]=Data[[#This Row],[W Rank]] -> FALSE
D38: =D37 -> 45468 | E38: =$K$1 -> danram | F38: =IFERROR(AVERAGE(Data[[#This Row],[alappatjoe]:[currydestroyer27]]), "TBD") -> 3 | G38: =IFERROR(_xlfn.STDEV.P(Data[[#This Row],[alappatjoe]:[currydestroyer27]]), "TBD") -> 1.2649111 | H38: Psychopomp | I38: Thank You Scientist | J38: 3 | K38: 1 | L38: 3 | M38: 3 | N38: 5 | P38: Rock | Q38: Progressive Rock | R38: =IF(SUM(Data[[#This Row],[alappatjoe]:[currydestroyer27]])>0, COUNTIFS(Data[Date], Data[[#This Row],[Date]], Data[Average], "<"&Data[[#This Row],[Average]]) + COUNTIFS(Data[Date], Data[[#This Row],[Date]], Data[Average], Data[[#This Row],[Average]], Data[STDEV], "<"&Data[[#This Row],[STDEV]])+1, "TBD") -> 3 | S38: 1 | T38: =Data[[#This Row],[Day Rank]]=Data[[#This Row],[W Rank]] -> FALSE
D39: =D37 -> 45468 | E39: =$L$1 -> loganworsdell | F39: =IFERROR(AVERAGE(Data[[#This Row],[alappatjoe]:[currydestroyer27]]), "TBD") -> 3 | G39: =IFERROR(_xlfn.STDEV.P(Data[[#This Row],[alappatjoe]:[currydestroyer27]]), "TBD") -> 0.89442719 | H39: Really good cry | I39: BETWEEN FRIENDS | J39: 4 | K39: 2 | L39: 4 | M39: 2 | N39: 3 | P39: Pop | Q39: Indie Pop | R39: =IF(SUM(Data[[#This Row],[alappatjoe]:[currydestroyer27]])>0, COUNTIFS(Data[Date], Data[[#This Row],[Date]], Data[Average], "<"&Data[[#This Row],[Average]]) + COUNTIFS(Data[Date], Data[[#This Row],[Date]], Data[Average], Data[[#This Row],[Average]], Data[STDEV], "<"&Data[[#This Row],[STDEV]])+1, "TBD") -> 2 | S39: 1 | T39: =Data[[#This Row],[Day Rank]]=Data[[#This Row],[W Rank]] -> FALSE
D40: =D37 -> 45468 | E40: =$M$1 -> samuelbattista | F40: =IFERROR(AVERAGE(Data[[#This Row],[alappatjoe]:[currydestroyer27]]), "TBD") -> 3 | G40: =IFERROR(_xlfn.STDEV.P(Data[[#This Row],[alappatjoe]:[currydestroyer27]]), "TBD") -> 1.4142136 | H40: ABC | I40: Polyphia, Sophia Black | J40: 5 | K40: 3 | L40: 2 | M40: 1 | N40: 4 | P40: Metal | Q40: Progressive Metal | R40: =IF(SUM(Data[[#This Row],[alappatjoe]:[currydestroyer27]])>0, COUNTIFS(Data[Date], Data[[#This Row],[Date]], Data[Average], "<"&Data[[#This Row],[Average]]) + COUNTIFS(Data[Date], Data[[#This Row],[Date]], Data[Average], Data[[#This Row],[Average]], Data[STDEV], "<"&Data[[#This Row],[STDEV]])+1, "TBD") -> 4 | S40: 1 | T40: =Data[[#This Row],[Day Rank]]=Data[[#This Row],[W Rank]] -> FALSE
D41: =D37 -> 45468 | E41: =$N$1 -> currydestroyer27 | F41: =IFERROR(AVERAGE(Data[[#This Row],[alappatjoe]:[currydestroyer27]]), "TBD") -> 2.6 | G41: =IFERROR(_xlfn.STDEV.P(Data[[#This Row],[alappatjoe]:[currydestroyer27]]), "TBD") -> 1.6248077 | H41: Right Now | I41: New Jeans | J41: 2 | K41: 5 | L41: 1 | M41: 4 | N41: 1 | P41: International | Q41: J-Pop | R41: =IF(SUM(Data[[#This Row],[alappatjoe]:[currydestroyer27]])>0, COUNTIFS(Data[Date], Data[[#This Row],[Date]], Data[Average], "<"&Data[[#This Row],[Average]]) + COUNTIFS(Data[Date], Data[[#This Row],[Date]], Data[Average], Data[[#This Row],[Average]], Data[STDEV], "<"&Data[[#This Row],[STDEV]])+1, "TBD") -> 1 | S41: 1 | T41: =Data[[#This Row],[Day Rank]]=Data[[#This Row],[W Rank]] -> TRUE
A42: 45469 | C42: {=_xlfn.LET(_xlpm.matches, _xlfn._xlws.FILTER(Data[Poster], (Data[Date]=A42)*(Data[Winner]=TRUE)), IF(ROWS(_xlpm.matches)>1, "TIE", _xlpm.matches))} -> loganworsdell | D42: =A42 -> 45469 | E42: =$J$1 -> alappatjoe | F42: =IFERROR(AVERAGE(Data[[#This Row],[alappatjoe]:[currydestroyer27]]), "TBD") -> 3.4 | G42: =IFERROR(_xlfn.STDEV.P(Data[[#This Row],[alappatjoe]:[currydestroyer27]]), "TBD") -> 1.356466 | H42: LOST IN PARADISE | I42: ALI, AKLO | J42: 1 | K42: 5 | L42: 4 | M42: 3 | N42: 4 | P42: International | Q42: J-Rap | R42: =IF(SUM(Data[[#This Row],[alappatjoe]:[currydestroyer27]])>0, COUNTIFS(Data[Date], Data[[#This Row],[Date]], Data[Average], "<"&Data[[#This Row],[Average]]) + COUNTIFS(Data[Date], Data[[#This Row],[Date]], Data[Average], Data[[#This Row],[Average]], Data[STDEV], "<"&Data[[#This Row],[STDEV]])+1, "TBD") -> 4 | S42: 1 | T42: =Data[[#This Row],[Day Rank]]=Data[[#This Row],[W Rank]] -> FALSE
D43: =D42 -> 45469 | E43: =$K$1 -> danram | F43: =IFERROR(AVERAGE(Data[[#This Row],[alappatjoe]:[currydestroyer27]]), "TBD") -> 4.8 | G43: =IFERROR(_xlfn.STDEV.P(Data[[#This Row],[alappatjoe]:[currydestroyer27]]), "TBD") -> 0.4 | H43: Mass Critical Error | I43: Sybyr | J43: 5 | K43: 4 | L43: 5 | M43: 5 | N43: 5 | P43: Rap | Q43: Rap | R43: =IF(SUM(Data[[#This Row],[alappatjoe]:[currydestroyer27]])>0, COUNTIFS(Data[Date], Data[[#This Row],[Date]], Data[Average], "<"&Data[[#This Row],[Average]]) + COUNTIFS(Data[Date], Data[[#This Row],[Date]], Data[Average], Data[[#This Row],[Average]], Data[STDEV], "<"&Data[[#This Row],[STDEV]])+1, "TBD") -> 5 | S43: 1 | T43: =Data[[#This Row],[Day Rank]]=Data[[#This Row],[W Rank]] -> FALSE
D44: =D42 -> 45469 | E44: =$L$1 -> loganworsdell | F44: =IFERROR(AVERAGE(Data[[#This Row],[alappatjoe]:[currydestroyer27]]), "TBD") -> 2 | G44: =IFERROR(_xlfn.STDEV.P(Data[[#This Row],[alappatjoe]:[currydestroyer27]]), "TBD") -> 0.89442719 | H44: KLINK | I44: Smino | J44: 3 | K44: 1 | L44: 3 | M44: 2 | N44: 1 | P44: R&B | Q44: Alertnative R&B | R44: =IF(SUM(Data[[#This Row],[alappatjoe]:[currydestroyer27]])>0, COUNTIFS(Data[Date], Data[[#This Row],[Date]], Data[Average], "<"&Data[[#This Row],[Average]]) + COUNTIFS(Data[Date], Data[[#This Row],[Date]], Data[Average], Data[[#This Row],[Average]], Data[STDEV], "<"&Data[[#This Row],[STDEV]])+1, "TBD") -> 1 | S44: 1 | T44: =Data[[#This Row],[Day Rank]]=Data[[#This Row],[W Rank]] -> TRUE
D45: =D42 -> 45469 | E45: =$M$1 -> samuelbattista | F45: =IFERROR(AVERAGE(Data[[#This Row],[alappatjoe]:[currydestroyer27]]), "TBD") -> 2.2 | G45: =IFERROR(_xlfn.STDEV.P(Data[[#This Row],[alappatjoe]:[currydestroyer27]]), "TBD") -> 1.1661904 | H45: Sadie Sorceress | I45: King Gizard & The Lizard Wizard | J45: 4 | K45: 2 | L45: 1 | M45: 1 | N45: 3 | P45: Other | Q45: Neo-Psychedelic | R45: =IF(SUM(Data[[#This Row],[alappatjoe]:[currydestroyer27]])>0, COUNTIFS(Data[Date], Data[[#This Row],[Date]], Data[Average], "<"&Data[[#This Row],[Average]]) + COUNTIFS(Data[Date], Data[[#This Row],[Date]], Data[Average], Data[[#This Row],[Average]], Data[STDEV], "<"&Data[[#This Row],[STDEV]])+1, "TBD") -> 2 | S45: 1 | T45: =Data[[#This Row],[Day Rank]]=Data[[#This Row],[W Rank]] -> FALSE
D46: =D42 -> 45469 | E46: =$N$1 -> currydestroyer27 | F46: =IFERROR(AVERAGE(Data[[#This Row],[alappatjoe]:[currydestroyer27]]), "TBD") -> 2.6 | G46: =IFERROR(_xlfn.STDEV.P(Data[[#This Row],[alappatjoe]:[currydestroyer27]]), "TBD") -> 0.8 | H46: Russian Roulette | I46: Red Velvet | J46: 2 | K46: 3 | L46: 2 | M46: 4 | N46: 2 | P46: International | Q46: K-Pop | R46: =IF(SUM(Data[[#This Row],[alappatjoe]:[currydestroyer27]])>0, COUNTIFS(Data[Date], Data[[#This Row],[Date]], Data[Average], "<"&Data[[#This Row],[Average]]) + COUNTIFS(Data[Date], Data[[#This Row],[Date]], Data[Average], Data[[#This Row],[Average]], Data[STDEV], "<"&Data[[#This Row],[STDEV]])+1, "TBD") -> 3 | S46: 1 | T46: =Data[[#This Row],[Day Rank]]=Data[[#This Row],[W Rank]] -> FALSE
A47: 45470 | C47: {=_xlfn.LET(_xlpm.matches, _xlfn._xlws.FILTER(Data[Poster], (Data[Date]=A47)*(Data[Winner]=TRUE)), IF(ROWS(_xlpm.matches)>1, "TIE", _xlpm.matches))} -> samuelbattista | D47: =A47 -> 45470 | E47: =$J$1 -> alappatjoe | F47: =IFERROR(AVERAGE(Data[[#This Row],[alappatjoe]:[currydestroyer27]]), "TBD") -> 2.8 | G47: =IFERROR(_xlfn.STDEV.P(Data[[#This Row],[alappatjoe]:[currydestroyer27]]), "TBD") -> 1.4696938 | H47: Moanin' | I47: Mingus Big Band | J47: 1 | K47: 2 | L47: 5 | M47: 2 | N47: 4 | P47: Jazz | Q47: Big Band Jazz | R47: =IF(SUM(Data[[#This Row],[alappatjoe]:[currydestroyer27]])>0, COUNTIFS(Data[Date], Data[[#This Row],[Date]], Data[Average], "<"&Data[[#This Row],[Average]]) + COUNTIFS(Data[Date], Data[[#This Row],[Date]], Data[Average], Data[[#This Row],[Average]], Data[STDEV], "<"&Data[[#This Row],[STDEV]])+1, "TBD") -> 4 | S47: 1 | T47: =Data[[#This Row],[Day Rank]]=Data[[#This Row],[W Rank]] -> FALSE | U47: Theme: Hectic
D48: =D47 -> 45470 | E48: =$K$1 -> danram | F48: =IFERROR(AVERAGE(Data[[#This Row],[alappatjoe]:[currydestroyer27]]), "TBD") -> 2.6 | G48: =IFERROR(_xlfn.STDEV.P(Data[[#This Row],[alappatjoe]:[currydestroyer27]]), "TBD") -> 1.9595918 | H48: lost | I48: hkmori | J48: 5 | K48: 1 | L48: 1 | M48: 5 | N48: 1 | P48: Other | Q48: Breakcore | R48: =IF(SUM(Data[[#This Row],[alappatjoe]:[currydestroyer27]])>0, COUNTIFS(Data[Date], Data[[#This Row],[Date]], Data[Average], "<"&Data[[#This Row],[Average]]) + COUNTIFS(Data[Date], Data[[#This Row],[Date]], Data[Average], Data[[#This Row],[Average]], Data[STDEV], "<"&Data[[#This Row],[STDEV]])+1, "TBD") -> 2 | S48: 1 | T48: =Data[[#This Row],[Day Rank]]=Data[[#This Row],[W Rank]] -> FALSE
D49: =D47 -> 45470 | E49: =$L$1 -> loganworsdell | F49: =IFERROR(AVERAGE(Data[[#This Row],[alappatjoe]:[currydestroyer27]]), "TBD") -> 4.2 | G49: =IFERROR(_xlfn.STDEV.P(Data[[#This Row],[alappatjoe]:[currydestroyer27]]), "TBD") -> 0.74833148 | H49: Demons Around | I49: yatashigang | J49: 3 | K49: 5 | L49: 4 | M49: 4 | N49: 5 | P49: Pop | Q49: Gym Phonk | R49: =IF(SUM(Data[[#This Row],[alappatjoe]:[currydestroyer27]])>0, COUNTIFS(Data[Date], Data[[#This Row],[Date]], Data[Average], "<"&Data[[#This Row],[Average]]) + COUNTIFS(Data[Date], Data[[#This Row],[Date]], Data[Average], Data[[#This Row],[Average]], Data[STDEV], "<"&Data[[#This Row],[STDEV]])+1, "TBD") -> 5 | S49: 1 | T49: =Data[[#This Row],[Day Rank]]=Data[[#This Row],[W Rank]] -> FALSE
D50: =D47 -> 45470 | E50: =$M$1 -> samuelbattista | F50: =IFERROR(AVERAGE(Data[[#This Row],[alappatjoe]:[currydestroyer27]]), "TBD") -> 2.6 | G50: =IFERROR(_xlfn.STDEV.P(Data[[#This Row],[alappatjoe]:[currydestroyer27]]), "TBD") -> 1.0198039 | H50: Doritos & Fritos | I50: 100 gecs | J50: 2 | K50: 4 | L50: 3 | M50: 1 | N50: 3 | P50: Pop | Q50: Hyperpop | R50: =IF(SUM(Data[[#This Row],[alappatjoe]:[currydestroyer27]])>0, COUNTIFS(Data[Date], Data[[#This Row],[Date]], Data[Average], "<"&Data[[#This Row],[Average]]) + COUNTIFS(Data[Date], Data[[#This Row],[Date]], Data[Average], Data[[#This Row],[Average]], Data[STDEV], "<"&Data[[#This Row],[STDEV]])+1, "TBD") -> 1 | S50: 1 | T50: =Data[[#This Row],[Day Rank]]=Data[[#This Row],[W Rank]] -> TRUE
D51: =D47 -> 45470 | E51: =$N$1 -> currydestroyer27 | F51: =IFERROR(AVERAGE(Data[[#This Row],[alappatjoe]:[currydestroyer27]]), "TBD") -> 2.8 | G51: =IFERROR(_xlfn.STDEV.P(Data[[#This Row],[alappatjoe]:[currydestroyer27]]), "TBD") -> 0.74833148 | H51: SMOKE IT OFF! | I51: Lumi Athena, jnhygs | J51: 4 | K51: 3 | L51: 2 | M51: 3 | N51: 2 | P51: Other | Q51: Breakcore | R51: =IF(SUM(Data[[#This Row],[alappatjoe]:[currydestroyer27]])>0, COUNTIFS(Data[Date], Data[[#This Row],[Date]], Data[Average], "<"&Data[[#This Row],[Average]]) + COUNTIFS(Data[Date], Data[[#This Row],[Date]], Data[Average], Data[[#This Row],[Average]], Data[STDEV], "<"&Data[[#This Row],[STDEV]])+1, "TBD") -> 3 | S51: 1 | T51: =Data[[#This Row],[Day Rank]]=Data[[#This Row],[W Rank]] -> FALSE
A52: 45474 | C52: {=_xlfn.LET(_xlpm.matches, _xlfn._xlws.FILTER(Data[Poster], (Data[Date]=A52)*(Data[Winner]=TRUE)), IF(ROWS(_xlpm.matches)>1, "TIE", _xlpm.matches))} -> alappatjoe | D52: =A52 -> 45474 | E52: =$J$1 -> alappatjoe | F52: =IFERROR(AVERAGE(Data[[#This Row],[alappatjoe]:[currydestroyer27]]), "TBD") -> 2.6 | G52: =IFERROR(_xlfn.STDEV.P(Data[[#This Row],[alappatjoe]:[currydestroyer27]]), "TBD") -> 1.9595918 | H52: Spain | I52: US Air Force Airmen of Note | J52: 1 | K52: 1 | L52: 5 | M52: 1 | N52: 5 | P52: Jazz | Q52: Big Band Jazz | R52: =IF(SUM(Data[[#This Row],[alappatjoe]:[currydestroyer27]])>0, COUNTIFS(Data[Date], Data[[#This Row],[Date]], Data[Average], "<"&Data[[#This Row],[Average]]) + COUNTIFS(Data[Date], Data[[#This Row],[Date]], Data[Average], Data[[#This Row],[Average]], Data[STDEV], "<"&Data[[#This Row],[STDEV]])+1, "TBD") -> 1 | S52: 1 | T52: =Data[[#This Row],[Day Rank]]=Data[[#This Row],[W Rank]] -> TRUE
D53: =D52 -> 45474 | E53: =$K$1 -> danram | F53: =IFERROR(AVERAGE(Data[[#This Row],[alappatjoe]:[currydestroyer27]]), "TBD") -> 3.2 | G53: =IFERROR(_xlfn.STDEV.P(Data[[#This Row],[alappatjoe]:[currydestroyer27]]), "TBD") -> 1.1661904 | H53: Ski | I53: YSL, Young Thug, Gunna | J53: 4 | K53: 2 | L53: 2 | M53: 5 | N53: 3 | P53: Rap | Q53: Rap | R53: =IF(SUM(Data[[#This Row],[alappatjoe]:[currydestroyer27]])>0, COUNTIFS(Data[Date], Data[[#This Row],[Date]], Data[Average], "<"&Data[[#This Row],[Average]]) + COUNTIFS(Data[Date], Data[[#This Row],[Date]], Data[Average], Data[[#This Row],[Average]], Data[STDEV], "<"&Data[[#This Row],[STDEV]])+1, "TBD") -> 4 | S53: 1 | T53: =Data[[#This Row],[Day Rank]]=Data[[#This Row],[W Rank]] -> FALSE
D54: =D52 -> 45474 | E54: =$L$1 -> loganworsdell | F54: =IFERROR(AVERAGE(Data[[#This Row],[alappatjoe]:[currydestroyer27]]), "TBD") -> 3.6 | G54: =IFERROR(_xlfn.STDEV.P(Data[[#This Row],[alappatjoe]:[currydestroyer27]]), "TBD") -> 1.0198039 | H54: On God | I54: N7, Pwap | J54: 2 | K54: 5 | L54: 3 | M54: 4 | N54: 4 | P54: Rap | Q54: Rap | R54: =IF(SUM(Data[[#This Row],[alappatjoe]:[currydestroyer27]])>0, COUNTIFS(Data[Date], Data[[#This Row],[Date]], Data[Average], "<"&Data[[#This Row],[Average]]) + COUNTIFS(Data[Date], Data[[#This Row],[Date]], Data[Average], Data[[#This Row],[Average]], Data[STDEV], "<"&Data[[#This Row],[STDEV]])+1, "TBD") -> 5 | S54: 1 | T54: =Data[[#This Row],[Day Rank]]=Data[[#This Row],[W Rank]] -> FALSE
D55: =D52 -> 45474 | E55: =$M$1 -> samuelbattista | F55: =IFERROR(AVERAGE(Data[[#This Row],[alappatjoe]:[currydestroyer27]]), "TBD") -> 2.8 | G55: =IFERROR(_xlfn.STDEV.P(Data[[#This Row],[alappatjoe]:[currydestroyer27]]), "TBD") -> 0.74833148 | H55: Ignorance | I55: Paramore | J55: 3 | K55: 3 | L55: 4 | M55: 2 | N55: 2 | P55: Pop | Q55: Pop Punk | R55: =IF(SUM(Data[[#This Row],[alappatjoe]:[currydestroyer27]])>0, COUNTIFS(Data[Date], Data[[#This Row],[Date]], Data[Average], "<"&Data[[#This Row],[Average]]) + COUNTIFS(Data[Date], Data[[#This Row],[Date]], Data[Average], Data[[#This Row],[Average]], Data[STDEV], "<"&Data[[#This Row],[STDEV]])+1, "TBD") -> 2 | S55: 1 | T55: =Data[[#This Row],[Day Rank]]=Data[[#This Row],[W Rank]] -> FALSE
D56: =D52 -> 45474 | E56: =$N$1 -> currydestroyer27 | F56: =IFERROR(AVERAGE(Data[[#This Row],[alappatjoe]:[currydestroyer27]]), "TBD") -> 2.8 | G56: =IFERROR(_xlfn.STDEV.P(Data[[#This Row],[alappatjoe]:[currydestroyer27]]), "TBD") -> 1.6 | H56: You & Me | I56: Jennie | J56: 5 | K56: 4 | L56: 1 | M56: 3 | N56: 1 | P56: Pop | Q56: Pop | R56: =IF(SUM(Data[[#This Row],[alappatjoe]:[currydestroyer27]])>0, COUNTIFS(Data[Date], Data[[#This Row],[Date]], Data[Average], "<"&Data[[#This Row],[Average]]) + COUNTIFS(Data[Date], Data[[#This Row],[Date]], Data[Average], Data[[#This Row],[Average]], Data[STDEV], "<"&Data[[#This Row],[STDEV]])+1, "TBD") -> 3 | S56: 1 | T56: =Data[[#This Row],[Day Rank]]=Data[[#This Row],[W Rank]] -> FALSE
A57: 45475 | C57: {=_xlfn.LET(_xlpm.matches, _xlfn._xlws.FILTER(Data[Poster], (Data[Date]=A57)*(Data[Winner]=TRUE)), IF(ROWS(_xlpm.matches)>1, "TIE", _xlpm.matches))} -> danram | D57: =A57 -> 45475 | E57: =$J$1 -> alappatjoe | F57: =IFERROR(AVERAGE(Data[[#This Row],[alappatjoe]:[currydestroyer27]]), "TBD") -> 3.8 | G57: =IFERROR(_xlfn.STDEV.P(Data[[#This Row],[alappatjoe]:[currydestroyer27]]), "TBD") -> 1.6 | H57: Birdland | I57: Maynard Ferguson | J57: 1 | K57: 5 | L57: 5 | M57: 3 | N57: 5 | P57: Jazz | Q57: Big Band Jazz | R57: =IF(SUM(Data[[#This Row],[alappatjoe]:[currydestroyer27]])>0, COUNTIFS(Data[Date], Data[[#This Row],[Date]], Data[Average], "<"&Data[[#This Row],[Average]]) + COUNTIFS(Data[Date], Data[[#This Row],[Date]], Data[Average], Data[[#This Row],[Average]], Data[STDEV], "<"&Data[[#This Row],[STDEV]])+1, "TBD") -> 5 | S57: 1 | T57: =Data[[#This Row],[Day Rank]]=Data[[#This Row],[W Rank]] -> FALSE
D58: =D57 -> 45475 | E58: =$K$1 -> danram | F58: =IFERROR(AVERAGE(Data[[#This Row],[alappatjoe]:[currydestroyer27]]), "TBD") -> 2.2 | G58: =IFERROR(_xlfn.STDEV.P(Data[[#This Row],[alappatjoe]:[currydestroyer27]]), "TBD") -> 1.4696938 | H58: Stop Signs are Merely Suggestions | I58: Moving Boxes | J58: 5 | K58: 2 | L58: 2 | M58: 1 | N58: 1 | P58: Rock | Q58: Post Pop Punk | R58: =IF(SUM(Data[[#This Row],[alappatjoe]:[currydestroyer27]])>0, COUNTIFS(Data[Date], Data[[#This Row],[Date]], Data[Average], "<"&Data[[#This Row],[Average]]) + COUNTIFS(Data[Date], Data[[#This Row],[Date]], Data[Average], Data[[#This Row],[Average]], Data[STDEV], "<"&Data[[#This Row],[STDEV]])+1, "TBD") -> 1 | S58: 1 | T58: =Data[[#This Row],[Day Rank]]=Data[[#This Row],[W Rank]] -> TRUE
D59: =D57 -> 45475 | E59: =$L$1 -> loganworsdell | F59: =IFERROR(AVERAGE(Data[[#This Row],[alappatjoe]:[currydestroyer27]]), "TBD") -> 2.6 | G59: =IFERROR(_xlfn.STDEV.P(Data[[#This Row],[alappatjoe]:[currydestroyer27]]), "TBD") -> 1.6248077 | H59: Throw Shade | I59: CRUISR | J59: 2 | K59: 1 | L59: 1 | M59: 5 | N59: 4 | P59: Pop | Q59: Indie Poptimism | R59: =IF(SUM(Data[[#This Row],[alappatjoe]:[currydestroyer27]])>0, COUNTIFS(Data[Date], Data[[#This Row],[Date]], Data[Average], "<"&Data[[#This Row],[Average]]) + COUNTIFS(Data[Date], Data[[#This Row],[Date]], Data[Average], Data[[#This Row],[Average]], Data[STDEV], "<"&Data[[#This Row],[STDEV]])+1, "TBD") -> 2 | S59: 1 | T59: =Data[[#This Row],[Day Rank]]=Data[[#This Row],[W Rank]] -> FALSE
D60: =D57 -> 45475 | E60: =$M$1 -> samuelbattista | F60: =IFERROR(AVERAGE(Data[[#This Row],[alappatjoe]:[currydestroyer27]]), "TBD") -> 3.2 | G60: =IFERROR(_xlfn.STDEV.P(Data[[#This Row],[alappatjoe]:[currydestroyer27]]), "TBD") -> 0.74833148 | H60: Interstellar Love | I60: Nine Spark Riots | J60: 4 | K60: 3 | L60: 4 | M60: 2 | N60: 3 | P60: R&B | Q60: Modern Funk | R60: =IF(SUM(Data[[#This Row],[alappatjoe]:[currydestroyer27]])>0, COUNTIFS(Data[Date], Data[[#This Row],[Date]], Data[Average], "<"&Data[[#This Row],[Average]]) + COUNTIFS(Data[Date], Data[[#This Row],[Date]], Data[Average], Data[[#This Row],[Average]], Data[STDEV], "<"&Data[[#This Row],[STDEV]])+1, "TBD") -> 3 | S60: 1 | T60: =Data[[#This Row],[Day Rank]]=Data[[#This Row],[W Rank]] -> FALSE
D61: =D57 -> 45475 | E61: =$N$1 -> currydestroyer27 | F61: =IFERROR(AVERAGE(Data[[#This Row],[alappatjoe]:[currydestroyer27]]), "TBD") -> 3.2 | G61: =IFERROR(_xlfn.STDEV.P(Data[[#This Row],[alappatjoe]:[currydestroyer27]]), "TBD") -> 0.74833148 | H61: Who's Ready for Tomorrow | I61: RAT BOY, IBDY | J61: 3 | K61: 4 | L61: 3 | M61: 4 | N61: 2 | P61: Pop | Q61: Alternative Pop | R61: =IF(SUM(Data[[#This Row],[alappatjoe]:[currydestroyer27]])>0, COUNTIFS(Data[Date], Data[[#This Row],[Date]], Data[Average], "<"&Data[[#This Row],[Average]]) + COUNTIFS(Data[Date], Data[[#This Row],[Date]], Data[Average], Data[[#This Row],[Average]], Data[STDEV], "<"&Data[[#This Row],[STDEV]])+1, "TBD") -> 3 | S61: 1 | T61: =Data[[#This Row],[Day Rank]]=Data[[#This Row],[W Rank]] -> FALSE
A62: 45476 | C62: {=_xlfn.LET(_xlpm.matches, _xlfn._xlws.FILTER(Data[Poster], (Data[Date]=A62)*(Data[Winner]=TRUE)), IF(ROWS(_xlpm.matches)>1, "TIE", _xlpm.matches))} -> alappatjoe | D62: =A62 -> 45476 | E62: =$J$1 -> alappatjoe | F62: =IFERROR(AVERAGE(Data[[#This Row],[alappatjoe]:[currydestroyer27]]), "TBD") -> 1.4 | G62: =IFERROR(_xlfn.STDEV.P(Data[[#This Row],[alappatjoe]:[currydestroyer27]]), "TBD") -> 0.48989795 | H62: specialist | I62: アトラスサウンドチーム | J62: 1 | K62: 2 | L62: 1 | M62: 2 | N62: 1 | P62: Jazz | Q62: VGM Jazz | R62: =IF(SUM(Data[[#This Row],[alappatjoe]:[currydestroyer27]])>0, COUNTIFS(Data[Date], Data[[#This Row],[Date]], Data[Average], "<"&Data[[#This Row],[Average]]) + COUNTIFS(Data[Date], Data[[#This Row],[Date]], Data[Average], Data[[#This Row],[Average]], Data[STDEV], "<"&Data[[#This Row],[STDEV]])+1, "TBD") -> 1 | S62: 1 | T62: =Data[[#This Row],[Day Rank]]=Data[[#This Row],[W Rank]] -> TRUE
D63: =D62 -> 45476 | E63: =$K$1 -> danram | F63: =IFERROR(AVERAGE(Data[[#This Row],[alappatjoe]:[currydestroyer27]]), "TBD") -> 4.4 | G63: =IFERROR(_xlfn.STDEV.P(Data[[#This Row],[alappatjoe]:[currydestroyer27]]), "TBD") -> 0.8 | H63: CRYING IN THE KITCHEN | I63: Dave Blunts | J63: 5 | K63: 5 | L63: 4 | M63: 5 | N63: 3 | P63: Rap | Q63: Rap | R63: =IF(SUM(Data[[#This Row],[alappatjoe]:[currydestroyer27]])>0, COUNTIFS(Data[Date], Data[[#This Row],[Date]], Data[Average], "<"&Data[[#This Row],[Average]]) + COUNTIFS(Data[Date], Data[[#This Row],[Date]], Data[Average], Data[[#This Row],[Average]], Data[STDEV], "<"&Data[[#This Row],[STDEV]])+1, "TBD") -> 5 | S63: 1 | T63: =Data[[#This Row],[Day Rank]]=Data[[#This Row],[W Rank]] -> FALSE
D64: =D62 -> 45476 | E64: =$L$1 -> loganworsdell | F64: =IFERROR(AVERAGE(Data[[#This Row],[alappatjoe]:[currydestroyer27]]), "TBD") -> 4.2 | G64: =IFERROR(_xlfn.STDEV.P(Data[[#This Row],[alappatjoe]:[currydestroyer27]]), "TBD") -> 0.74833148 | H64: Naruto x So What | I64: AniLifts, Mqx, ilysmoke | J64: 4 | K64: 4 | L64: 5 | M64: 3 | N64: 5 | P64: Electronic | Q64: Gym Hardstyle | R64: =IF(SUM(Data[[#This Row],[alappatjoe]:[currydestroyer27]])>0, COUNTIFS(Data[Date], Data[[#This Row],[Date]], Data[Average], "<"&Data[[#This Row],[Average]]) + COUNTIFS(Data[Date], Data[[#This Row],[Date]], Data[Average], Data[[#This Row],[Average]], Data[STDEV], "<"&Data[[#This Row],[STDEV]])+1, "TBD") -> 4 | S64: 1 | T64: =Data[[#This Row],[Day Rank]]=Data[[#This Row],[W Rank]] -> FALSE
D65: =D62 -> 45476 | E65: =$M$1 -> samuelbattista | F65: =IFERROR(AVERAGE(Data[[#This Row],[alappatjoe]:[currydestroyer27]]), "TBD") -> 2.2 | G65: =IFERROR(_xlfn.STDEV.P(Data[[#This Row],[alappatjoe]:[currydestroyer27]]), "TBD") -> 1.1661904 | H65: Rapp Snitch Knishes | I65: MF DOOM | J65: 3 | K65: 1 | L65: 2 | M65: 1 | N65: 4 | P65: Rap | Q65: Rap | R65: =IF(SUM(Data[[#This Row],[alappatjoe]:[currydestroyer27]])>0, COUNTIFS(Data[Date], Data[[#This Row],[Date]], Data[Average], "<"&Data[[#This Row],[Average]]) + COUNTIFS(Data[Date], Data[[#This Row],[Date]], Data[Average], Data[[#This Row],[Average]], Data[STDEV], "<"&Data[[#This Row],[STDEV]])+1, "TBD") -> 2 | S65: 1 | T65: =Data[[#This Row],[Day Rank]]=Data[[#This Row],[W Rank]] -> FALSE
D66: =D62 -> 45476 | E66: =$N$1 -> currydestroyer27 | F66: =IFERROR(AVERAGE(Data[[#This Row],[alappatjoe]:[currydestroyer27]]), "TBD") -> 2.8 | G66: =IFERROR(_xlfn.STDEV.P(Data[[#This Row],[alappatjoe]:[currydestroyer27]]), "TBD") -> 0.74833148 | H66: Last Surprise | I66: Lyn | J66: 2 | K66: 3 | L66: 3 | M66: 4 | N66: 2 | P66: Rock | Q66: Funk Rock | R66: =IF(SUM(Data[[#This Row],[alappatjoe]:[currydestroyer27]])>0, COUNTIFS(Data[Date], Data[[#This Row],[Date]], Data[Average], "<"&Data[[#This Row],[Average]]) + COUNTIFS(Data[Date], Data[[#This Row],[Date]], Data[Average], Data[[#This Row],[Average]], Data[STDEV], "<"&Data[[#This Row],[STDEV]])+1, "TBD") -> 3 | S66: 1 | T66: =Data[[#This Row],[Day Rank]]=Data[[#This Row],[W Rank]] -> FALSE
A67: 45477 | C67: {=_xlfn.LET(_xlpm.matches, _xlfn._xlws.FILTER(Data[Poster], (Data[Date]=A67)*(Data[Winner]=TRUE)), IF(ROWS(_xlpm.matches)>1, "TIE", _xlpm.matches))} -> loganworsdell | D67: =A67 -> 45477 | E67: =$J$1 -> alappatjoe | F67: =IFERROR(AVERAGE(Data[[#This Row],[alappatjoe]:[currydestroyer27]]), "TBD") -> 3.8 | G67: =IFERROR(_xlfn.STDEV.P(Data[[#This Row],[alappatjoe]:[currydestroyer27]]), "TBD") -> 1.4696938 | H67: Life Will Change | I67: Lyn | J67: 1 | K67: 5 | L67: 4 | M67: 4 | N67: 5 | P67: Other | Q67: VGM | R67: =IF(SUM(Data[[#This Row],[alappatjoe]:[currydestroyer27]])>0, COUNTIFS(Data[Date], Data[[#This Row],[Date]], Data[Average], "<"&Data[[#This Row],[Average]]) + COUNTIFS(Data[Date], Data[[#This Row],[Date]], Data[Average], Data[[#This Row],[Average]], Data[STDEV], "<"&Data[[#This Row],[STDEV]])+1, "TBD") -> 5 | S67: 1 | T67: =Data[[#This Row],[Day Rank]]=Data[[#This Row],[W Rank]] -> FALSE | U67: One day early
D68: =D67 -> 45477 | E68: =$K$1 -> danram | F68: =IFERROR(AVERAGE(Data[[#This Row],[alappatjoe]:[currydestroyer27]]), "TBD") -> 3.6 | G68: =IFERROR(_xlfn.STDEV.P(Data[[#This Row],[alappatjoe]:[currydestroyer27]]), "TBD") -> 1.356466 | H68: Vem pra ser meu refrao | I68: Reinaldo | J68: 5 | K68: 2 | L68: 5 | M68: 2 | N68: 4 | P68: International | Q68: Samba | R68: =IF(SUM(Data[[#This Row],[alappatjoe]:[currydestroyer27]])>0, COUNTIFS(Data[Date], Data[[#This Row],[Date]], Data[Average], "<"&Data[[#This Row],[Average]]) + COUNTIFS(Data[Date], Data[[#This Row],[Date]], Data[Average], Data[[#This Row],[Average]], Data[STDEV], "<"&Data[[#This Row],[STDEV]])+1, "TBD") -> 4 | S68: 1 | T68: =Data[[#This Row],[Day Rank]]=Data[[#This Row],[W Rank]] -> FALSE
D69: =D67 -> 45477 | E69: =$L$1 -> loganworsdell | F69: =IFERROR(AVERAGE(Data[[#This Row],[alappatjoe]:[currydestroyer27]]), "TBD") -> 2.4 | G69: =IFERROR(_xlfn.STDEV.P(Data[[#This Row],[alappatjoe]:[currydestroyer27]]), "TBD") -> 0.8 | H69: Otaku Hot Girl | I69: Megan Thee Stallion | J69: 3 | K69: 1 | L69: 2 | M69: 3 | N69: 3 | P69: Rap | Q69: Houston Rap | R69: =IF(SUM(Data[[#This Row],[alappatjoe]:[currydestroyer27]])>0, COUNTIFS(Data[Date], Data[[#This Row],[Date]], Data[Average], "<"&Data[[#This Row],[Average]]) + COUNTIFS(Data[Date], Data[[#This Row],[Date]], Data[Average], Data[[#This Row],[Average]], Data[STDEV], "<"&Data[[#This Row],[STDEV]])+1, "TBD") -> 1 | S69: 1 | T69: =Data[[#This Row],[Day Rank]]=Data[[#This Row],[W Rank]] -> TRUE
D70: =D67 -> 45477 | E70: =$M$1 -> samuelbattista | F70: =IFERROR(AVERAGE(Data[[#This Row],[alappatjoe]:[currydestroyer27]]), "TBD") -> 2.4 | G70: =IFERROR(_xlfn.STDEV.P(Data[[#This Row],[alappatjoe]:[currydestroyer27]]), "TBD") -> 1.356466 | H70: BABY SAID | I70: Maneskin | J70: 4 | K70: 4 | L70: 1 | M70: 1 | N70: 2 | P70: Rock | Q70: Rock | R70: =IF(SUM(Data[[#This Row],[alappatjoe]:[currydestroyer27]])>0, COUNTIFS(Data[Date], Data[[#This Row],[Date]], Data[Average], "<"&Data[[#This Row],[Average]]) + COUNTIFS(Data[Date], Data[[#This Row],[Date]], Data[Average], Data[[#This Row],[Average]], Data[STDEV], "<"&Data[[#This Row],[STDEV]])+1, "TBD") -> 2 | S70: 1 | T70: =Data[[#This Row],[Day Rank]]=Data[[#This Row],[W Rank]] -> FALSE
D71: =D67 -> 45477 | E71: =$N$1 -> currydestroyer27 | F71: =IFERROR(AVERAGE(Data[[#This Row],[alappatjoe]:[currydestroyer27]]), "TBD") -> 2.8 | G71: =IFERROR(_xlfn.STDEV.P(Data[[#This Row],[alappatjoe]:[currydestroyer27]]), "TBD") -> 1.3266499 | H71: Number One - Bankai | I71: Shiro Sagisu, Hazel Fernandes | J71: 2 | K71: 3 | L71: 3 | M71: 5 | N71: 1 | P71: Rock | Q71: Funk Rock | R71: =IF(SUM(Data[[#This Row],[alappatjoe]:[currydestroyer27]])>0, COUNTIFS(Data[Date], Data[[#This Row],[Date]], Data[Average], "<"&Data[[#This Row],[Average]]) + COUNTIFS(Data[Date], Data[[#This Row],[Date]], Data[Average], Data[[#This Row],[Average]], Data[STDEV], "<"&Data[[#This Row],[STDEV]])+1, "TBD") -> 3 | S71: 1 | T71: =Data[[#This Row],[Day Rank]]=Data[[#This Row],[W Rank]] -> FALSE
A72: 45481 | C72: {=_xlfn.LET(_xlpm.matches, _xlfn._xlws.FILTER(Data[Poster], (Data[Date]=A72)*(Data[Winner]=TRUE)), IF(ROWS(_xlpm.matches)>1, "TIE", _xlpm.matches))} -> currydestroyer27 | D72: =A72 -> 45481 | E72: =$J$1 -> alappatjoe | F72: =IFERROR(AVERAGE(Data[[#This Row],[alappatjoe]:[currydestroyer27]]), "TBD") -> 2.6 | G72: =IFERROR(_xlfn.STDEV.P(Data[[#This Row],[alappatjoe]:[currydestroyer27]]), "TBD") -> 1.496663 | H72: Plastic Love | I72: Friday Night Plans | J72: 1 | K72: 3 | L72: 5 | M72: 1 | N72: 3 | P72: International | Q72: J-Pop | R72: =IF(SUM(Data[[#This Row],[alappatjoe]:[currydestroyer27]])>0, COUNTIFS(Data[Date], Data[[#This Row],[Date]], Data[Average], "<"&Data[[#This Row],[Average]]) + COUNTIFS(Data[Date], Data[[#This Row],[Date]], Data[Average], Data[[#This Row],[Average]], Data[STDEV], "<"&Data[[#This Row],[STDEV]])+1, "TBD") -> 3 | S72: 1 | T72: =Data[[#This Row],[Day Rank]]=Data[[#This Row],[W Rank]] -> FALSE
D73: =D72 -> 45481 | E73: =$K$1 -> danram | F73: =IFERROR(AVERAGE(Data[[#This Row],[alappatjoe]:[currydestroyer27]]), "TBD") -> 4 | G73: =IFERROR(_xlfn.STDEV.P(Data[[#This Row],[alappatjoe]:[currydestroyer27]]), "TBD") -> 1.0954451 | H73: Molasses | I73: Hiatus Kaiyote | J73: 4 | K73: 2 | L73: 4 | M73: 5 | N73: 5 | P73: Rock | Q73: Jazz Funk | R73: =IF(SUM(Data[[#This Row],[alappatjoe]:[currydestroyer27]])>0, COUNTIFS(Data[Date], Data[[#This Row],[Date]], Data[Average], "<"&Data[[#This Row],[Average]]) + COUNTIFS(Data[Date], Data[[#This Row],[Date]], Data[Average], Data[[#This Row],[Average]], Data[STDEV], "<"&Data[[#This Row],[STDEV]])+1, "TBD") -> 5 | S73: 1 | T73: =Data[[#This Row],[Day Rank]]=Data[[#This Row],[W Rank]] -> FALSE
D74: =D72 -> 45481 | E74: =$L$1 -> loganworsdell | F74: =IFERROR(AVERAGE(Data[[#This Row],[alappatjoe]:[currydestroyer27]]), "TBD") -> 2.6 | G74: =IFERROR(_xlfn.STDEV.P(Data[[#This Row],[alappatjoe]:[currydestroyer27]]), "TBD") -> 0.8 | H74: Papaoutai | I74: Stromae | J74: 2 | K74: 4 | L74: 2 | M74: 3 | N74: 2 | P74: International | Q74: Belgian Pop | R74: =IF(SUM(Data[[#This Row],[alappatjoe]:[currydestroyer27]])>0, COUNTIFS(Data[Date], Data[[#This Row],[Date]], Data[Average], "<"&Data[[#This Row],[Average]]) + COUNTIFS(Data[Date], Data[[#This Row],[Date]], Data[Average], Data[[#This Row],[Average]], Data[STDEV], "<"&Data[[#This Row],[STDEV]])+1, "TBD") -> 2 | S74: 1 | T74: =Data[[#This Row],[Day Rank]]=Data[[#This Row],[W Rank]] -> FALSE
D75: =D72 -> 45481 | E75: =$M$1 -> samuelbattista | F75: =IFERROR(AVERAGE(Data[[#This Row],[alappatjoe]:[currydestroyer27]]), "TBD") -> 3.8 | G75: =IFERROR(_xlfn.STDEV.P(Data[[#This Row],[alappatjoe]:[currydestroyer27]]), "TBD") -> 1.1661904 | H75: End of Beginning | I75: Djo | J75: 5 | K75: 5 | L75: 3 | M75: 2 | N75: 4 | P75: Pop | Q75: Psychedelic Pop | R75: =IF(SUM(Data[[#This Row],[alappatjoe]:[currydestroyer27]])>0, COUNTIFS(Data[Date], Data[[#This Row],[Date]], Data[Average], "<"&Data[[#This Row],[Average]]) + COUNTIFS(Data[Date], Data[[#This Row],[Date]], Data[Average], Data[[#This Row],[Average]], Data[STDEV], "<"&Data[[#This Row],[STDEV]])+1, "TBD") -> 4 | S75: 1 | T75: =Data[[#This Row],[Day Rank]]=Data[[#This Row],[W Rank]] -> FALSE
D76: =D72 -> 45481 | E76: =$N$1 -> currydestroyer27 | F76: =IFERROR(AVERAGE(Data[[#This Row],[alappatjoe]:[currydestroyer27]]), "TBD") -> 2 | G76: =IFERROR(_xlfn.STDEV.P(Data[[#This Row],[alappatjoe]:[currydestroyer27]]), "TBD") -> 1.2649111 | H76: Chasing The Sun | I76: The Wanted | J76: 3 | K76: 1 | L76: 1 | M76: 4 | N76: 1 | P76: Pop | Q76: Pop | R76: =IF(SUM(Data[[#This Row],[alappatjoe]:[currydestroyer27]])>0, COUNTIFS(Data[Date], Data[[#This Row],[Date]], Data[Average], "<"&Data[[#This Row],[Average]]) + COUNTIFS(Data[Date], Data[[#This Row],[Date]], Data[Average], Data[[#This Row],[Average]], Data[STDEV], "<"&Data[[#This Row],[STDEV]])+1, "TBD") -> 1 | S76: 1 | T76: =Data[[#This Row],[Day Rank]]=Data[[#This Row],[W Rank]] -> TRUE
A77: 45482 | C77: {=_xlfn.LET(_xlpm.matches, _xlfn._xlws.FILTER(Data[Poster], (Data[Date]=A77)*(Data[Winner]=TRUE)), IF(ROWS(_xlpm.matches)>1, "TIE", _xlpm.matches))} -> loganworsdell | D77: =A77 -> 45482 | E77: =$J$1 -> alappatjoe | F77: =IFERROR(AVERAGE(Data[[#This Row],[alappatjoe]:[currydestroyer27]]), "TBD") -> 3.8 | G77: =IFERROR(_xlfn.STDEV.P(Data[[#This Row],[alappatjoe]:[currydestroyer27]]), "TBD") -> 0.9797959 | H77: Kimijyanakya Damemitai | I77: Masayoshi Oishi | J77: 2 | K77: 4 | L77: 4 | M77: 5 | N77: 4 | P77: International | Q77: Anime Rock | R77: =IF(SUM(Data[[#This Row],[alappatjoe]:[currydestroyer27]])>0, COUNTIFS(Data[Date], Data[[#This Row],[Date]], Data[Average], "<"&Data[[#This Row],[Average]]) + COUNTIFS(Data[Date], Data[[#This Row],[Date]], Data[Average], Data[[#This Row],[Average]], Data[STDEV], "<"&Data[[#This Row],[STDEV]])+1, "TBD") -> 5 | S77: 1 | T77: =Data[[#This Row],[Day Rank]]=Data[[#This Row],[W Rank]] -> FALSE
D78: =D77 -> 45482 | E78: =$K$1 -> danram | F78: =IFERROR(AVERAGE(Data[[#This Row],[alappatjoe]:[currydestroyer27]]), "TBD") -> 2.8 | G78: =IFERROR(_xlfn.STDEV.P(Data[[#This Row],[alappatjoe]:[currydestroyer27]]), "TBD") -> 1.3266499 | H78: Impulse | I78: An Endless Sporadic | J78: 5 | K78: 1 | L78: 3 | M78: 2 | N78: 3 | P78: Rock | Q78: Progressive Metal | R78: =IF(SUM(Data[[#This Row],[alappatjoe]:[currydestroyer27]])>0, COUNTIFS(Data[Date], Data[[#This Row],[Date]], Data[Average], "<"&Data[[#This Row],[Average]]) + COUNTIFS(Data[Date], Data[[#This Row],[Date]], Data[Average], Data[[#This Row],[Average]], Data[STDEV], "<"&Data[[#This Row],[STDEV]])+1, "TBD") -> 3 | S78: 1 | T78: =Data[[#This Row],[Day Rank]]=Data[[#This Row],[W Rank]] -> FALSE
D79: =D77 -> 45482 | E79: =$L$1 -> loganworsdell | F79: =IFERROR(AVERAGE(Data[[#This Row],[alappatjoe]:[currydestroyer27]]), "TBD") -> 2.4 | G79: =IFERROR(_xlfn.STDEV.P(Data[[#This Row],[alappatjoe]:[currydestroyer27]]), "TBD") -> 1.496663 | H79: DNA | I79: Ghali | J79: 1 | K79: 5 | L79: 1 | M79: 3 | N79: 2 | P79: International | Q79: Pop Italiano | R79: =IF(SUM(Data[[#This Row],[alappatjoe]:[currydestroyer27]])>0, COUNTIFS(Data[Date], Data[[#This Row],[Date]], Data[Average], "<"&Data[[#This Row],[Average]]) + COUNTIFS(Data[Date], Data[[#This Row],[Date]], Data[Average], Data[[#This Row],[Average]], Data[STDEV], "<"&Data[[#This Row],[STDEV]])+1, "TBD") -> 1 | S79: 1 | T79: =Data[[#This Row],[Day Rank]]=Data[[#This Row],[W Rank]] -> TRUE
D80: =D77 -> 45482 | E80: =$M$1 -> samuelbattista | F80: =IFERROR(AVERAGE(Data[[#This Row],[alappatjoe]:[currydestroyer27]]), "TBD") -> 3.2 | G80: =IFERROR(_xlfn.STDEV.P(Data[[#This Row],[alappatjoe]:[currydestroyer27]]), "TBD") -> 1.6 | H80: From The Start | I80: Laufey | J80: 3 | K80: 2 | L80: 5 | M80: 1 | N80: 5 | P80: Pop | Q80: Jazz Pop | R80: =IF(SUM(Data[[#This Row],[alappatjoe]:[currydestroyer27]])>0, COUNTIFS(Data[Date], Data[[#This Row],[Date]], Data[Average], "<"&Data[[#This Row],[Average]]) + COUNTIFS(Data[Date], Data[[#This Row],[Date]], Data[Average], Data[[#This Row],[Average]], Data[STDEV], "<"&Data[[#This Row],[STDEV]])+1, "TBD") -> 4 | S80: 1 | T80: =Data[[#This Row],[Day Rank]]=Data[[#This Row],[W Rank]] -> FALSE
D81: =D77 -> 45482 | E81: =$N$1 -> currydestroyer27 | F81: =IFERROR(AVERAGE(Data[[#This Row],[alappatjoe]:[currydestroyer27]]), "TBD") -> 2.8 | G81: =IFERROR(_xlfn.STDEV.P(Data[[#This Row],[alappatjoe]:[currydestroyer27]]), "TBD") -> 1.1661904 | H81: Hanabi | I81: Ikimonogakari | J81: 4 | K81: 3 | L81: 2 | M81: 4 | N81: 1 | P81: International | Q81: J-Pop | R81: =IF(SUM(Data[[#This Row],[alappatjoe]:[currydestroyer27]])>0, COUNTIFS(Data[Date], Data[[#This Row],[Date]], Data[Average], "<"&Data[[#This Row],[Average]]) + COUNTIFS(Data[Date], Data[[#This Row],[Date]], Data[Average], Data[[#This Row],[Average]], Data[STDEV], "<"&Data[[#This Row],[STDEV]])+1, "TBD") -> 2 | S81: 1 | T81: =Data[[#This Row],[Day Rank]]=Data[[#This Row],[W Rank]] -> FALSE
A82: 45483 | C82: {=_xlfn.LET(_xlpm.matches, _xlfn._xlws.FILTER(Data[Poster], (Data[Date]=A82)*(Data[Winner]=TRUE)), IF(ROWS(_xlpm.matches)>1, "TIE", _xlpm.matches))} -> currydestroyer27 | D82: =A82 -> 45483 | E82: =$J$1 -> alappatjoe | F82: =IFERROR(AVERAGE(Data[[#This Row],[alappatjoe]:[currydestroyer27]]), "TBD") -> 3.4 | G82: =IFERROR(_xlfn.STDEV.P(Data[[#This Row],[alappatjoe]:[currydestroyer27]]), "TBD") -> 1.6248077 | H82: あの空の向こうがわへ | I82: Junk Fujiyama | J82: 1 | K82: 5 | L82: 4 | M82: 5 | N82: 2 | P82: International | Q82: J-Pop | R82: =IF(SUM(Data[[#This Row],[alappatjoe]:[currydestroyer27]])>0, COUNTIFS(Data[Date], Data[[#This Row],[Date]], Data[Average], "<"&Data[[#This Row],[Average]]) + COUNTIFS(Data[Date], Data[[#This Row],[Date]], Data[Average], Data[[#This Row],[Average]], Data[STDEV], "<"&Data[[#This Row],[STDEV]])+1, "TBD") -> 3 | S82: 1 | T82: =Data[[#This Row],[Day Rank]]=Data[[#This Row],[W Rank]] -> FALSE
D83: =D82 -> 45483 | E83: =$K$1 -> danram | F83: =IFERROR(AVERAGE(Data[[#This Row],[alappatjoe]:[currydestroyer27]]), "TBD") -> 2.4 | G83: =IFERROR(_xlfn.STDEV.P(Data[[#This Row],[alappatjoe]:[currydestroyer27]]), "TBD") -> 1.496663 | H83: Electronic Girl | I83: Chinese Football | J83: 5 | K83: 1 | L83: 1 | M83: 2 | N83: 3 | P83: International | Q83: Indie Rock | R83: =IF(SUM(Data[[#This Row],[alappatjoe]:[currydestroyer27]])>0, COUNTIFS(Data[Date], Data[[#This Row],[Date]], Data[Average], "<"&Data[[#This Row],[Average]]) + COUNTIFS(Data[Date], Data[[#This Row],[Date]], Data[Average], Data[[#This Row],[Average]], Data[STDEV], "<"&Data[[#This Row],[STDEV]])+1, "TBD") -> 2 | S83: 1 | T83: =Data[[#This Row],[Day Rank]]=Data[[#This Row],[W Rank]] -> FALSE
D84: =D82 -> 45483 | E84: =$L$1 -> loganworsdell | F84: =IFERROR(AVERAGE(Data[[#This Row],[alappatjoe]:[currydestroyer27]]), "TBD") -> 3.8 | G84: =IFERROR(_xlfn.STDEV.P(Data[[#This Row],[alappatjoe]:[currydestroyer27]]), "TBD") -> 0.74833148 | H84: Waves Wandering | I84: EggPlantEgg | J84: 3 | K84: 3 | L84: 5 | M84: 4 | N84: 4 | P84: International | Q84: Mandopop | R84: =IF(SUM(Data[[#This Row],[alappatjoe]:[currydestroyer27]])>0, COUNTIFS(Data[Date], Data[[#This Row],[Date]], Data[Average], "<"&Data[[#This Row],[Average]]) + COUNTIFS(Data[Date], Data[[#This Row],[Date]], Data[Average], Data[[#This Row],[Average]], Data[STDEV], "<"&Data[[#This Row],[STDEV]])+1, "TBD") -> 5 | S84: 1 | T84: =Data[[#This Row],[Day Rank]]=Data[[#This Row],[W Rank]] -> FALSE
D85: =D82 -> 45483 | E85: =$M$1 -> samuelbattista | F85: =IFERROR(AVERAGE(Data[[#This Row],[alappatjoe]:[currydestroyer27]]), "TBD") -> 3.6 | G85: =IFERROR(_xlfn.STDEV.P(Data[[#This Row],[alappatjoe]:[currydestroyer27]]), "TBD") -> 1.0198039 | H85: Punk Tactics | I85: Joey Valence & Brae | J85: 4 | K85: 4 | L85: 2 | M85: 3 | N85: 5 | P85: Rap | Q85: Rap Rock | R85: =IF(SUM(Data[[#This Row],[alappatjoe]:[currydestroyer27]])>0, COUNTIFS(Data[Date], Data[[#This Row],[Date]], Data[Average], "<"&Data[[#This Row],[Average]]) + COUNTIFS(Data[Date], Data[[#This Row],[Date]], Data[Average], Data[[#This Row],[Average]], Data[STDEV], "<"&Data[[#This Row],[STDEV]])+1, "TBD") -> 4 | S85: 1 | T85: =Data[[#This Row],[Day Rank]]=Data[[#This Row],[W Rank]] -> FALSE
D86: =D82 -> 45483 | E86: =$N$1 -> currydestroyer27 | F86: =IFERROR(AVERAGE(Data[[#This Row],[alappatjoe]:[currydestroyer27]]), "TBD") -> 1.8 | G86: =IFERROR(_xlfn.STDEV.P(Data[[#This Row],[alappatjoe]:[currydestroyer27]]), "TBD") -> 0.74833148 | H86: Great Escape | I86: Cinema Staff | J86: 2 | K86: 2 | L86: 3 | M86: 1 | N86: 1 | P86: International | Q86: Japanese Alternative Rock | R86: =IF(SUM(Data[[#This Row],[alappatjoe]:[currydestroyer27]])>0, COUNTIFS(Data[Date], Data[[#This Row],[Date]], Data[Average], "<"&Data[[#This Row],[Average]]) + COUNTIFS(Data[Date], Data[[#This Row],[Date]], Data[Average], Data[[#This Row],[Average]], Data[STDEV], "<"&Data[[#This Row],[STDEV]])+1, "TBD") -> 1 | S86: 1 | T86: =Data[[#This Row],[Day Rank]]=Data[[#This Row],[W Rank]] -> TRUE
A87: 45484 | C87: {=_xlfn.LET(_xlpm.matches, _xlfn._xlws.FILTER(Data[Poster], (Data[Date]=A87)*(Data[Winner]=TRUE)), IF(ROWS(_xlpm.matches)>1, "TIE", _xlpm.matches))} -> samuelbattista | D87: =A87 -> 45484 | E87: =$J$1 -> alappatjoe | F87: =IFERROR(AVERAGE(Data[[#This Row],[alappatjoe]:[currydestroyer27]]), "TBD") -> 3 | G87: =IFERROR(_xlfn.STDEV.P(Data[[#This Row],[alappatjoe]:[currydestroyer27]]), "TBD") -> 1.7888544 | H87: The Greatest | I87: Sia, Kendrick Lamar | J87: 1 | K87: 5 | L87: 3 | M87: 5 | N87: 1 | P87: Pop | Q87: Pop | R87: =IF(SUM(Data[[#This Row],[alappatjoe]:[currydestroyer27]])>0, COUNTIFS(Data[Date], Data[[#This Row],[Date]], Data[Average], "<"&Data[[#This Row],[Average]]) + COUNTIFS(Data[Date], Data[[#This Row],[Date]], Data[Average], Data[[#This Row],[Average]], Data[STDEV], "<"&Data[[#This Row],[STDEV]])+1, "TBD") -> 3 | S87: 1 | T87: =Data[[#This Row],[Day Rank]]=Data[[#This Row],[W Rank]] -> FALSE | U87: Theme: 2016
D88: =D87 -> 45484 | E88: =$K$1 -> danram | F88: =IFERROR(AVERAGE(Data[[#This Row],[alappatjoe]:[currydestroyer27]]), "TBD") -> 3 | G88: =IFERROR(_xlfn.STDEV.P(Data[[#This Row],[alappatjoe]:[currydestroyer27]]), "TBD") -> 1.6733201 | H88: Finish Line / Drown | I88: Chance the Rapper | J88: 2 | K88: 1 | L88: 5 | M88: 2 | N88: 5 | P88: Rap | Q88: Rap | R88: =IF(SUM(Data[[#This Row],[alappatjoe]:[currydestroyer27]])>0, COUNTIFS(Data[Date], Data[[#This Row],[Date]], Data[Average], "<"&Data[[#This Row],[Average]]) + COUNTIFS(Data[Date], Data[[#This Row],[Date]], Data[Average], Data[[#This Row],[Average]], Data[STDEV], "<"&Data[[#This Row],[STDEV]])+1, "TBD") -> 2 | S88: 1 | T88: =Data[[#This Row],[Day Rank]]=Data[[#This Row],[W Rank]] -> FALSE
D89: =D87 -> 45484 | E89: =$L$1 -> loganworsdell | F89: =IFERROR(AVERAGE(Data[[#This Row],[alappatjoe]:[currydestroyer27]]), "TBD") -> 3.4 | G89: =IFERROR(_xlfn.STDEV.P(Data[[#This Row],[alappatjoe]:[currydestroyer27]]), "TBD") -> 0.8 | H89: Lavender | I89: Two Door Cinema Club | J89: 4 | K89: 3 | L89: 2 | M89: 4 | N89: 4 | P89: Rock | Q89: Indietronica | R89: =IF(SUM(Data[[#This Row],[alappatjoe]:[currydestroyer27]])>0, COUNTIFS(Data[Date], Data[[#This Row],[Date]], Data[Average], "<"&Data[[#This Row],[Average]]) + COUNTIFS(Data[Date], Data[[#This Row],[Date]], Data[Average], Data[[#This Row],[Average]], Data[STDEV], "<"&Data[[#This Row],[STDEV]])+1, "TBD") -> 5 | S89: 1 | T89: =Data[[#This Row],[Day Rank]]=Data[[#This Row],[W Rank]] -> FALSE
D90: =D87 -> 45484 | E90: =$M$1 -> samuelbattista | F90: =IFERROR(AVERAGE(Data[[#This Row],[alappatjoe]:[currydestroyer27]]), "TBD") -> 2.2 | G90: =IFERROR(_xlfn.STDEV.P(Data[[#This Row],[alappatjoe]:[currydestroyer27]]), "TBD") -> 1.4696938 | H90: Congratulations | I90: Post Malone | J90: 5 | K90: 2 | L90: 1 | M90: 1 | N90: 2 | P90: Rap | Q90: Rap | R90: =IF(SUM(Data[[#This Row],[alappatjoe]:[currydestroyer27]])>0, COUNTIFS(Data[Date], Data[[#This Row],[Date]], Data[Average], "<"&Data[[#This Row],[Average]]) + COUNTIFS(Data[Date], Data[[#This Row],[Date]], Data[Average], Data[[#This Row],[Average]], Data[STDEV], "<"&Data[[#This Row],[STDEV]])+1, "TBD") -> 1 | S90: 1 | T90: =Data[[#This Row],[Day Rank]]=Data[[#This Row],[W Rank]] -> TRUE
D91: =D87 -> 45484 | E91: =$N$1 -> currydestroyer27 | F91: =IFERROR(AVERAGE(Data[[#This Row],[alappatjoe]:[currydestroyer27]]), "TBD") -> 3.4 | G91: =IFERROR(_xlfn.STDEV.P(Data[[#This Row],[alappatjoe]:[currydestroyer27]]), "TBD") -> 0.48989795 | H91: Chill Bill | I91: Rob $tone, J. DaviS, J Spooks | J91: 3 | K91: 4 | L91: 4 | M91: 3 | N91: 3 | P91: Rap | Q91: Pop Rap | R91: =IF(SUM(Data[[#This Row],[alappatjoe]:[currydestroyer27]])>0, COUNTIFS(Data[Date], Data[[#This Row],[Date]], Data[Average], "<"&Data[[#This Row],[Average]]) + COUNTIFS(Data[Date], Data[[#This Row],[Date]], Data[Average], Data[[#This Row],[Average]], Data[STDEV], "<"&Data[[#This Row],[STDEV]])+1, "TBD") -> 4 | S91: 1 | T91: =Data[[#This Row],[Day Rank]]=Data[[#This Row],[W Rank]] -> FALSE
A92: 45488 | C92: {=_xlfn.LET(_xlpm.matches, _xlfn._xlws.FILTER(Data[Poster], (Data[Date]=A92)*(Data[Winner]=TRUE)), IF(ROWS(_xlpm.matches)>1, "TIE", _xlpm.matches))} -> currydestroyer27 | D92: =A92 -> 45488 | E92: =$J$1 -> alappatjoe | F92: =IFERROR(AVERAGE(Data[[#This Row],[alappatjoe]:[currydestroyer27]]), "TBD") -> 2.6 | G92: =IFERROR(_xlfn.STDEV.P(Data[[#This Row],[alappatjoe]:[currydestroyer27]]), "TBD") -> 1.6248077 | H92: Silk & Cologne | I92: EI8HT, Offset | J92: 1 | K92: 1 | L92: 4 | M92: 5 | N92: 2 | P92: Hip-Hop | Q92: Hip-Hop | R92: =IF(SUM(Data[[#This Row],[alappatjoe]:[currydestroyer27]])>0, COUNTIFS(Data[Date], Data[[#This Row],[Date]], Data[Average], "<"&Data[[#This Row],[Average]]) + COUNTIFS(Data[Date], Data[[#This Row],[Date]], Data[Average], Data[[#This Row],[Average]], Data[STDEV], "<"&Data[[#This Row],[STDEV]])+1, "TBD") -> 2 | S92: 1 | T92: =Data[[#This Row],[Day Rank]]=Data[[#This Row],[W Rank]] -> FALSE
D93: =D92 -> 45488 | E93: =$K$1 -> danram | F93: =IFERROR(AVERAGE(Data[[#This Row],[alappatjoe]:[currydestroyer27]]), "TBD") -> 3.6 | G93: =IFERROR(_xlfn.STDEV.P(Data[[#This Row],[alappatjoe]:[currydestroyer27]]), "TBD") -> 0.8 | H93: HAZARD DUTY PAY! | I93: JPEGMAFIA | J93: 3 | K93: 3 | L93: 5 | M93: 3 | N93: 4 | P93: Rap | Q93: Rap Rock | R93: =IF(SUM(Data[[#This Row],[alappatjoe]:[currydestroyer27]])>0, COUNTIFS(Data[Date], Data[[#This Row],[Date]], Data[Average], "<"&Data[[#This Row],[Average]]) + COUNTIFS(Data[Date], Data[[#This Row],[Date]], Data[Average], Data[[#This Row],[Average]], Data[STDEV], "<"&Data[[#This Row],[STDEV]])+1, "TBD") -> 4 | S93: 1 | T93: =Data[[#This Row],[Day Rank]]=Data[[#This Row],[W Rank]] -> FALSE
D94: =D92 -> 45488 | E94: =$L$1 -> loganworsdell | F94: =IFERROR(AVERAGE(Data[[#This Row],[alappatjoe]:[currydestroyer27]]), "TBD") -> 3.2 | G94: =IFERROR(_xlfn.STDEV.P(Data[[#This Row],[alappatjoe]:[currydestroyer27]]), "TBD") -> 1.1661904 | H94: Me (FWM) | I94: Meek Mill, A$AP Ferg | J94: 4 | K94: 4 | L94: 1 | M94: 4 | N94: 3 | P94: Rap | Q94: Philly Rap | R94: =IF(SUM(Data[[#This Row],[alappatjoe]:[currydestroyer27]])>0, COUNTIFS(Data[Date], Data[[#This Row],[Date]], Data[Average], "<"&Data[[#This Row],[Average]]) + COUNTIFS(Data[Date], Data[[#This Row],[Date]], Data[Average], Data[[#This Row],[Average]], Data[STDEV], "<"&Data[[#This Row],[STDEV]])+1, "TBD") -> 3 | S94: 1 | T94: =Data[[#This Row],[Day Rank]]=Data[[#This Row],[W Rank]] -> FALSE
D95: =D92 -> 45488 | E95: =$M$1 -> samuelbattista | F95: =IFERROR(AVERAGE(Data[[#This Row],[alappatjoe]:[currydestroyer27]]), "TBD") -> 3.8 | G95: =IFERROR(_xlfn.STDEV.P(Data[[#This Row],[alappatjoe]:[currydestroyer27]]), "TBD") -> 1.6 | H95: Watch The World Burn | I95: Falling in Reverse | J95: 5 | K95: 5 | L95: 3 | M95: 1 | N95: 5 | P95: Metal | Q95: Alternative Metal | R95: =IF(SUM(Data[[#This Row],[alappatjoe]:[currydestroyer27]])>0, COUNTIFS(Data[Date], Data[[#This Row],[Date]], Data[Average], "<"&Data[[#This Row],[Average]]) + COUNTIFS(Data[Date], Data[[#This Row],[Date]], Data[Average], Data[[#This Row],[Average]], Data[STDEV], "<"&Data[[#This Row],[STDEV]])+1, "TBD") -> 5 | S95: 1 | T95: =Data[[#This Row],[Day Rank]]=Data[[#This Row],[W Rank]] -> FALSE
D96: =D92 -> 45488 | E96: =$N$1 -> currydestroyer27 | F96: =IFERROR(AVERAGE(Data[[#This Row],[alappatjoe]:[currydestroyer27]]), "TBD") -> 1.8 | G96: =IFERROR(_xlfn.STDEV.P(Data[[#This Row],[alappatjoe]:[currydestroyer27]]), "TBD") -> 0.4 | H96: Annihilate | I96: Metro Boomin, Swae Lee, Lil Wayne | J96: 2 | K96: 2 | L96: 2 | M96: 2 | N96: 1 | P96: Rap | Q96: Rap | R96: =IF(SUM(Data[[#This Row],[alappatjoe]:[currydestroyer27]])>0, COUNTIFS(Data[Date], Data[[#This Row],[Date]], Data[Average], "<"&Data[[#This Row],[Average]]) + COUNTIFS(Data[Date], Data[[#This Row],[Date]], Data[Average], Data[[#This Row],[Average]], Data[STDEV], "<"&Data[[#This Row],[STDEV]])+1, "TBD") -> 1 | S96: 1 | T96: =Data[[#This Row],[Day Rank]]=Data[[#This Row],[W Rank]] -> TRUE
A97: 45489 | C97: {=_xlfn.LET(_xlpm.matches, _xlfn._xlws.FILTER(Data[Poster], (Data[Date]=A97)*(Data[Winner]=TRUE)), IF(ROWS(_xlpm.matches)>1, "TIE", _xlpm.matches))} -> loganworsdell | D97: =A97 -> 45489 | E97: =$J$1 -> alappatjoe | F97: =IFERROR(AVERAGE(Data[[#This Row],[alappatjoe]:[currydestroyer27]]), "TBD") -> 3.2 | G97: =IFERROR(_xlfn.STDEV.P(Data[[#This Row],[alappatjoe]:[currydestroyer27]]), "TBD") -> 1.1661904 | H97: Mona Lisa | I97: Dominic Fike | J97: 1 | K97: 4 | L97: 4 | M97: 4 | N97: 3 | P97: R&B | Q97: Alternative R&B | R97: =IF(SUM(Data[[#This Row],[alappatjoe]:[currydestroyer27]])>0, COUNTIFS(Data[Date], Data[[#This Row],[Date]], Data[Average], "<"&Data[[#This Row],[Average]]) + COUNTIFS(Data[Date], Data[[#This Row],[Date]], Data[Average], Data[[#This Row],[Average]], Data[STDEV], "<"&Data[[#This Row],[STDEV]])+1, "TBD") -> 3 | S97: 1 | T97: =Data[[#This Row],[Day Rank]]=Data[[#This Row],[W Rank]] -> FALSE
D98: =D97 -> 45489 | E98: =$K$1 -> danram | F98: =IFERROR(AVERAGE(Data[[#This Row],[alappatjoe]:[currydestroyer27]]), "TBD") -> 3.4 | G98: =IFERROR(_xlfn.STDEV.P(Data[[#This Row],[alappatjoe]:[currydestroyer27]]), "TBD") -> 1.0198039 | H98: Lonely At The Top | I98: Asake | J98: 5 | K98: 2 | L98: 3 | M98: 3 | N98: 4 | P98: International | Q98: Afro-Beat | R98: =IF(SUM(Data[[#This Row],[alappatjoe]:[currydestroyer27]])>0, COUNTIFS(Data[Date], Data[[#This Row],[Date]], Data[Average], "<"&Data[[#This Row],[Average]]) + COUNTIFS(Data[Date], Data[[#This Row],[Date]], Data[Average], Data[[#This Row],[Average]], Data[STDEV], "<"&Data[[#This Row],[STDEV]])+1, "TBD") -> 4 | S98: 1 | T98: =Data[[#This Row],[Day Rank]]=Data[[#This Row],[W Rank]] -> FALSE
D99: =D97 -> 45489 | E99: =$L$1 -> loganworsdell | F99: =IFERROR(AVERAGE(Data[[#This Row],[alappatjoe]:[currydestroyer27]]), "TBD") -> 1.4 | G99: =IFERROR(_xlfn.STDEV.P(Data[[#This Row],[alappatjoe]:[currydestroyer27]]), "TBD") -> 0.8 | H99: Feel It | I99: d4vd | J99: 3 | K99: 1 | L99: 1 | M99: 1 | N99: 1 | P99: Pop | Q99: Bedroom Pop | R99: =IF(SUM(Data[[#This Row],[alappatjoe]:[currydestroyer27]])>0, COUNTIFS(Data[Date], Data[[#This Row],[Date]], Data[Average], "<"&Data[[#This Row],[Average]]) + COUNTIFS(Data[Date], Data[[#This Row],[Date]], Data[Average], Data[[#This Row],[Average]], Data[STDEV], "<"&Data[[#This Row],[STDEV]])+1, "TBD") -> 1 | S99: 1 | T99: =Data[[#This Row],[Day Rank]]=Data[[#This Row],[W Rank]] -> TRUE
D100: =D97 -> 45489 | E100: =$M$1 -> samuelbattista | F100: =IFERROR(AVERAGE(Data[[#This Row],[alappatjoe]:[currydestroyer27]]), "TBD") -> 4.2 | G100: =IFERROR(_xlfn.STDEV.P(Data[[#This Row],[alappatjoe]:[currydestroyer27]]), "TBD") -> 1.1661904 | H100: Them Changes | I100: Thundercat | J100: 4 | K100: 5 | L100: 5 | M100: 2 | N100: 5 | P100: R&B | Q100: Funk | R100: =IF(SUM(Data[[#This Row],[alappatjoe]:[currydestroyer27]])>0, COUNTIFS(Data[Date], Data[[#This Row],[Date]], Data[Average], "<"&Data[[#This Row],[Average]]) + COUNTIFS(Data[Date], Data[[#This Row],[Date]], Data[Average], Data[[#This Row],[Average]], Data[STDEV], "<"&Data[[#This Row],[STDEV]])+1, "TBD") -> 5 | S100: 1 | T100: =Data[[#This Row],[Day Rank]]=Data[[#This Row],[W Rank]] -> FALSE
...

Sheet Leaderboard
B2: =_xlfn.CONCAT("Day ",COUNTIF(Rankings!A:A,"<="&TODAY())) -> Day 445 | C2: Number of Wins | D2: Sum of Average | E2: Overall Average | F2: Place | G2: Constructors | I2: Poster\Day Rank | J2: 1 | K2: 2 | L2: 3 | M2: 4 | N2: 5 | P2: Plays | Q2: Mean | R2: 1B+ | S2: Median | T2: Min | U2: Max
B3: =Rankings!$J$1 -> alappatjoe | C3: =COUNTIFS(Data[[Poster]:[Poster]],$B3, Data[Winner],TRUE()) -> 87 | D3: {=SUM(IF(Data[Poster]=$B3, Data[Average]))} -> 1354.4 | E3: {=AVERAGE(IF(Data[Poster]=$B3, Data[Average]))} -> 3.0435955 | F3: =_xlfn.RANK.EQ(C3,$C$3:$C$7,0) -> 4 | G3: =_xlfn.RANK.EQ(E3,$E$3:$E$7,1) -> 4 | I3: =Rankings!$J$1 -> alappatjoe | J3: =COUNTIFS(Data[[Poster]:[Poster]],$I3, Data[[Day Rank]:[Day Rank]],J$2) -> 91 | K3: =COUNTIFS(Data[[Poster]:[Poster]],$I3, Data[[Day Rank]:[Day Rank]],K$2) -> 64 | L3: =COUNTIFS(Data[[Poster]:[Poster]],$I3, Data[[Day Rank]:[Day Rank]],L$2) -> 96 | M3: =COUNTIFS(Data[[Poster]:[Poster]],$I3, Data[[Day Rank]:[Day Rank]],M$2) -> 96 | N3: =COUNTIFS(Data[[Poster]:[Poster]],$I3, Data[[Day Rank]:[Day Rank]],N$2) -> 98 | P3: =Rankings!$J$1 -> alappatjoe | Q3: {=AVERAGE(IF(Data[Poster]=$P3, IF(Data[Plays]>0, Data[Plays])))} -> 1.757084e+08 | R3: =COUNTIFS(Data[[Poster]:[Poster]],$I3, Data[[Plays]:[Plays]],">="&1000000000) -> 13 | S3: {=MEDIAN(IF(Data[Poster]=$P3, IF(Data[Plays]>0, Data[Plays])))} -> 4921398 | T3: {=MIN(IF(Data[Poster]=$P3, IF(Data[Plays]>0, Data[Plays])))} -> 999 | U3: {=MAX(IF(Data[Poster]=$P3, IF(Data[Plays]>0, Data[Plays])))} -> 3355842640
B4: =Rankings!$K$1 -> danram | C4: =COUNTIFS(Data[[Poster]:[Poster]],$B4, Data[Winner],TRUE()) -> 89 | D4: {=SUM(IF(Data[Poster]=$B4, Data[Average]))} -> 1393.6 | E4: {=AVERAGE(IF(Data[Poster]=$B4, Data[Average]))} -> 3.1316854 | F4: =_xlfn.RANK.EQ(C4,$C$3:$C$7,0) -> 3 | G4: =_xlfn.RANK.EQ(E4,$E$3:$E$7,1) -> 5 | I4: =Rankings!$K$1 -> danram | J4: =COUNTIFS(Data[[Poster]:[Poster]],$I4, Data[[Day Rank]:[Day Rank]],J$2) -> 89 | K4: =COUNTIFS(Data[[Poster]:[Poster]],$I4, Data[[Day Rank]:[Day Rank]],K$2) -> 81 | L4: =COUNTIFS(Data[[Poster]:[Poster]],$I4, Data[[Day Rank]:[Day Rank]],L$2) -> 68 | M4: =COUNTIFS(Data[[Poster]:[Poster]],$I4, Data[[Day Rank]:[Day Rank]],M$2) -> 98 | N4: =COUNTIFS(Data[[Poster]:[Poster]],$I4, Data[[Day Rank]:[Day Rank]],N$2) -> 109 | P4: =Rankings!$K$1 -> danram | Q4: {=AVERAGE(IF(Data[Poster]=$P4, IF(Data[Plays]>0, Data[Plays])))} -> 9.4006842e+08 | R4: =COUNTIFS(Data[[Poster]:[Poster]],$I4, Data[[Plays]:[Plays]],">="&1000000000) -> 10 | S4: {=MEDIAN(IF(Data[Poster]=$P4, IF(Data[Plays]>0, Data[Plays])))} -> 629447417 | T4: {=MIN(IF(Data[Poster]=$P4, IF(Data[Plays]>0, Data[Plays])))} -> 667073 | U4: {=MAX(IF(Data[Poster]=$P4, IF(Data[Plays]>0, Data[Plays])))} -> 4454441248
B5: =Rankings!$L$1 -> loganworsdell | C5: =COUNTIFS(Data[[Poster]:[Poster]],$B5, Data[Winner],TRUE()) -> 90 | D5: {=SUM(IF(Data[Poster]=$B5, Data[Average]))} -> 1339.4 | E5: {=AVERAGE(IF(Data[Poster]=$B5, Data[Average]))} -> 3.0098876 | F5: =_xlfn.RANK.EQ(C5,$C$3:$C$7,0) -> 2 | G5: =_xlfn.RANK.EQ(E5,$E$3:$E$7,1) -> 3 | I5: =Rankings!$L$1 -> loganworsdell | J5: =COUNTIFS(Data[[Poster]:[Poster]],$I5, Data[[Day Rank]:[Day Rank]],J$2) -> 93 | K5: =COUNTIFS(Data[[Poster]:[Poster]],$I5, Data[[Day Rank]:[Day Rank]],K$2) -> 92 | L5: =COUNTIFS(Data[[Poster]:[Poster]],$I5, Data[[Day Rank]:[Day Rank]],L$2) -> 84 | M5: =COUNTIFS(Data[[Poster]:[Poster]],$I5, Data[[Day Rank]:[Day Rank]],M$2) -> 91 | N5: =COUNTIFS(Data[[Poster]:[Poster]],$I5, Data[[Day Rank]:[Day Rank]],N$2) -> 85 | P5: =Rankings!$L$1 -> loganworsdell | Q5: {=AVERAGE(IF(Data[Poster]=$P5, IF(Data[Plays]>0, Data[Plays])))} -> 1.4136032e+08 | R5: =COUNTIFS(Data[[Poster]:[Poster]],$I5, Data[[Plays]:[Plays]],">="&1000000000) -> 10 | S5: {=MEDIAN(IF(Data[Poster]=$P5, IF(Data[Plays]>0, Data[Plays])))} -> 7367511 | T5: {=MIN(IF(Data[Poster]=$P5, IF(Data[Plays]>0, Data[Plays])))} -> 999 | U5: {=MAX(IF(Data[Poster]=$P5, IF(Data[Plays]>0, Data[Plays])))} -> 3869670265
B6: =Rankings!$M$1 -> samuelbattista | C6: =COUNTIFS(Data[[Poster]:[Poster]],$B6, Data[Winner],TRUE()) -> 87 | D6: {=SUM(IF(Data[Poster]=$B6, Data[Average]))} -> 1306.2 | E6: {=AVERAGE(IF(Data[Poster]=$B6, Data[Average]))} -> 2.9352809 | F6: =_xlfn.RANK.EQ(C6,$C$3:$C$7,0) -> 4 | G6: =_xlfn.RANK.EQ(E6,$E$3:$E$7,1) -> 2 | I6: =Rankings!$M$1 -> samuelbattista | J6: =COUNTIFS(Data[[Poster]:[Poster]],$I6, Data[[Day Rank]:[Day Rank]],J$2) -> 92 | K6: =COUNTIFS(Data[[Poster]:[Poster]],$I6, Data[[Day Rank]:[Day Rank]],K$2) -> 107 | L6: =COUNTIFS(Data[[Poster]:[Poster]],$I6, Data[[Day Rank]:[Day Rank]],L$2) -> 96 | M6: =COUNTIFS(Data[[Poster]:[Poster]],$I6, Data[[Day Rank]:[Day Rank]],M$2) -> 76 | N6: =COUNTIFS(Data[[Poster]:[Poster]],$I6, Data[[Day Rank]:[Day Rank]],N$2) -> 74 | P6: =Rankings!$M$1 -> samuelbattista | Q6: {=AVERAGE(IF(Data[Poster]=$P6, IF(Data[Plays]>0, Data[Plays])))} -> 4.3092698e+08 | R6: =COUNTIFS(Data[[Poster]:[Poster]],$I6, Data[[Plays]:[Plays]],">="&1000000000) -> 7 | S6: {=MEDIAN(IF(Data[Poster]=$P6, IF(Data[Plays]>0, Data[Plays])))} -> 27496238 | T6: {=MIN(IF(Data[Poster]=$P6, IF(Data[Plays]>0, Data[Plays])))} -> 40645 | U6: {=MAX(IF(Data[Poster]=$P6, IF(Data[Plays]>0, Data[Plays])))} -> 5351958417
B7: =Rankings!$N$1 -> currydestroyer27 | C7: =COUNTIFS(Data[[Poster]:[Poster]],$B7, Data[Winner],TRUE()) -> 92 | D7: {=SUM(IF(Data[Poster]=$B7, Data[Average]))} -> 1281.4 | E7: {=AVERAGE(IF(Data[Poster]=$B7, Data[Average]))} -> 2.8795506 | F7: =_xlfn.RANK.EQ(C7,$C$3:$C$7,0) -> 1 | G7: =_xlfn.RANK.EQ(E7,$E$3:$E$7,1) -> 1 | I7: =Rankings!$N$1 -> currydestroyer27 | J7: =COUNTIFS(Data[[Poster]:[Poster]],$I7, Data[[Day Rank]:[Day Rank]],J$2) -> 96 | K7: =COUNTIFS(Data[[Poster]:[Poster]],$I7, Data[[Day Rank]:[Day Rank]],K$2) -> 104 | L7: =COUNTIFS(Data[[Poster]:[Poster]],$I7, Data[[Day Rank]:[Day Rank]],L$2) -> 93 | M7: =COUNTIFS(Data[[Poster]:[Poster]],$I7, Data[[Day Rank]:[Day Rank]],M$2) -> 83 | N7: =COUNTIFS(Data[[Poster]:[Poster]],$I7, Data[[Day Rank]:[Day Rank]],N$2) -> 69 | P7: =Rankings!$N$1 -> currydestroyer27 | Q7: {=AVERAGE(IF(Data[Poster]=$P7, IF(Data[Plays]>0, Data[Plays])))} -> 2.6256088e+08 | R7: =COUNTIFS(Data[[Poster]:[Poster]],$I7, Data[[Plays]:[Plays]],">="&1000000000) -> 17 | S7: {=MEDIAN(IF(Data[Poster]=$P7, IF(Data[Plays]>0, Data[Plays])))} -> 63260342 | T7: {=MIN(IF(Data[Poster]=$P7, IF(Data[Plays]>0, Data[Plays])))} -> 3000 | U7: {=MAX(IF(Data[Poster]=$P7, IF(Data[Plays]>0, Data[Plays])))} -> 2883211530
B9: Average Rank for past | E9: 28 | F9: days | I9: Median Rank for past | L9: 28 | M9: days | P9: 1 | Q9: =_xlfn.CONCAT("Amount of ",P9,"'s given for past") -> Amount of 1's given for past | T9: 1000 | U9: days | V9: Sum | X9: 2 | Y9: =_xlfn.CONCAT("Amount of ",X9,"'s given for past") -> Amount of 2's given for past | AB9: 1000 | AC9: days | AD9: Sum
B10: Poster\Voter | C10: =Rankings!$J$1 -> alappatjoe | D10: =Rankings!$K$1 -> danram | E10: =Rankings!$L$1 -> loganworsdell | F10: =Rankings!$M$1 -> samuelbattista | G10: =Rankings!$N$1 -> currydestroyer27 | I10: Poster\Voter | J10: =Rankings!$J$1 -> alappatjoe | K10: =Rankings!$K$1 -> danram | L10: =Rankings!$L$1 -> loganworsdell | M10: =Rankings!$M$1 -> samuelbattista | N10: =Rankings!$N$1 -> currydestroyer27 | P10: Poster\Voter | Q10: =Rankings!$J$1 -> alappatjoe | R10: =Rankings!$K$1 -> danram | S10: =Rankings!$L$1 -> loganworsdell | T10: =Rankings!$M$1 -> samuelbattista | U10: =Rankings!$N$1 -> currydestroyer27 | X10: Poster\Voter | Y10: =Rankings!$J$1 -> alappatjoe | Z10: =Rankings!$K$1 -> danram | AA10: =Rankings!$L$1 -> loganworsdell | AB10: =Rankings!$M$1 -> samuelbattista | AC10: =Rankings!$N$1 -> currydestroyer27
B11: =Rankings!$J$1 -> alappatjoe | C11: {=AVERAGE(IF(Data[Poster]=$B11, IF(Data[Date]> TODAY()-$E$9, IF(INDIRECT(_xlfn.CONCAT("Data[", C$10, "]"))>0, INDIRECT(_xlfn.CONCAT("Data[", C$10, "]"))))))} -> 1.375 | D11: {=AVERAGE(IF(Data[Poster]=$B11, IF(Data[Date]> TODAY()-$E$9, IF(INDIRECT(_xlfn.CONCAT("Data[", D$10, "]"))>0, INDIRECT(_xlfn.CONCAT("Data[", D$10, "]"))))))} -> 3.4375 | E11: {=AVERAGE(IF(Data[Poster]=$B11, IF(Data[Date]> TODAY()-$E$9, IF(INDIRECT(_xlfn.CONCAT("Data[", E$10, "]"))>0, INDIRECT(_xlfn.CONCAT("Data[", E$10, "]"))))))} -> 3 | F11: {=AVERAGE(IF(Data[Poster]=$B11, IF(Data[Date]> TODAY()-$E$9, IF(INDIRECT(_xlfn.CONCAT("Data[", F$10, "]"))>0, INDIRECT(_xlfn.CONCAT("Data[", F$10, "]"))))))} -> 3.5625 | G11: {=AVERAGE(IF(Data[Poster]=$B11, IF(Data[Date]> TODAY()-$E$9, IF(INDIRECT(_xlfn.CONCAT("Data[", G$10, "]"))>0, INDIRECT(_xlfn.CONCAT("Data[", G$10, "]"))))))} -> 3.0625 | I11: =Rankings!$J$1 -> alappatjoe | J11: {=MEDIAN(IF(Data[Poster]=$I11, IF(Data[Date]> TODAY()-$L$9, IF(INDIRECT(_xlfn.CONCAT("Data[", J$10, "]"))>0, INDIRECT(_xlfn.CONCAT("Data[", J$10, "]"))))))} -> 1 | K11: {=MEDIAN(IF(Data[Poster]=$I11, IF(Data[Date]> TODAY()-$L$9, IF(INDIRECT(_xlfn.CONCAT("Data[", K$10, "]"))>0, INDIRECT(_xlfn.CONCAT("Data[", K$10, "]"))))))} -> 3.5 | L11: {=MEDIAN(IF(Data[Poster]=$I11, IF(Data[Date]> TODAY()-$L$9, IF(INDIRECT(_xlfn.CONCAT("Data[", L$10, "]"))>0, INDIRECT(_xlfn.CONCAT("Data[", L$10, "]"))))))} -> 3 | M11: {=MEDIAN(IF(Data[Poster]=$I11, IF(Data[Date]> TODAY()-$L$9, IF(INDIRECT(_xlfn.CONCAT("Data[", M$10, "]"))>0, INDIRECT(_xlfn.CONCAT("Data[", M$10, "]"))))))} -> 4 | N11: {=MEDIAN(IF(Data[Poster]=$I11, IF(Data[Date]> TODAY()-$L$9, IF(INDIRECT(_xlfn.CONCAT("Data[", N$10, "]"))>0, INDIRECT(_xlfn.CONCAT("Data[", N$10, "]"))))))} -> 3 | P11: =Rankings!$J$1 -> alappatjoe | Q11: =COUNTIFS(Data[Date],">"&TODAY()-$T$9,Data[Poster],$P11,INDIRECT(_xlfn.CONCAT("Data[", Q$10, "]")),$P$9) -> 384 | R11: =COUNTIFS(Data[Date],">"&TODAY()-$T$9,Data[Poster],$P11,INDIRECT(_xlfn.CONCAT("Data[", R$10, "]")),$P$9) -> 29 | S11: =COUNTIFS(Data[Date],">"&TODAY()-$T$9,Data[Poster],$P11,INDIRECT(_xlfn.CONCAT("Data[", S$10, "]")),$P$9) -> 38 | T11: =COUNTIFS(Data[Date],">"&TODAY()-$T$9,Data[Poster],$P11,INDIRECT(_xlfn.CONCAT("Data[", T$10, "]")),$P$9) -> 17 | U11: =COUNTIFS(Data[Date],">"&TODAY()-$T$9,Data[Poster],$P11,INDIRECT(_xlfn.CONCAT("Data[", U$10, "]")),$P$9) -> 33 | V11: =SUM(Q11:U11) -> 501 | X11: =Rankings!$J$1 -> alappatjoe | Y11: =COUNTIFS(Data[Date],">"&TODAY()-$AB$9,Data[Poster],$X11,INDIRECT(_xlfn.CONCAT("Data[", Y$10, "]")),$X$9) -> 38 | Z11: =COUNTIFS(Data[Date],">"&TODAY()-$AB$9,Data[Poster],$X11,INDIRECT(_xlfn.CONCAT("Data[", Z$10, "]")),$X$9) -> 68 | AA11: =COUNTIFS(Data[Date],">"&TODAY()-$AB$9,Data[Poster],$X11,INDIRECT(_xlfn.CONCAT("Data[", AA$10, "]")),$X$9) -> 71 | AB11: =COUNTIFS(Data[Date],">"&TODAY()-$AB$9,Data[Poster],$X11,INDIRECT(_xlfn.CONCAT("Data[", AB$10, "]")),$X$9) -> 77 | AC11: =COUNTIFS(Data[Date],">"&TODAY()-$AB$9,Data[Poster],$X11,INDIRECT(_xlfn.CONCAT("Data[", AC$10, "]")),$X$9) -> 118 | AD11: =SUM(Y11:AC11) -> 372
B12: =Rankings!$K$1 -> danram | C12: {=AVERAGE(IF(Data[Poster]=$B12, IF(Data[Date]> TODAY()-$E$9, IF(INDIRECT(_xlfn.CONCAT("Data[", C$10, "]"))>0, INDIRECT(_xlfn.CONCAT("Data[", C$10, "]"))))))} -> 3.6875 | D12: {=AVERAGE(IF(Data[Poster]=$B12, IF(Data[Date]> TODAY()-$E$9, IF(INDIRECT(_xlfn.CONCAT("Data[", D$10, "]"))>0, INDIRECT(_xlfn.CONCAT("Data[", D$10, "]"))))))} -> 2.25 | E12: {=AVERAGE(IF(Data[Poster]=$B12, IF(Data[Date]> TODAY()-$E$9, IF(INDIRECT(_xlfn.CONCAT("Data[", E$10, "]"))>0, INDIRECT(_xlfn.CONCAT("Data[", E$10, "]"))))))} -> 4.0625 | F12: {=AVERAGE(IF(Data[Poster]=$B12, IF(Data[Date]> TODAY()-$E$9, IF(INDIRECT(_xlfn.CONCAT("Data[", F$10, "]"))>0, INDIRECT(_xlfn.CONCAT("Data[", F$10, "]"))))))} -> 2.8125 | G12: {=AVERAGE(IF(Data[Poster]=$B12, IF(Data[Date]> TODAY()-$E$9, IF(INDIRECT(_xlfn.CONCAT("Data[", G$10, "]"))>0, INDIRECT(_xlfn.CONCAT("Data[", G$10, "]"))))))} -> 3.5625 | I12: =Rankings!$K$1 -> danram | J12: {=MEDIAN(IF(Data[Poster]=$I12, IF(Data[Date]> TODAY()-$L$9, IF(INDIRECT(_xlfn.CONCAT("Data[", J$10, "]"))>0, INDIRECT(_xlfn.CONCAT("Data[", J$10, "]"))))))} -> 4 | K12: {=MEDIAN(IF(Data[Poster]=$I12, IF(Data[Date]> TODAY()-$L$9, IF(INDIRECT(_xlfn.CONCAT("Data[", K$10, "]"))>0, INDIRECT(_xlfn.CONCAT("Data[", K$10, "]"))))))} -> 1.5 | L12: {=MEDIAN(IF(Data[Poster]=$I12, IF(Data[Date]> TODAY()-$L$9, IF(INDIRECT(_xlfn.CONCAT("Data[", L$10, "]"))>0, INDIRECT(_xlfn.CONCAT("Data[", L$10, "]"))))))} -> 5 | M12: {=MEDIAN(IF(Data[Poster]=$I12, IF(Data[Date]> TODAY()-$L$9, IF(INDIRECT(_xlfn.CONCAT("Data[", M$10, "]"))>0, INDIRECT(_xlfn.CONCAT("Data[", M$10, "]"))))))} -> 2 | N12: {=MEDIAN(IF(Data[Poster]=$I12, IF(Data[Date]> TODAY()-$L$9, IF(INDIRECT(_xlfn.CONCAT("Data[", N$10, "]"))>0, INDIRECT(_xlfn.CONCAT("Data[", N$10, "]"))))))} -> 4 | P12: =Rankings!$K$1 -> danram | Q12: =COUNTIFS(Data[Date],">"&TODAY()-$T$9,Data[Poster],$P12,INDIRECT(_xlfn.CONCAT("Data[", Q$10, "]")),$P$9) -> 17 | R12: =COUNTIFS(Data[Date],">"&TODAY()-$T$9,Data[Poster],$P12,INDIRECT(_xlfn.CONCAT("Data[", R$10, "]")),$P$9) -> 238 | S12: =COUNTIFS(Data[Date],">"&TODAY()-$T$9,Data[Poster],$P12,INDIRECT(_xlfn.CONCAT("Data[", S$10, "]")),$P$9) -> 52 | T12: =COUNTIFS(Data[Date],">"&TODAY()-$T$9,Data[Poster],$P12,INDIRECT(_xlfn.CONCAT("Data[", T$10, "]")),$P$9) -> 33 | U12: =COUNTIFS(Data[Date],">"&TODAY()-$T$9,Data[Poster],$P12,INDIRECT(_xlfn.CONCAT("Data[", U$10, "]")),$P$9) -> 25 | V12: =SUM(Q12:U12) -> 365 | X12: =Rankings!$K$1 -> danram | Y12: =COUNTIFS(Data[Date],">"&TODAY()-$AB$9,Data[Poster],$X12,INDIRECT(_xlfn.CONCAT("Data[", Y$10, "]")),$X$9) -> 82 | Z12: =COUNTIFS(Data[Date],">"&TODAY()-$AB$9,Data[Poster],$X12,INDIRECT(_xlfn.CONCAT("Data[", Z$10, "]")),$X$9) -> 90 | AA12: =COUNTIFS(Data[Date],">"&TODAY()-$AB$9,Data[Poster],$X12,INDIRECT(_xlfn.CONCAT("Data[", AA$10, "]")),$X$9) -> 59 | AB12: =COUNTIFS(Data[Date],">"&TODAY()-$AB$9,Data[Poster],$X12,INDIRECT(_xlfn.CONCAT("Data[", AB$10, "]")),$X$9) -> 120 | AC12: =COUNTIFS(Data[Date],">"&TODAY()-$AB$9,Data[Poster],$X12,INDIRECT(_xlfn.CONCAT("Data[", AC$10, "]")),$X$9) -> 97 | AD12: =SUM(Y12:AC12) -> 448
B13: =Rankings!$L$1 -> loganworsdell | C13: {=AVERAGE(IF(Data[Poster]=$B13, IF(Data[Date]> TODAY()-$E$9, IF(INDIRECT(_xlfn.CONCAT("Data[", C$10, "]"))>0, INDIRECT(_xlfn.CONCAT("Data[", C$10, "]"))))))} -> 3.0625 | D13: {=AVERAGE(IF(Data[Poster]=$B13, IF(Data[Date]> TODAY()-$E$9, IF(INDIRECT(_xlfn.CONCAT("Data[", D$10, "]"))>0, INDIRECT(_xlfn.CONCAT("Data[", D$10, "]"))))))} -> 3.1875 | E13: {=AVERAGE(IF(Data[Poster]=$B13, IF(Data[Date]> TODAY()-$E$9, IF(INDIRECT(_xlfn.CONCAT("Data[", E$10, "]"))>0, INDIRECT(_xlfn.CONCAT("Data[", E$10, "]"))))))} -> 1.8125 | F13: {=AVERAGE(IF(Data[Poster]=$B13, IF(Data[Date]> TODAY()-$E$9, IF(INDIRECT(_xlfn.CONCAT("Data[", F$10, "]"))>0, INDIRECT(_xlfn.CONCAT("Data[", F$10, "]"))))))} -> 3.5 | G13: {=AVERAGE(IF(Data[Poster]=$B13, IF(Data[Date]> TODAY()-$E$9, IF(INDIRECT(_xlfn.CONCAT("Data[", G$10, "]"))>0, INDIRECT(_xlfn.CONCAT("Data[", G$10, "]"))))))} -> 3.4375 | I13: =Rankings!$L$1 -> loganworsdell | J13: {=MEDIAN(IF(Data[Poster]=$I13, IF(Data[Date]> TODAY()-$L$9, IF(INDIRECT(_xlfn.CONCAT("Data[", J$10, "]"))>0, INDIRECT(_xlfn.CONCAT("Data[", J$10, "]"))))))} -> 2.5 | K13: {=MEDIAN(IF(Data[Poster]=$I13, IF(Data[Date]> TODAY()-$L$9, IF(INDIRECT(_xlfn.CONCAT("Data[", K$10, "]"))>0, INDIRECT(_xlfn.CONCAT("Data[", K$10, "]"))))))} -> 3 | L13: {=MEDIAN(IF(Data[Poster]=$I13, IF(Data[Date]> TODAY()-$L$9, IF(INDIRECT(_xlfn.CONCAT("Data[", L$10, "]"))>0, INDIRECT(_xlfn.CONCAT("Data[", L$10, "]"))))))} -> 1.5 | M13: {=MEDIAN(IF(Data[Poster]=$I13, IF(Data[Date]> TODAY()-$L$9, IF(INDIRECT(_xlfn.CONCAT("Data[", M$10, "]"))>0, INDIRECT(_xlfn.CONCAT("Data[", M$10, "]"))))))} -> 3 | N13: {=MEDIAN(IF(Data[Poster]=$I13, IF(Data[Date]> TODAY()-$L$9, IF(INDIRECT(_xlfn.CONCAT("Data[", N$10, "]"))>0, INDIRECT(_xlfn.CONCAT("Data[", N$10, "]"))))))} -> 3 | P13: =Rankings!$L$1 -> loganworsdell | Q13: =COUNTIFS(Data[Date],">"&TODAY()-$T$9,Data[Poster],$P13,INDIRECT(_xlfn.CONCAT("Data[", Q$10, "]")),$P$9) -> 17 | R13: =COUNTIFS(Data[Date],">"&TODAY()-$T$9,Data[Poster],$P13,INDIRECT(_xlfn.CONCAT("Data[", R$10, "]")),$P$9) -> 61 | S13: =COUNTIFS(Data[Date],">"&TODAY()-$T$9,Data[Poster],$P13,INDIRECT(_xlfn.CONCAT("Data[", S$10, "]")),$P$9) -> 215 | T13: =COUNTIFS(Data[Date],">"&TODAY()-$T$9,Data[Poster],$P13,INDIRECT(_xlfn.CONCAT("Data[", T$10, "]")),$P$9) -> 15 | U13: =COUNTIFS(Data[Date],">"&TODAY()-$T$9,Data[Poster],$P13,INDIRECT(_xlfn.CONCAT("Data[", U$10, "]")),$P$9) -> 37 | V13: =SUM(Q13:U13) -> 345 | X13: =Rankings!$L$1 -> loganworsdell | Y13: =COUNTIFS(Data[Date],">"&TODAY()-$AB$9,Data[Poster],$X13,INDIRECT(_xlfn.CONCAT("Data[", Y$10, "]")),$X$9) -> 118 | Z13: =COUNTIFS(Data[Date],">"&TODAY()-$AB$9,Data[Poster],$X13,INDIRECT(_xlfn.CONCAT("Data[", Z$10, "]")),$X$9) -> 87 | AA13: =COUNTIFS(Data[Date],">"&TODAY()-$AB$9,Data[Poster],$X13,INDIRECT(_xlfn.CONCAT("Data[", AA$10, "]")),$X$9) -> 122 | AB13: =COUNTIFS(Data[Date],">"&TODAY()-$AB$9,Data[Poster],$X13,INDIRECT(_xlfn.CONCAT("Data[", AB$10, "]")),$X$9) -> 105 | AC13: =COUNTIFS(Data[Date],">"&TODAY()-$AB$9,Data[Poster],$X13,INDIRECT(_xlfn.CONCAT("Data[", AC$10, "]")),$X$9) -> 83 | AD13: =SUM(Y13:AC13) -> 515
B14: =Rankings!$M$1 -> samuelbattista | C14: {=AVERAGE(IF(Data[Poster]=$B14, IF(Data[Date]> TODAY()-$E$9, IF(INDIRECT(_xlfn.CONCAT("Data[", C$10, "]"))>0, INDIRECT(_xlfn.CONCAT("Data[", C$10, "]"))))))} -> 3.625 | D14: {=AVERAGE(IF(Data[Poster]=$B14, IF(Data[Date]> TODAY()-$E$9, IF(INDIRECT(_xlfn.CONCAT("Data[", D$10, "]"))>0, INDIRECT(_xlfn.CONCAT("Data[", D$10, "]"))))))} -> 3.25 | E14: {=AVERAGE(IF(Data[Poster]=$B14, IF(Data[Date]> TODAY()-$E$9, IF(INDIRECT(_xlfn.CONCAT("Data[", E$10, "]"))>0, INDIRECT(_xlfn.CONCAT("Data[", E$10, "]"))))))} -> 3.0625 | F14: {=AVERAGE(IF(Data[Poster]=$B14, IF(Data[Date]> TODAY()-$E$9, IF(INDIRECT(_xlfn.CONCAT("Data[", F$10, "]"))>0, INDIRECT(_xlfn.CONCAT("Data[", F$10, "]"))))))} -> 1.4375 | G14: {=AVERAGE(IF(Data[Poster]=$B14, IF(Data[Date]> TODAY()-$E$9, IF(INDIRECT(_xlfn.CONCAT("Data[", G$10, "]"))>0, INDIRECT(_xlfn.CONCAT("Data[", G$10, "]"))))))} -> 3.3125 | I14: =Rankings!$M$1 -> samuelbattista | J14: {=MEDIAN(IF(Data[Poster]=$I14, IF(Data[Date]> TODAY()-$L$9, IF(INDIRECT(_xlfn.CONCAT("Data[", J$10, "]"))>0, INDIRECT(_xlfn.CONCAT("Data[", J$10, "]"))))))} -> 4 | K14: {=MEDIAN(IF(Data[Poster]=$I14, IF(Data[Date]> TODAY()-$L$9, IF(INDIRECT(_xlfn.CONCAT("Data[", K$10, "]"))>0, INDIRECT(_xlfn.CONCAT("Data[", K$10, "]"))))))} -> 3 | L14: {=MEDIAN(IF(Data[Poster]=$I14, IF(Data[Date]> TODAY()-$L$9, IF(INDIRECT(_xlfn.CONCAT("Data[", L$10, "]"))>0, INDIRECT(_xlfn.CONCAT("Data[", L$10, "]"))))))} -> 3.5 | M14: {=MEDIAN(IF(Data[Poster]=$I14, IF(Data[Date]> TODAY()-$L$9, IF(INDIRECT(_xlfn.CONCAT("Data[", M$10, "]"))>0, INDIRECT(_xlfn.CONCAT("Data[", M$10, "]"))))))} -> 1 | N14: {=MEDIAN(IF(Data[Poster]=$I14, IF(Data[Date]> TODAY()-$L$9, IF(INDIRECT(_xlfn.CONCAT("Data[", N$10, "]"))>0, INDIRECT(_xlfn.CONCAT("Data[", N$10, "]"))))))} -> 3.5 | P14: =Rankings!$M$1 -> samuelbattista | Q14: =COUNTIFS(Data[Date],">"&TODAY()-$T$9,Data[Poster],$P14,INDIRECT(_xlfn.CONCAT("Data[", Q$10, "]")),$P$9) -> 9 | R14: =COUNTIFS(Data[Date],">"&TODAY()-$T$9,Data[Poster],$P14,INDIRECT(_xlfn.CONCAT("Data[", R$10, "]")),$P$9) -> 60 | S14: =COUNTIFS(Data[Date],">"&TODAY()-$T$9,Data[Poster],$P14,INDIRECT(_xlfn.CONCAT("Data[", S$10, "]")),$P$9) -> 75 | T14: =COUNTIFS(Data[Date],">"&TODAY()-$T$9,Data[Poster],$P14,INDIRECT(_xlfn.CONCAT("Data[", T$10, "]")),$P$9) -> 361 | U14: =COUNTIFS(Data[Date],">"&TODAY()-$T$9,Data[Poster],$P14,INDIRECT(_xlfn.CONCAT("Data[", U$10, "]")),$P$9) -> 15 | V14: =SUM(Q14:U14) -> 520 | X14: =Rankings!$M$1 -> samuelbattista | Y14: =COUNTIFS(Data[Date],">"&TODAY()-$AB$9,Data[Poster],$X14,INDIRECT(_xlfn.CONCAT("Data[", Y$10, "]")),$X$9) -> 87 | Z14: =COUNTIFS(Data[Date],">"&TODAY()-$AB$9,Data[Poster],$X14,INDIRECT(_xlfn.CONCAT("Data[", Z$10, "]")),$X$9) -> 97 | AA14: =COUNTIFS(Data[Date],">"&TODAY()-$AB$9,Data[Poster],$X14,INDIRECT(_xlfn.CONCAT("Data[", AA$10, "]")),$X$9) -> 87 | AB14: =COUNTIFS(Data[Date],">"&TODAY()-$AB$9,Data[Poster],$X14,INDIRECT(_xlfn.CONCAT("Data[", AB$10, "]")),$X$9) -> 59 | AC14: =COUNTIFS(Data[Date],">"&TODAY()-$AB$9,Data[Poster],$X14,INDIRECT(_xlfn.CONCAT("Data[", AC$10, "]")),$X$9) -> 85 | AD14: =SUM(Y14:AC14) -> 415
B15: =Rankings!$N$1 -> currydestroyer27 | C15: {=AVERAGE(IF(Data[Poster]=$B15, IF(Data[Date]> TODAY()-$E$9, IF(INDIRECT(_xlfn.CONCAT("Data[", C$10, "]"))>0, INDIRECT(_xlfn.CONCAT("Data[", C$10, "]"))))))} -> 3.25 | D15: {=AVERAGE(IF(Data[Poster]=$B15, IF(Data[Date]> TODAY()-$E$9, IF(INDIRECT(_xlfn.CONCAT("Data[", D$10, "]"))>0, INDIRECT(_xlfn.CONCAT("Data[", D$10, "]"))))))} -> 2.875 | E15: {=AVERAGE(IF(Data[Poster]=$B15, IF(Data[Date]> TODAY()-$E$9, IF(INDIRECT(_xlfn.CONCAT("Data[", E$10, "]"))>0, INDIRECT(_xlfn.CONCAT("Data[", E$10, "]"))))))} -> 3.0625 | F15: {=AVERAGE(IF(Data[Poster]=$B15, IF(Data[Date]> TODAY()-$E$9, IF(INDIRECT(_xlfn.CONCAT("Data[", F$10, "]"))>0, INDIRECT(_xlfn.CONCAT("Data[", F$10, "]"))))))} -> 3.6875 | G15: {=AVERAGE(IF(Data[Poster]=$B15, IF(Data[Date]> TODAY()-$E$9, IF(INDIRECT(_xlfn.CONCAT("Data[", G$10, "]"))>0, INDIRECT(_xlfn.CONCAT("Data[", G$10, "]"))))))} -> 1.625 | I15: =Rankings!$N$1 -> currydestroyer27 | J15: {=MEDIAN(IF(Data[Poster]=$I15, IF(Data[Date]> TODAY()-$L$9, IF(INDIRECT(_xlfn.CONCAT("Data[", J$10, "]"))>0, INDIRECT(_xlfn.CONCAT("Data[", J$10, "]"))))))} -> 3 | K15: {=MEDIAN(IF(Data[Poster]=$I15, IF(Data[Date]> TODAY()-$L$9, IF(INDIRECT(_xlfn.CONCAT("Data[", K$10, "]"))>0, INDIRECT(_xlfn.CONCAT("Data[", K$10, "]"))))))} -> 3 | L15: {=MEDIAN(IF(Data[Poster]=$I15, IF(Data[Date]> TODAY()-$L$9, IF(INDIRECT(_xlfn.CONCAT("Data[", L$10, "]"))>0, INDIRECT(_xlfn.CONCAT("Data[", L$10, "]"))))))} -> 3 | M15: {=MEDIAN(IF(Data[Poster]=$I15, IF(Data[Date]> TODAY()-$L$9, IF(INDIRECT(_xlfn.CONCAT("Data[", M$10, "]"))>0, INDIRECT(_xlfn.CONCAT("Data[", M$10, "]"))))))} -> 4 | N15: {=MEDIAN(IF(Data[Poster]=$I15, IF(Data[Date]> TODAY()-$L$9, IF(INDIRECT(_xlfn.CONCAT("Data[", N$10, "]"))>0, INDIRECT(_xlfn.CONCAT("Data[", N$10, "]"))))))} -> 1 | P15: =Rankings!$N$1 -> currydestroyer27 | Q15: =COUNTIFS(Data[Date],">"&TODAY()-$T$9,Data[Poster],$P15,INDIRECT(_xlfn.CONCAT("Data[", Q$10, "]")),$P$9) -> 18 | R15: =COUNTIFS(Data[Date],">"&TODAY()-$T$9,Data[Poster],$P15,INDIRECT(_xlfn.CONCAT("Data[", R$10, "]")),$P$9) -> 57 | S15: =COUNTIFS(Data[Date],">"&TODAY()-$T$9,Data[Poster],$P15,INDIRECT(_xlfn.CONCAT("Data[", S$10, "]")),$P$9) -> 65 | T15: =COUNTIFS(Data[Date],">"&TODAY()-$T$9,Data[Poster],$P15,INDIRECT(_xlfn.CONCAT("Data[", T$10, "]")),$P$9) -> 19 | U15: =COUNTIFS(Data[Date],">"&TODAY()-$T$9,Data[Poster],$P15,INDIRECT(_xlfn.CONCAT("Data[", U$10, "]")),$P$9) -> 335 | V15: =SUM(Q15:U15) -> 494 | X15: =Rankings!$N$1 -> currydestroyer27 | Y15: =COUNTIFS(Data[Date],">"&TODAY()-$AB$9,Data[Poster],$X15,INDIRECT(_xlfn.CONCAT("Data[", Y$10, "]")),$X$9) -> 120 | Z15: =COUNTIFS(Data[Date],">"&TODAY()-$AB$9,Data[Poster],$X15,INDIRECT(_xlfn.CONCAT("Data[", Z$10, "]")),$X$9) -> 103 | AA15: =COUNTIFS(Data[Date],">"&TODAY()-$AB$9,Data[Poster],$X15,INDIRECT(_xlfn.CONCAT("Data[", AA$10, "]")),$X$9) -> 106 | AB15: =COUNTIFS(Data[Date],">"&TODAY()-$AB$9,Data[Poster],$X15,INDIRECT(_xlfn.CONCAT("Data[", AB$10, "]")),$X$9) -> 84 | AC15: =COUNTIFS(Data[Date],">"&TODAY()-$AB$9,Data[Poster],$X15,INDIRECT(_xlfn.CONCAT("Data[", AC$10, "]")),$X$9) -> 62 | AD15: =SUM(Y15:AC15) -> 475
B17: Standard Deviation for past | E17: 28 | F17: days | I17: Mode Rank for past | L17: 28 | M17: days | P17: 3 | Q17: =_xlfn.CONCAT("Amount of ",P17,"'s given for past") -> Amount of 3's given for past | T17: 1000 | U17: days | V17: Sum | X17: 4 | Y17: =_xlfn.CONCAT("Amount of ",X17,"'s given for past") -> Amount of 4's given for past | AB17: 1000 | AC17: days | AD17: Sum
B18: Poster\Voter | C18: =Rankings!$J$1 -> alappatjoe | D18: =Rankings!$K$1 -> danram | E18: =Rankings!$L$1 -> loganworsdell | F18: =Rankings!$M$1 -> samuelbattista | G18: =Rankings!$N$1 -> currydestroyer27 | I18: Poster\Voter | J18: =Rankings!$J$1 -> alappatjoe | K18: =Rankings!$K$1 -> danram | L18: =Rankings!$L$1 -> loganworsdell | M18: =Rankings!$M$1 -> samuelbattista | N18: =Rankings!$N$1 -> currydestroyer27 | P18: Poster\Voter | Q18: =Rankings!$J$1 -> alappatjoe | R18: =Rankings!$K$1 -> danram | S18: =Rankings!$L$1 -> loganworsdell | T18: =Rankings!$M$1 -> samuelbattista | U18: =Rankings!$N$1 -> currydestroyer27 | X18: Poster\Voter | Y18: =Rankings!$J$1 -> alappatjoe | Z18: =Rankings!$K$1 -> danram | AA18: =Rankings!$L$1 -> loganworsdell | AB18: =Rankings!$M$1 -> samuelbattista | AC18: =Rankings!$N$1 -> currydestroyer27
B19: =Rankings!$J$1 -> alappatjoe | C19: {=_xlfn.STDEV.P(IF(Data[Poster]=$B19, IF(Data[Date]> TODAY()-$E$17, IF(INDIRECT(_xlfn.CONCAT("Data[", C$18, "]"))>0, INDIRECT(_xlfn.CONCAT("Data[", C$18, "]"))))))} -> 0.85695683 | D19: {=_xlfn.STDEV.P(IF(Data[Poster]=$B19, IF(Data[Date]> TODAY()-$E$17, IF(INDIRECT(_xlfn.CONCAT("Data[", D$18, "]"))>0, INDIRECT(_xlfn.CONCAT("Data[", D$18, "]"))))))} -> 1.2231491 | E19: {=_xlfn.STDEV.P(IF(Data[Poster]=$B19, IF(Data[Date]> TODAY()-$E$17, IF(INDIRECT(_xlfn.CONCAT("Data[", E$18, "]"))>0, INDIRECT(_xlfn.CONCAT("Data[", E$18, "]"))))))} -> 1.457738 | F19: {=_xlfn.STDEV.P(IF(Data[Poster]=$B19, IF(Data[Date]> TODAY()-$E$17, IF(INDIRECT(_xlfn.CONCAT("Data[", F$18, "]"))>0, INDIRECT(_xlfn.CONCAT("Data[", F$18, "]"))))))} -> 0.86376719 | G19: {=_xlfn.STDEV.P(IF(Data[Poster]=$B19, IF(Data[Date]> TODAY()-$E$17, IF(INDIRECT(_xlfn.CONCAT("Data[", G$18, "]"))>0, INDIRECT(_xlfn.CONCAT("Data[", G$18, "]"))))))} -> 1.1439378 | I19: =Rankings!$J$1 -> alappatjoe | J19: {=MODE(IF(Data[Poster]=$I19, IF(Data[Date]> TODAY()-$L$17, IF(INDIRECT(_xlfn.CONCAT("Data[", J$18, "]"))>0, INDIRECT(_xlfn.CONCAT("Data[", J$18, "]"))))))} -> 1 | K19: {=MODE(IF(Data[Poster]=$I19, IF(Data[Date]> TODAY()-$L$17, IF(INDIRECT(_xlfn.CONCAT("Data[", K$18, "]"))>0, INDIRECT(_xlfn.CONCAT("Data[", K$18, "]"))))))} -> 3 | L19: {=MODE(IF(Data[Poster]=$I19, IF(Data[Date]> TODAY()-$L$17, IF(INDIRECT(_xlfn.CONCAT("Data[", L$18, "]"))>0, INDIRECT(_xlfn.CONCAT("Data[", L$18, "]"))))))} -> 4 | M19: {=MODE(IF(Data[Poster]=$I19, IF(Data[Date]> TODAY()-$L$17, IF(INDIRECT(_xlfn.CONCAT("Data[", M$18, "]"))>0, INDIRECT(_xlfn.CONCAT("Data[", M$18, "]"))))))} -> 4 | N19: {=MODE(IF(Data[Poster]=$I19, IF(Data[Date]> TODAY()-$L$17, IF(INDIRECT(_xlfn.CONCAT("Data[", N$18, "]"))>0, INDIRECT(_xlfn.CONCAT("Data[", N$18, "]"))))))} -> 2 | P19: =Rankings!$J$1 -> alappatjoe | Q19: =COUNTIFS(Data[Date],">"&TODAY()-$T$17,Data[Poster],$P19,INDIRECT(_xlfn.CONCAT("Data[", Q$18, "]")),$P$17) -> 19 | R19: =COUNTIFS(Data[Date],">"&TODAY()-$T$17,Data[Poster],$P19,INDIRECT(_xlfn.CONCAT("Data[", R$18, "]")),$P$17) -> 73 | S19: =COUNTIFS(Data[Date],">"&TODAY()-$T$17,Data[Poster],$P19,INDIRECT(_xlfn.CONCAT("Data[", S$18, "]")),$P$17) -> 87 | T19: =COUNTIFS(Data[Date],">"&TODAY()-$T$17,Data[Poster],$P19,INDIRECT(_xlfn.CONCAT("Data[", T$18, "]")),$P$17) -> 98 | U19: =COUNTIFS(Data[Date],">"&TODAY()-$T$17,Data[Poster],$P19,INDIRECT(_xlfn.CONCAT("Data[", U$18, "]")),$P$17) -> 97 | V19: =SUM(Q19:U19) -> 374 | X19: =Rankings!$J$1 -> alappatjoe | Y19: =COUNTIFS(Data[Date],">"&TODAY()-$AB$17,Data[Poster],$X19,INDIRECT(_xlfn.CONCAT("Data[", Y$18, "]")),$X$17) -> 3 | Z19: =COUNTIFS(Data[Date],">"&TODAY()-$AB$17,Data[Poster],$X19,INDIRECT(_xlfn.CONCAT("Data[", Z$18, "]")),$X$17) -> 125 | AA19: =COUNTIFS(Data[Date],">"&TODAY()-$AB$17,Data[Poster],$X19,INDIRECT(_xlfn.CONCAT("Data[", AA$18, "]")),$X$17) -> 131 | AB19: =COUNTIFS(Data[Date],">"&TODAY()-$AB$17,Data[Poster],$X19,INDIRECT(_xlfn.CONCAT("Data[", AB$18, "]")),$X$17) -> 126 | AC19: =COUNTIFS(Data[Date],">"&TODAY()-$AB$17,Data[Poster],$X19,INDIRECT(_xlfn.CONCAT("Data[", AC$18, "]")),$X$17) -> 100 | AD19: =SUM(Y19:AC19) -> 485
B20: =Rankings!$K$1 -> danram | C20: {=_xlfn.STDEV.P(IF(Data[Poster]=$B20, IF(Data[Date]> TODAY()-$E$17, IF(INDIRECT(_xlfn.CONCAT("Data[", C$18, "]"))>0, INDIRECT(_xlfn.CONCAT("Data[", C$18, "]"))))))} -> 1.1021995 | D20: {=_xlfn.STDEV.P(IF(Data[Poster]=$B20, IF(Data[Date]> TODAY()-$E$17, IF(INDIRECT(_xlfn.CONCAT("Data[", D$18, "]"))>0, INDIRECT(_xlfn.CONCAT("Data[", D$18, "]"))))))} -> 1.5612495 | E20: {=_xlfn.STDEV.P(IF(Data[Poster]=$B20, IF(Data[Date]> TODAY()-$E$17, IF(INDIRECT(_xlfn.CONCAT("Data[", E$18, "]"))>0, INDIRECT(_xlfn.CONCAT("Data[", E$18, "]"))))))} -> 1.2975337 | F20: {=_xlfn.STDEV.P(IF(Data[Poster]=$B20, IF(Data[Date]> TODAY()-$E$17, IF(INDIRECT(_xlfn.CONCAT("Data[", F$18, "]"))>0, INDIRECT(_xlfn.CONCAT("Data[", F$18, "]"))))))} -> 1.6286018 | G20: {=_xlfn.STDEV.P(IF(Data[Poster]=$B20, IF(Data[Date]> TODAY()-$E$17, IF(INDIRECT(_xlfn.CONCAT("Data[", G$18, "]"))>0, INDIRECT(_xlfn.CONCAT("Data[", G$18, "]"))))))} -> 1.3678793 | I20: =Rankings!$K$1 -> danram | J20: {=MODE(IF(Data[Poster]=$I20, IF(Data[Date]> TODAY()-$L$17, IF(INDIRECT(_xlfn.CONCAT("Data[", J$18, "]"))>0, INDIRECT(_xlfn.CONCAT("Data[", J$18, "]"))))))} -> 5 | K20: {=MODE(IF(Data[Poster]=$I20, IF(Data[Date]> TODAY()-$L$17, IF(INDIRECT(_xlfn.CONCAT("Data[", K$18, "]"))>0, INDIRECT(_xlfn.CONCAT("Data[", K$18, "]"))))))} -> 1 | L20: {=MODE(IF(Data[Poster]=$I20, IF(Data[Date]> TODAY()-$L$17, IF(INDIRECT(_xlfn.CONCAT("Data[", L$18, "]"))>0, INDIRECT(_xlfn.CONCAT("Data[", L$18, "]"))))))} -> 5 | M20: {=MODE(IF(Data[Poster]=$I20, IF(Data[Date]> TODAY()-$L$17, IF(INDIRECT(_xlfn.CONCAT("Data[", M$18, "]"))>0, INDIRECT(_xlfn.CONCAT("Data[", M$18, "]"))))))} -> 2 | N20: {=MODE(IF(Data[Poster]=$I20, IF(Data[Date]> TODAY()-$L$17, IF(INDIRECT(_xlfn.CONCAT("Data[", N$18, "]"))>0, INDIRECT(_xlfn.CONCAT("Data[", N$18, "]"))))))} -> 5 | P20: =Rankings!$K$1 -> danram | Q20: =COUNTIFS(Data[Date],">"&TODAY()-$T$17,Data[Poster],$P20,INDIRECT(_xlfn.CONCAT("Data[", Q$18, "]")),$P$17) -> 112 | R20: =COUNTIFS(Data[Date],">"&TODAY()-$T$17,Data[Poster],$P20,INDIRECT(_xlfn.CONCAT("Data[", R$18, "]")),$P$17) -> 65 | S20: =COUNTIFS(Data[Date],">"&TODAY()-$T$17,Data[Poster],$P20,INDIRECT(_xlfn.CONCAT("Data[", S$18, "]")),$P$17) -> 84 | T20: =COUNTIFS(Data[Date],">"&TODAY()-$T$17,Data[Poster],$P20,INDIRECT(_xlfn.CONCAT("Data[", T$18, "]")),$P$17) -> 100 | U20: =COUNTIFS(Data[Date],">"&TODAY()-$T$17,Data[Poster],$P20,INDIRECT(_xlfn.CONCAT("Data[", U$18, "]")),$P$17) -> 94 | V20: =SUM(Q20:U20) -> 455 | X20: =Rankings!$K$1 -> danram | Y20: =COUNTIFS(Data[Date],">"&TODAY()-$AB$17,Data[Poster],$X20,INDIRECT(_xlfn.CONCAT("Data[", Y$18, "]")),$X$17) -> 103 | Z20: =COUNTIFS(Data[Date],">"&TODAY()-$AB$17,Data[Poster],$X20,INDIRECT(_xlfn.CONCAT("Data[", Z$18, "]")),$X$17) -> 28 | AA20: =COUNTIFS(Data[Date],">"&TODAY()-$AB$17,Data[Poster],$X20,INDIRECT(_xlfn.CONCAT("Data[", AA$18, "]")),$X$17) -> 113 | AB20: =COUNTIFS(Data[Date],">"&TODAY()-$AB$17,Data[Poster],$X20,INDIRECT(_xlfn.CONCAT("Data[", AB$18, "]")),$X$17) -> 89 | AC20: =COUNTIFS(Data[Date],">"&TODAY()-$AB$17,Data[Poster],$X20,INDIRECT(_xlfn.CONCAT("Data[", AC$18, "]")),$X$17) -> 110 | AD20: =SUM(Y20:AC20) -> 443
B21: =Rankings!$L$1 -> loganworsdell | C21: {=_xlfn.STDEV.P(IF(Data[Poster]=$B21, IF(Data[Date]> TODAY()-$E$17, IF(INDIRECT(_xlfn.CONCAT("Data[", C$18, "]"))>0, INDIRECT(_xlfn.CONCAT("Data[", C$18, "]"))))))} -> 1.3448397 | D21: {=_xlfn.STDEV.P(IF(Data[Poster]=$B21, IF(Data[Date]> TODAY()-$E$17, IF(INDIRECT(_xlfn.CONCAT("Data[", D$18, "]"))>0, INDIRECT(_xlfn.CONCAT("Data[", D$18, "]"))))))} -> 1.3792548 | E21: {=_xlfn.STDEV.P(IF(Data[Poster]=$B21, IF(Data[Date]> TODAY()-$E$17, IF(INDIRECT(_xlfn.CONCAT("Data[", E$18, "]"))>0, INDIRECT(_xlfn.CONCAT("Data[", E$18, "]"))))))} -> 0.881671 | F21: {=_xlfn.STDEV.P(IF(Data[Poster]=$B21, IF(Data[Date]> TODAY()-$E$17, IF(INDIRECT(_xlfn.CONCAT("Data[", F$18, "]"))>0, INDIRECT(_xlfn.CONCAT("Data[", F$18, "]"))))))} -> 1 | G21: {=_xlfn.STDEV.P(IF(Data[Poster]=$B21, IF(Data[Date]> TODAY()-$E$17, IF(INDIRECT(_xlfn.CONCAT("Data[", G$18, "]"))>0, INDIRECT(_xlfn.CONCAT("Data[", G$18, "]"))))))} -> 1.0588171 | I21: =Rankings!$L$1 -> loganworsdell | J21: {=MODE(IF(Data[Poster]=$I21, IF(Data[Date]> TODAY()-$L$17, IF(INDIRECT(_xlfn.CONCAT("Data[", J$18, "]"))>0, INDIRECT(_xlfn.CONCAT("Data[", J$18, "]"))))))} -> 2 | K21: {=MODE(IF(Data[Poster]=$I21, IF(Data[Date]> TODAY()-$L$17, IF(INDIRECT(_xlfn.CONCAT("Data[", K$18, "]"))>0, INDIRECT(_xlfn.CONCAT("Data[", K$18, "]"))))))} -> 2 | L21: {=MODE(IF(Data[Poster]=$I21, IF(Data[Date]> TODAY()-$L$17, IF(INDIRECT(_xlfn.CONCAT("Data[", L$18, "]"))>0, INDIRECT(_xlfn.CONCAT("Data[", L$18, "]"))))))} -> 1 | M21: {=MODE(IF(Data[Poster]=$I21, IF(Data[Date]> TODAY()-$L$17, IF(INDIRECT(_xlfn.CONCAT("Data[", M$18, "]"))>0, INDIRECT(_xlfn.CONCAT("Data[", M$18, "]"))))))} -> 3 | N21: {=MODE(IF(Data[Poster]=$I21, IF(Data[Date]> TODAY()-$L$17, IF(INDIRECT(_xlfn.CONCAT("Data[", N$18, "]"))>0, INDIRECT(_xlfn.CONCAT("Data[", N$18, "]"))))))} -> 3 | P21: =Rankings!$L$1 -> loganworsdell | Q21: =COUNTIFS(Data[Date],">"&TODAY()-$T$17,Data[Poster],$P21,INDIRECT(_xlfn.CONCAT("Data[", Q$18, "]")),$P$17) -> 108 | R21: =COUNTIFS(Data[Date],">"&TODAY()-$T$17,Data[Poster],$P21,INDIRECT(_xlfn.CONCAT("Data[", R$18, "]")),$P$17) -> 98 | S21: =COUNTIFS(Data[Date],">"&TODAY()-$T$17,Data[Poster],$P21,INDIRECT(_xlfn.CONCAT("Data[", S$18, "]")),$P$17) -> 68 | T21: =COUNTIFS(Data[Date],">"&TODAY()-$T$17,Data[Poster],$P21,INDIRECT(_xlfn.CONCAT("Data[", T$18, "]")),$P$17) -> 131 | U21: =COUNTIFS(Data[Date],">"&TODAY()-$T$17,Data[Poster],$P21,INDIRECT(_xlfn.CONCAT("Data[", U$18, "]")),$P$17) -> 115 | V21: =SUM(Q21:U21) -> 520 | X21: =Rankings!$L$1 -> loganworsdell | Y21: =COUNTIFS(Data[Date],">"&TODAY()-$AB$17,Data[Poster],$X21,INDIRECT(_xlfn.CONCAT("Data[", Y$18, "]")),$X$17) -> 105 | Z21: =COUNTIFS(Data[Date],">"&TODAY()-$AB$17,Data[Poster],$X21,INDIRECT(_xlfn.CONCAT("Data[", Z$18, "]")),$X$17) -> 116 | AA21: =COUNTIFS(Data[Date],">"&TODAY()-$AB$17,Data[Poster],$X21,INDIRECT(_xlfn.CONCAT("Data[", AA$18, "]")),$X$17) -> 27 | AB21: =COUNTIFS(Data[Date],">"&TODAY()-$AB$17,Data[Poster],$X21,INDIRECT(_xlfn.CONCAT("Data[", AB$18, "]")),$X$17) -> 107 | AC21: =COUNTIFS(Data[Date],">"&TODAY()-$AB$17,Data[Poster],$X21,INDIRECT(_xlfn.CONCAT("Data[", AC$18, "]")),$X$17) -> 108 | AD21: =SUM(Y21:AC21) -> 463
B22: =Rankings!$M$1 -> samuelbattista | C22: {=_xlfn.STDEV.P(IF(Data[Poster]=$B22, IF(Data[Date]> TODAY()-$E$17, IF(INDIRECT(_xlfn.CONCAT("Data[", C$18, "]"))>0, INDIRECT(_xlfn.CONCAT("Data[", C$18, "]"))))))} -> 1.1659224 | D22: {=_xlfn.STDEV.P(IF(Data[Poster]=$B22, IF(Data[Date]> TODAY()-$E$17, IF(INDIRECT(_xlfn.CONCAT("Data[", D$18, "]"))>0, INDIRECT(_xlfn.CONCAT("Data[", D$18, "]"))))))} -> 1.25 | E22: {=_xlfn.STDEV.P(IF(Data[Poster]=$B22, IF(Data[Date]> TODAY()-$E$17, IF(INDIRECT(_xlfn.CONCAT("Data[", E$18, "]"))>0, INDIRECT(_xlfn.CONCAT("Data[", E$18, "]"))))))} -> 1.43478 | F22: {=_xlfn.STDEV.P(IF(Data[Poster]=$B22, IF(Data[Date]> TODAY()-$E$17, IF(INDIRECT(_xlfn.CONCAT("Data[", F$18, "]"))>0, INDIRECT(_xlfn.CONCAT("Data[", F$18, "]"))))))} -> 0.99804496 | G22: {=_xlfn.STDEV.P(IF(Data[Poster]=$B22, IF(Data[Date]> TODAY()-$E$17, IF(INDIRECT(_xlfn.CONCAT("Data[", G$18, "]"))>0, INDIRECT(_xlfn.CONCAT("Data[", G$18, "]"))))))} -> 1.4456292 | I22: =Rankings!$M$1 -> samuelbattista | J22: {=MODE(IF(Data[Poster]=$I22, IF(Data[Date]> TODAY()-$L$17, IF(INDIRECT(_xlfn.CONCAT("Data[", J$18, "]"))>0, INDIRECT(_xlfn.CONCAT("Data[", J$18, "]"))))))} -> 5 | K22: {=MODE(IF(Data[Poster]=$I22, IF(Data[Date]> TODAY()-$L$17, IF(INDIRECT(_xlfn.CONCAT("Data[", K$18, "]"))>0, INDIRECT(_xlfn.CONCAT("Data[", K$18, "]"))))))} -> 3 | L22: {=MODE(IF(Data[Poster]=$I22, IF(Data[Date]> TODAY()-$L$17, IF(INDIRECT(_xlfn.CONCAT("Data[", L$18, "]"))>0, INDIRECT(_xlfn.CONCAT("Data[", L$18, "]"))))))} -> 4 | M22: {=MODE(IF(Data[Poster]=$I22, IF(Data[Date]> TODAY()-$L$17, IF(INDIRECT(_xlfn.CONCAT("Data[", M$18, "]"))>0, INDIRECT(_xlfn.CONCAT("Data[", M$18, "]"))))))} -> 1 | N22: {=MODE(IF(Data[Poster]=$I22, IF(Data[Date]> TODAY()-$L$17, IF(INDIRECT(_xlfn.CONCAT("Data[", N$18, "]"))>0, INDIRECT(_xlfn.CONCAT("Data[", N$18, "]"))))))} -> 5 | P22: =Rankings!$M$1 -> samuelbattista | Q22: =COUNTIFS(Data[Date],">"&TODAY()-$T$17,Data[Poster],$P22,INDIRECT(_xlfn.CONCAT("Data[", Q$18, "]")),$P$17) -> 98 | R22: =COUNTIFS(Data[Date],">"&TODAY()-$T$17,Data[Poster],$P22,INDIRECT(_xlfn.CONCAT("Data[", R$18, "]")),$P$17) -> 110 | S22: =COUNTIFS(Data[Date],">"&TODAY()-$T$17,Data[Poster],$P22,INDIRECT(_xlfn.CONCAT("Data[", S$18, "]")),$P$17) -> 95 | T22: =COUNTIFS(Data[Date],">"&TODAY()-$T$17,Data[Poster],$P22,INDIRECT(_xlfn.CONCAT("Data[", T$18, "]")),$P$17) -> 16 | U22: =COUNTIFS(Data[Date],">"&TODAY()-$T$17,Data[Poster],$P22,INDIRECT(_xlfn.CONCAT("Data[", U$18, "]")),$P$17) -> 112 | V22: =SUM(Q22:U22) -> 431 | X22: =Rankings!$M$1 -> samuelbattista | Y22: =COUNTIFS(Data[Date],">"&TODAY()-$AB$17,Data[Poster],$X22,INDIRECT(_xlfn.CONCAT("Data[", Y$18, "]")),$X$17) -> 109 | Z22: =COUNTIFS(Data[Date],">"&TODAY()-$AB$17,Data[Poster],$X22,INDIRECT(_xlfn.CONCAT("Data[", Z$18, "]")),$X$17) -> 96 | AA22: =COUNTIFS(Data[Date],">"&TODAY()-$AB$17,Data[Poster],$X22,INDIRECT(_xlfn.CONCAT("Data[", AA$18, "]")),$X$17) -> 90 | AB22: =COUNTIFS(Data[Date],">"&TODAY()-$AB$17,Data[Poster],$X22,INDIRECT(_xlfn.CONCAT("Data[", AB$18, "]")),$X$17) -> 3 | AC22: =COUNTIFS(Data[Date],">"&TODAY()-$AB$17,Data[Poster],$X22,INDIRECT(_xlfn.CONCAT("Data[", AC$18, "]")),$X$17) -> 109 | AD22: =SUM(Y22:AC22) -> 407
B23: =Rankings!$N$1 -> currydestroyer27 | C23: {=_xlfn.STDEV.P(IF(Data[Poster]=$B23, IF(Data[Date]> TODAY()-$E$17, IF(INDIRECT(_xlfn.CONCAT("Data[", C$18, "]"))>0, INDIRECT(_xlfn.CONCAT("Data[", C$18, "]"))))))} -> 1.1456439 | D23: {=_xlfn.STDEV.P(IF(Data[Poster]=$B23, IF(Data[Date]> TODAY()-$E$17, IF(INDIRECT(_xlfn.CONCAT("Data[", D$18, "]"))>0, INDIRECT(_xlfn.CONCAT("Data[", D$18, "]"))))))} -> 1.3169567 | E23: {=_xlfn.STDEV.P(IF(Data[Poster]=$B23, IF(Data[Date]> TODAY()-$E$17, IF(INDIRECT(_xlfn.CONCAT("Data[", E$18, "]"))>0, INDIRECT(_xlfn.CONCAT("Data[", E$18, "]"))))))} -> 0.89921841 | F23: {=_xlfn.STDEV.P(IF(Data[Poster]=$B23, IF(Data[Date]> TODAY()-$E$17, IF(INDIRECT(_xlfn.CONCAT("Data[", F$18, "]"))>0, INDIRECT(_xlfn.CONCAT("Data[", F$18, "]"))))))} -> 1.0439558 | G23: {=_xlfn.STDEV.P(IF(Data[Poster]=$B23, IF(Data[Date]> TODAY()-$E$17, IF(INDIRECT(_xlfn.CONCAT("Data[", G$18, "]"))>0, INDIRECT(_xlfn.CONCAT("Data[", G$18, "]"))))))} -> 1.0532687 | I23: =Rankings!$N$1 -> currydestroyer27 | J23: {=MODE(IF(Data[Poster]=$I23, IF(Data[Date]> TODAY()-$L$17, IF(INDIRECT(_xlfn.CONCAT("Data[", J$18, "]"))>0, INDIRECT(_xlfn.CONCAT("Data[", J$18, "]"))))))} -> 3 | K23: {=MODE(IF(Data[Poster]=$I23, IF(Data[Date]> TODAY()-$L$17, IF(INDIRECT(_xlfn.CONCAT("Data[", K$18, "]"))>0, INDIRECT(_xlfn.CONCAT("Data[", K$18, "]"))))))} -> 2 | L23: {=MODE(IF(Data[Poster]=$I23, IF(Data[Date]> TODAY()-$L$17, IF(INDIRECT(_xlfn.CONCAT("Data[", L$18, "]"))>0, INDIRECT(_xlfn.CONCAT("Data[", L$18, "]"))))))} -> 3 | M23: {=MODE(IF(Data[Poster]=$I23, IF(Data[Date]> TODAY()-$L$17, IF(INDIRECT(_xlfn.CONCAT("Data[", M$18, "]"))>0, INDIRECT(_xlfn.CONCAT("Data[", M$18, "]"))))))} -> 4 | N23: {=MODE(IF(Data[Poster]=$I23, IF(Data[Date]> TODAY()-$L$17, IF(INDIRECT(_xlfn.CONCAT("Data[", N$18, "]"))>0, INDIRECT(_xlfn.CONCAT("Data[", N$18, "]"))))))} -> 1 | P23: =Rankings!$N$1 -> currydestroyer27 | Q23: =COUNTIFS(Data[Date],">"&TODAY()-$T$17,Data[Poster],$P23,INDIRECT(_xlfn.CONCAT("Data[", Q$18, "]")),$P$17) -> 108 | R23: =COUNTIFS(Data[Date],">"&TODAY()-$T$17,Data[Poster],$P23,INDIRECT(_xlfn.CONCAT("Data[", R$18, "]")),$P$17) -> 99 | S23: =COUNTIFS(Data[Date],">"&TODAY()-$T$17,Data[Poster],$P23,INDIRECT(_xlfn.CONCAT("Data[", S$18, "]")),$P$17) -> 111 | T23: =COUNTIFS(Data[Date],">"&TODAY()-$T$17,Data[Poster],$P23,INDIRECT(_xlfn.CONCAT("Data[", T$18, "]")),$P$17) -> 100 | U23: =COUNTIFS(Data[Date],">"&TODAY()-$T$17,Data[Poster],$P23,INDIRECT(_xlfn.CONCAT("Data[", U$18, "]")),$P$17) -> 27 | V23: =SUM(Q23:U23) -> 445 | X23: =Rankings!$N$1 -> currydestroyer27 | Y23: =COUNTIFS(Data[Date],">"&TODAY()-$AB$17,Data[Poster],$X23,INDIRECT(_xlfn.CONCAT("Data[", Y$18, "]")),$X$17) -> 125 | Z23: =COUNTIFS(Data[Date],">"&TODAY()-$AB$17,Data[Poster],$X23,INDIRECT(_xlfn.CONCAT("Data[", Z$18, "]")),$X$17) -> 80 | AA23: =COUNTIFS(Data[Date],">"&TODAY()-$AB$17,Data[Poster],$X23,INDIRECT(_xlfn.CONCAT("Data[", AA$18, "]")),$X$17) -> 84 | AB23: =COUNTIFS(Data[Date],">"&TODAY()-$AB$17,Data[Poster],$X23,INDIRECT(_xlfn.CONCAT("Data[", AB$18, "]")),$X$17) -> 120 | AC23: =COUNTIFS(Data[Date],">"&TODAY()-$AB$17,Data[Poster],$X23,INDIRECT(_xlfn.CONCAT("Data[", AC$18, "]")),$X$17) -> 18 | AD23: =SUM(Y23:AC23) -> 427
B25: Best Rank for past | E25: 28 | F25: days | I25: Worst Rank for past | L25: 28 | M25: days | P25: 5 | Q25: =_xlfn.CONCAT("Amount of ",P25,"'s given for past") -> Amount of 5's given for past | T25: 1000 | U25: days | V25: Sum
B26: Poster\Voter | C26: =Rankings!$J$1 -> alappatjoe | D26: =Rankings!$K$1 -> danram | E26: =Rankings!$L$1 -> loganworsdell | F26: =Rankings!$M$1 -> samuelbattista | G26: =Rankings!$N$1 -> currydestroyer27 | I26: Poster\Voter | J26: =Rankings!$J$1 -> alappatjoe | K26: =Rankings!$K$1 -> danram | L26: =Rankings!$L$1 -> loganworsdell | M26: =Rankings!$M$1 -> samuelbattista | N26: =Rankings!$N$1 -> currydestroyer27 | P26: Poster\Voter | Q26: =Rankings!$J$1 -> alappatjoe | R26: =Rankings!$K$1 -> danram | S26: =Rankings!$L$1 -> loganworsdell | T26: =Rankings!$M$1 -> samuelbattista | U26: =Rankings!$N$1 -> currydestroyer27
B27: =Rankings!$J$1 -> alappatjoe | C27: {=MIN(IF(Data[Poster]=$B27, IF(Data[Date]> TODAY()-$E$25, IF(INDIRECT(_xlfn.CONCAT("Data[", C$26, "]"))>0, INDIRECT(_xlfn.CONCAT("Data[", C$26, "]"))))))} -> 1 | D27: {=MIN(IF(Data[Poster]=$B27, IF(Data[Date]> TODAY()-$E$25, IF(INDIRECT(_xlfn.CONCAT("Data[", D$26, "]"))>0, INDIRECT(_xlfn.CONCAT("Data[", D$26, "]"))))))} -> 1 | E27: {=MIN(IF(Data[Poster]=$B27, IF(Data[Date]> TODAY()-$E$25, IF(INDIRECT(_xlfn.CONCAT("Data[", E$26, "]"))>0, INDIRECT(_xlfn.CONCAT("Data[", E$26, "]"))))))} -> 1 | F27: {=MIN(IF(Data[Poster]=$B27, IF(Data[Date]> TODAY()-$E$25, IF(INDIRECT(_xlfn.CONCAT("Data[", F$26, "]"))>0, INDIRECT(_xlfn.CONCAT("Data[", F$26, "]"))))))} -> 2 | G27: {=MIN(IF(Data[Poster]=$B27, IF(Data[Date]> TODAY()-$E$25, IF(INDIRECT(_xlfn.CONCAT("Data[", G$26, "]"))>0, INDIRECT(_xlfn.CONCAT("Data[", G$26, "]"))))))} -> 1 | I27: =Rankings!$J$1 -> alappatjoe | J27: {=MAX(IF(Data[Poster]=$I27, IF(Data[Date]> TODAY()-$L$25, IF(INDIRECT(_xlfn.CONCAT("Data[", J$26, "]"))>0, INDIRECT(_xlfn.CONCAT("Data[", J$26, "]"))))))} -> 4 | K27: {=MAX(IF(Data[Poster]=$I27, IF(Data[Date]> TODAY()-$L$25, IF(INDIRECT(_xlfn.CONCAT("Data[", K$26, "]"))>0, INDIRECT(_xlfn.CONCAT("Data[", K$26, "]"))))))} -> 5 | L27: {=MAX(IF(Data[Poster]=$I27, IF(Data[Date]> TODAY()-$L$25, IF(INDIRECT(_xlfn.CONCAT("Data[", L$26, "]"))>0, INDIRECT(_xlfn.CONCAT("Data[", L$26, "]"))))))} -> 5 | M27: {=MAX(IF(Data[Poster]=$I27, IF(Data[Date]> TODAY()-$L$25, IF(INDIRECT(_xlfn.CONCAT("Data[", M$26, "]"))>0, INDIRECT(_xlfn.CONCAT("Data[", M$26, "]"))))))} -> 5 | N27: {=MAX(IF(Data[Poster]=$I27, IF(Data[Date]> TODAY()-$L$25, IF(INDIRECT(_xlfn.CONCAT("Data[", N$26, "]"))>0, INDIRECT(_xlfn.CONCAT("Data[", N$26, "]"))))))} -> 5 | P27: =Rankings!$J$1 -> alappatjoe | Q27: =COUNTIFS(Data[Date],">"&TODAY()-$T$25,Data[Poster],$P27,INDIRECT(_xlfn.CONCAT("Data[", Q$26, "]")),$P$25) -> 1 | R27: =COUNTIFS(Data[Date],">"&TODAY()-$T$25,Data[Poster],$P27,INDIRECT(_xlfn.CONCAT("Data[", R$26, "]")),$P$25) -> 150 | S27: =COUNTIFS(Data[Date],">"&TODAY()-$T$25,Data[Poster],$P27,INDIRECT(_xlfn.CONCAT("Data[", S$26, "]")),$P$25) -> 118 | T27: =COUNTIFS(Data[Date],">"&TODAY()-$T$25,Data[Poster],$P27,INDIRECT(_xlfn.CONCAT("Data[", T$26, "]")),$P$25) -> 127 | U27: =COUNTIFS(Data[Date],">"&TODAY()-$T$25,Data[Poster],$P27,INDIRECT(_xlfn.CONCAT("Data[", U$26, "]")),$P$25) -> 97 | V27: =SUM(Q27:U27) -> 493
B28: =Rankings!$K$1 -> danram | C28: {=MIN(IF(Data[Poster]=$B28, IF(Data[Date]> TODAY()-$E$25, IF(INDIRECT(_xlfn.CONCAT("Data[", C$26, "]"))>0, INDIRECT(_xlfn.CONCAT("Data[", C$26, "]"))))))} -> 2 | D28: {=MIN(IF(Data[Poster]=$B28, IF(Data[Date]> TODAY()-$E$25, IF(INDIRECT(_xlfn.CONCAT("Data[", D$26, "]"))>0, INDIRECT(_xlfn.CONCAT("Data[", D$26, "]"))))))} -> 1 | E28: {=MIN(IF(Data[Poster]=$B28, IF(Data[Date]> TODAY()-$E$25, IF(INDIRECT(_xlfn.CONCAT("Data[", E$26, "]"))>0, INDIRECT(_xlfn.CONCAT("Data[", E$26, "]"))))))} -> 1 | F28: {=MIN(IF(Data[Poster]=$B28, IF(Data[Date]> TODAY()-$E$25, IF(INDIRECT(_xlfn.CONCAT("Data[", F$26, "]"))>0, INDIRECT(_xlfn.CONCAT("Data[", F$26, "]"))))))} -> 1 | G28: {=MIN(IF(Data[Poster]=$B28, IF(Data[Date]> TODAY()-$E$25, IF(INDIRECT(_xlfn.CONCAT("Data[", G$26, "]"))>0, INDIRECT(_xlfn.CONCAT("Data[", G$26, "]"))))))} -> 1 | I28: =Rankings!$K$1 -> danram | J28: {=MAX(IF(Data[Poster]=$I28, IF(Data[Date]> TODAY()-$L$25, IF(INDIRECT(_xlfn.CONCAT("Data[", J$26, "]"))>0, INDIRECT(_xlfn.CONCAT("Data[", J$26, "]"))))))} -> 5 | K28: {=MAX(IF(Data[Poster]=$I28, IF(Data[Date]> TODAY()-$L$25, IF(INDIRECT(_xlfn.CONCAT("Data[", K$26, "]"))>0, INDIRECT(_xlfn.CONCAT("Data[", K$26, "]"))))))} -> 5 | L28: {=MAX(IF(Data[Poster]=$I28, IF(Data[Date]> TODAY()-$L$25, IF(INDIRECT(_xlfn.CONCAT("Data[", L$26, "]"))>0, INDIRECT(_xlfn.CONCAT("Data[", L$26, "]"))))))} -> 5 | M28: {=MAX(IF(Data[Poster]=$I28, IF(Data[Date]> TODAY()-$L$25, IF(INDIRECT(_xlfn.CONCAT("Data[", M$26, "]"))>0, INDIRECT(_xlfn.CONCAT("Data[", M$26, "]"))))))} -> 5 | N28: {=MAX(IF(Data[Poster]=$I28, IF(Data[Date]> TODAY()-$L$25, IF(INDIRECT(_xlfn.CONCAT("Data[", N$26, "]"))>0, INDIRECT(_xlfn.CONCAT("Data[", N$26, "]"))))))} -> 5 | P28: =Rankings!$K$1 -> danram | Q28: =COUNTIFS(Data[Date],">"&TODAY()-$T$25,Data[Poster],$P28,INDIRECT(_xlfn.CONCAT("Data[", Q$26, "]")),$P$25) -> 131 | R28: =COUNTIFS(Data[Date],">"&TODAY()-$T$25,Data[Poster],$P28,INDIRECT(_xlfn.CONCAT("Data[", R$26, "]")),$P$25) -> 24 | S28: =COUNTIFS(Data[Date],">"&TODAY()-$T$25,Data[Poster],$P28,INDIRECT(_xlfn.CONCAT("Data[", S$26, "]")),$P$25) -> 137 | T28: =COUNTIFS(Data[Date],">"&TODAY()-$T$25,Data[Poster],$P28,INDIRECT(_xlfn.CONCAT("Data[", T$26, "]")),$P$25) -> 103 | U28: =COUNTIFS(Data[Date],">"&TODAY()-$T$25,Data[Poster],$P28,INDIRECT(_xlfn.CONCAT("Data[", U$26, "]")),$P$25) -> 119 | V28: =SUM(Q28:U28) -> 514
B29: =Rankings!$L$1 -> loganworsdell | C29: {=MIN(IF(Data[Poster]=$B29, IF(Data[Date]> TODAY()-$E$25, IF(INDIRECT(_xlfn.CONCAT("Data[", C$26, "]"))>0, INDIRECT(_xlfn.CONCAT("Data[", C$26, "]"))))))} -> 1 | D29: {=MIN(IF(Data[Poster]=$B29, IF(Data[Date]> TODAY()-$E$25, IF(INDIRECT(_xlfn.CONCAT("Data[", D$26, "]"))>0, INDIRECT(_xlfn.CONCAT("Data[", D$26, "]"))))))} -> 1 | E29: {=MIN(IF(Data[Poster]=$B29, IF(Data[Date]> TODAY()-$E$25, IF(INDIRECT(_xlfn.CONCAT("Data[", E$26, "]"))>0, INDIRECT(_xlfn.CONCAT("Data[", E$26, "]"))))))} -> 1 | F29: {=MIN(IF(Data[Poster]=$B29, IF(Data[Date]> TODAY()-$E$25, IF(INDIRECT(_xlfn.CONCAT("Data[", F$26, "]"))>0, INDIRECT(_xlfn.CONCAT("Data[", F$26, "]"))))))} -> 2 | G29: {=MIN(IF(Data[Poster]=$B29, IF(Data[Date]> TODAY()-$E$25, IF(INDIRECT(_xlfn.CONCAT("Data[", G$26, "]"))>0, INDIRECT(_xlfn.CONCAT("Data[", G$26, "]"))))))} -> 1 | I29: =Rankings!$L$1 -> loganworsdell | J29: {=MAX(IF(Data[Poster]=$I29, IF(Data[Date]> TODAY()-$L$25, IF(INDIRECT(_xlfn.CONCAT("Data[", J$26, "]"))>0, INDIRECT(_xlfn.CONCAT("Data[", J$26, "]"))))))} -> 5 | K29: {=MAX(IF(Data[Poster]=$I29, IF(Data[Date]> TODAY()-$L$25, IF(INDIRECT(_xlfn.CONCAT("Data[", K$26, "]"))>0, INDIRECT(_xlfn.CONCAT("Data[", K$26, "]"))))))} -> 5 | L29: {=MAX(IF(Data[Poster]=$I29, IF(Data[Date]> TODAY()-$L$25, IF(INDIRECT(_xlfn.CONCAT("Data[", L$26, "]"))>0, INDIRECT(_xlfn.CONCAT("Data[", L$26, "]"))))))} -> 3 | M29: {=MAX(IF(Data[Poster]=$I29, IF(Data[Date]> TODAY()-$L$25, IF(INDIRECT(_xlfn.CONCAT("Data[", M$26, "]"))>0, INDIRECT(_xlfn.CONCAT("Data[", M$26, "]"))))))} -> 5 | N29: {=MAX(IF(Data[Poster]=$I29, IF(Data[Date]> TODAY()-$L$25, IF(INDIRECT(_xlfn.CONCAT("Data[", N$26, "]"))>0, INDIRECT(_xlfn.CONCAT("Data[", N$26, "]"))))))} -> 5 | P29: =Rankings!$L$1 -> loganworsdell | Q29: =COUNTIFS(Data[Date],">"&TODAY()-$T$25,Data[Poster],$P29,INDIRECT(_xlfn.CONCAT("Data[", Q$26, "]")),$P$25) -> 97 | R29: =COUNTIFS(Data[Date],">"&TODAY()-$T$25,Data[Poster],$P29,INDIRECT(_xlfn.CONCAT("Data[", R$26, "]")),$P$25) -> 83 | S29: =COUNTIFS(Data[Date],">"&TODAY()-$T$25,Data[Poster],$P29,INDIRECT(_xlfn.CONCAT("Data[", S$26, "]")),$P$25) -> 13 | T29: =COUNTIFS(Data[Date],">"&TODAY()-$T$25,Data[Poster],$P29,INDIRECT(_xlfn.CONCAT("Data[", T$26, "]")),$P$25) -> 87 | U29: =COUNTIFS(Data[Date],">"&TODAY()-$T$25,Data[Poster],$P29,INDIRECT(_xlfn.CONCAT("Data[", U$26, "]")),$P$25) -> 102 | V29: =SUM(Q29:U29) -> 382
B30: =Rankings!$M$1 -> samuelbattista | C30: {=MIN(IF(Data[Poster]=$B30, IF(Data[Date]> TODAY()-$E$25, IF(INDIRECT(_xlfn.CONCAT("Data[", C$26, "]"))>0, INDIRECT(_xlfn.CONCAT("Data[", C$26, "]"))))))} -> 2 | D30: {=MIN(IF(Data[Poster]=$B30, IF(Data[Date]> TODAY()-$E$25, IF(INDIRECT(_xlfn.CONCAT("Data[", D$26, "]"))>0, INDIRECT(_xlfn.CONCAT("Data[", D$26, "]"))))))} -> 1 | E30: {=MIN(IF(Data[Poster]=$B30, IF(Data[Date]> TODAY()-$E$25, IF(INDIRECT(_xlfn.CONCAT("Data[", E$26, "]"))>0, INDIRECT(_xlfn.CONCAT("Data[", E$26, "]"))))))} -> 1 | F30: {=MIN(IF(Data[Poster]=$B30, IF(Data[Date]> TODAY()-$E$25, IF(INDIRECT(_xlfn.CONCAT("Data[", F$26, "]"))>0, INDIRECT(_xlfn.CONCAT("Data[", F$26, "]"))))))} -> 1 | G30: {=MIN(IF(Data[Poster]=$B30, IF(Data[Date]> TODAY()-$E$25, IF(INDIRECT(_xlfn.CONCAT("Data[", G$26, "]"))>0, INDIRECT(_xlfn.CONCAT("Data[", G$26, "]"))))))} -> 1 | I30: =Rankings!$M$1 -> samuelbattista | J30: {=MAX(IF(Data[Poster]=$I30, IF(Data[Date]> TODAY()-$L$25, IF(INDIRECT(_xlfn.CONCAT("Data[", J$26, "]"))>0, INDIRECT(_xlfn.CONCAT("Data[", J$26, "]"))))))} -> 5 | K30: {=MAX(IF(Data[Poster]=$I30, IF(Data[Date]> TODAY()-$L$25, IF(INDIRECT(_xlfn.CONCAT("Data[", K$26, "]"))>0, INDIRECT(_xlfn.CONCAT("Data[", K$26, "]"))))))} -> 5 | L30: {=MAX(IF(Data[Poster]=$I30, IF(Data[Date]> TODAY()-$L$25, IF(INDIRECT(_xlfn.CONCAT("Data[", L$26, "]"))>0, INDIRECT(_xlfn.CONCAT("Data[", L$26, "]"))))))} -> 5 | M30: {=MAX(IF(Data[Poster]=$I30, IF(Data[Date]> TODAY()-$L$25, IF(INDIRECT(_xlfn.CONCAT("Data[", M$26, "]"))>0, INDIRECT(_xlfn.CONCAT("Data[", M$26, "]"))))))} -> 5 | N30: {=MAX(IF(Data[Poster]=$I30, IF(Data[Date]> TODAY()-$L$25, IF(INDIRECT(_xlfn.CONCAT("Data[", N$26, "]"))>0, INDIRECT(_xlfn.CONCAT("Data[", N$26, "]"))))))} -> 5 | P30: =Rankings!$M$1 -> samuelbattista | Q30: =COUNTIFS(Data[Date],">"&TODAY()-$T$25,Data[Poster],$P30,INDIRECT(_xlfn.CONCAT("Data[", Q$26, "]")),$P$25) -> 142 | R30: =COUNTIFS(Data[Date],">"&TODAY()-$T$25,Data[Poster],$P30,INDIRECT(_xlfn.CONCAT("Data[", R$26, "]")),$P$25) -> 82 | S30: =COUNTIFS(Data[Date],">"&TODAY()-$T$25,Data[Poster],$P30,INDIRECT(_xlfn.CONCAT("Data[", S$26, "]")),$P$25) -> 98 | T30: =COUNTIFS(Data[Date],">"&TODAY()-$T$25,Data[Poster],$P30,INDIRECT(_xlfn.CONCAT("Data[", T$26, "]")),$P$25) -> 6 | U30: =COUNTIFS(Data[Date],">"&TODAY()-$T$25,Data[Poster],$P30,INDIRECT(_xlfn.CONCAT("Data[", U$26, "]")),$P$25) -> 124 | V30: =SUM(Q30:U30) -> 452
B31: =Rankings!$N$1 -> currydestroyer27 | C31: {=MIN(IF(Data[Poster]=$B31, IF(Data[Date]> TODAY()-$E$25, IF(INDIRECT(_xlfn.CONCAT("Data[", C$26, "]"))>0, INDIRECT(_xlfn.CONCAT("Data[", C$26, "]"))))))} -> 1 | D31: {=MIN(IF(Data[Poster]=$B31, IF(Data[Date]> TODAY()-$E$25, IF(INDIRECT(_xlfn.CONCAT("Data[", D$26, "]"))>0, INDIRECT(_xlfn.CONCAT("Data[", D$26, "]"))))))} -> 1 | E31: {=MIN(IF(Data[Poster]=$B31, IF(Data[Date]> TODAY()-$E$25, IF(INDIRECT(_xlfn.CONCAT("Data[", E$26, "]"))>0, INDIRECT(_xlfn.CONCAT("Data[", E$26, "]"))))))} -> 2 | F31: {=MIN(IF(Data[Poster]=$B31, IF(Data[Date]> TODAY()-$E$25, IF(INDIRECT(_xlfn.CONCAT("Data[", F$26, "]"))>0, INDIRECT(_xlfn.CONCAT("Data[", F$26, "]"))))))} -> 2 | G31: {=MIN(IF(Data[Poster]=$B31, IF(Data[Date]> TODAY()-$E$25, IF(INDIRECT(_xlfn.CONCAT("Data[", G$26, "]"))>0, INDIRECT(_xlfn.CONCAT("Data[", G$26, "]"))))))} -> 1 | I31: =Rankings!$N$1 -> currydestroyer27 | J31: {=MAX(IF(Data[Poster]=$I31, IF(Data[Date]> TODAY()-$L$25, IF(INDIRECT(_xlfn.CONCAT("Data[", J$26, "]"))>0, INDIRECT(_xlfn.CONCAT("Data[", J$26, "]"))))))} -> 5 | K31: {=MAX(IF(Data[Poster]=$I31, IF(Data[Date]> TODAY()-$L$25, IF(INDIRECT(_xlfn.CONCAT("Data[", K$26, "]"))>0, INDIRECT(_xlfn.CONCAT("Data[", K$26, "]"))))))} -> 5 | L31: {=MAX(IF(Data[Poster]=$I31, IF(Data[Date]> TODAY()-$L$25, IF(INDIRECT(_xlfn.CONCAT("Data[", L$26, "]"))>0, INDIRECT(_xlfn.CONCAT("Data[", L$26, "]"))))))} -> 5 | M31: {=MAX(IF(Data[Poster]=$I31, IF(Data[Date]> TODAY()-$L$25, IF(INDIRECT(_xlfn.CONCAT("Data[", M$26, "]"))>0, INDIRECT(_xlfn.CONCAT("Data[", M$26, "]"))))))} -> 5 | N31: {=MAX(IF(Data[Poster]=$I31, IF(Data[Date]> TODAY()-$L$25, IF(INDIRECT(_xlfn.CONCAT("Data[", N$26, "]"))>0, INDIRECT(_xlfn.CONCAT("Data[", N$26, "]"))))))} -> 4 | P31: =Rankings!$N$1 -> currydestroyer27 | Q31: =COUNTIFS(Data[Date],">"&TODAY()-$T$25,Data[Poster],$P31,INDIRECT(_xlfn.CONCAT("Data[", Q$26, "]")),$P$25) -> 74 | R31: =COUNTIFS(Data[Date],">"&TODAY()-$T$25,Data[Poster],$P31,INDIRECT(_xlfn.CONCAT("Data[", R$26, "]")),$P$25) -> 106 | S31: =COUNTIFS(Data[Date],">"&TODAY()-$T$25,Data[Poster],$P31,INDIRECT(_xlfn.CONCAT("Data[", S$26, "]")),$P$25) -> 79 | T31: =COUNTIFS(Data[Date],">"&TODAY()-$T$25,Data[Poster],$P31,INDIRECT(_xlfn.CONCAT("Data[", T$26, "]")),$P$25) -> 122 | U31: =COUNTIFS(Data[Date],">"&TODAY()-$T$25,Data[Poster],$P31,INDIRECT(_xlfn.CONCAT("Data[", U$26, "]")),$P$25) -> 3 | V31: =SUM(Q31:U31) -> 384
B33: Hall of Fame | I33: Hall of Shame | P33: Hall of Same | X33: Clown Award
B34: Date | C34: Poster | D34: AVG | E34: Std Dev | F34: Song | G34: Artist | I34: Date | J34: Poster | K34: AVG | L34: Std Dev | M34: Song | N34: Artist | P34: Date | Q34: Poster | R34: AVG | S34: Std Dev | T34: Song | U34: Artist | X34: Date | Y34: Poster | Z34: AVG | AA34: Std Dev | AB34: Song | AC34: Artist
B35: {=_xlfn._xlws.FILTER(Data[[Date]:[Artist]], Data[Average]=MIN(Data[Average]), "TBD")} -> 45873 | C35: alappatjoe | D35: 1 | E35: 0 | F35: Billie Jean | G35: Michael Jackson | I35: {=_xlfn._xlws.FILTER(Data[[Date]:[Artist]], Data[Average]=MAX(Data[Average]), "TBD")} -> 45603 | J35: samuelbattista | K35: 5 | L35: 0 | M35: Electric Pow Wow Drum | N35: The Halluci Nation | P35: {=_xlfn._xlws.FILTER(Data[[Date]:[Artist]], (Data[Average]<>1)*(Data[Average]<>5)*(Data[STDEV]=0), "TBD")} -> 45861 | Q35: loganworsdell | R35: 3 | S35: 0 | T35: Dance With You | U35: Party Pupils, Yung Bae, Bryce Vine | X35: {=_xlfn._xlws.FILTER(Data[[Date]:[Artist]], (Data[Average]=4.2)*(Data[STDEV]>=1.6), "TBD")} -> 45491 | Y35: alappatjoe | Z35: 4.2 | AA35: 1.6 | AB35: I Don't Do Drugs | AC35: Doja Cat, Ariana Grande
I36: 45607 | J36: danram | K36: 5 | L36: 0 | M36: VENTE CONMIGO | N36: Feid | P36: 46126 | Q36: loganworsdell | R36: 2 | S36: 0 | T36: Dive Into Me | U36: Alok, Khalid | X36: 45498 | Y36: samuelbattista | Z36: 4.2 | AA36: 1.6 | AB36: Bridge Over Troubled Water | AC36: Jacob Collier, John Legend, Tori Kelly
I37: 45736 | J37: loganworsdell | K37: 5 | L37: 0 | M37: Gettin' Over You | N37: David Guetta, Chris Willis, Fergie, LMFAO | X37: 45551 | Y37: samuelbattista | Z37: 4.2 | AA37: 1.6 | AB37: Ur Mum | AC37: Wet Leg
I38: 45827 | J38: danram | K38: 5 | L38: 0 | M38: Kill That Yankee Soldier | N38: Un-Reconstructed | X38: 45559 | Y38: danram | Z38: 4.2 | AA38: 1.6 | AB38: Marsupial Superstars | AC38: SahBabii, T3
I39: 45902 | J39: samuelbattista | K39: 5 | L39: 0 | M39: BOOTZ | N39: Salina EsTitties | X39: 45580 | Y39: samuelbattista | Z39: 4.2 | AA39: 1.6 | AB39: Blue Eyes Crying In The Rain | AC39: Willie Nelson
I40: 45992 | J40: danram | K40: 5 | L40: 0 | M40: Flamingo | N40: Kero Kero Bonito | X40: 45595 | Y40: alappatjoe | Z40: 4.2 | AA40: 1.6 | AB40: I'm On Everything | AC40: Bad Meets Evil, Mike Epps
I41: 46009 | J41: samuelbattista | K41: 5 | L41: 0 | M41: Santa Claus And His Old Lady | N41: Cheech & Chong | X41: 45715 | Y41: danram | Z41: 4.2 | AA41: 1.6 | AB41: Guilt Trip | AC41: Kanye West
I42: 46050 | J42: loganworsdell | K42: 5 | L42: 0 | M42: Stay With Me | N42: 1nonly | X42: 45770 | Y42: loganworsdell | Z42: 4.2 | AA42: 1.6 | AB42: Lost At Sea | AC42: Zedd, Ryan Tedder
I43: 46072 | J43: alappatjoe | K43: 5 | L43: 0 | M43: Flexicution | N43: Logic | X43: 45777 | Y43: loganworsdell | Z43: 4.2 | AA43: 1.6 | AB43: I Really Wish I Hated You | AC43: blink-182
I44: 46113 | J44: loganworsdell | K44: 5 | L44: 0 | M44: Semicolon | N44: The Lonely Island, Solange | X44: 45825 | Y44: samuelbattista | Z44: 4.2 | AA44: 1.6 | AB44: Broken Wing Bird | AC44: Kashus Culpepper, Sierra Ferrell
I45: 46147 | J45: danram | K45: 5 | L45: 0 | M45: Aguanile | N45: Willie Colon, Hector Lavoe | X45: 45831 | Y45: samuelbattista | Z45: 4.2 | AA45: 1.6 | AB45: Cover Me Up | AC45: Jason Isbell
I46: 46209 | J46: danram | K46: 5 | L46: 0 | M46: Ballout | N46: 2slimey | X46: 45839 | Y46: alappatjoe | Z46: 4.2 | AA46: 1.6 | AB46: Fantasia on the "Dargason" | AC46: United States Air Force Band
I47: 46239 | J47: danram | K47: 5 | L47: 0 | M47: HENTAI | N47: Rosalia | X47: 45861 | Y47: samuelbattista | Z47: 4.2 | AA47: 1.6 | AB47: Friends in the End | AC47: Lukas Nelson, Sierra Ferrell
I48: 46258 | J48: danram | K48: 5 | L48: 0 | M48: She's the Best | N48: Troye Sivan | X48: 45862 | Y48: alappatjoe | Z48: 4.2 | AA48: 1.6 | AB48: DragonBallZ | AC48: Bruce Faulconer
X49: 45876 | Y49: currydestroyer27 | Z49: 4.2 | AA49: 1.6 | AB49: Starships | AC49: Nicki Minaj
X50: 45925 | Y50: currydestroyer27 | Z50: 4.2 | AA50: 1.6 | AB50: Some Nights | AC50: fun.
X51: 45960 | Y51: alappatjoe | Z51: 4.2 | AA51: 1.6 | AB51: Lavender Town | AC51: Louie Zong
X52: 46034 | Y52: alappatjoe | Z52: 4.2 | AA52: 1.6 | AB52: Jananto | AC52: Zeina
X53: 46057 | Y53: alappatjoe | Z53: 4.2 | AA53: 1.6 | AB53: 100 | AC53: Ella Mai
X54: 46084 | Y54: alappatjoe | Z54: 4.2 | AA54: 1.6 | AB54: Alley Oop | AC54: Chris Patrick
X55: 46111 | Y55: samuelbattista | Z55: 4.2 | AA55: 1.6 | AB55: B.Y.O.B | AC55: System of A Down
X56: 46132 | Y56: alappatjoe | Z56: 4.2 | AA56: 1.6 | AB56: I Do / Options | AC56: Kevin Ross
X57: 46133 | Y57: alappatjoe | Z57: 4.2 | AA57: 1.6 | AB57: IRL | AC57: Devon Gilfillian, Cory Wong
X58: 46254 | Y58: loganworsdell | Z58: 4.2 | AA58: 1.6 | AB58: Latch | AC58: Disclosure, Sam Smith

Sheet 2026 Song of the Month
A1: =MAX(Z2:Z17) -> 16 | B1: =FLOOR(LOG(A1, 2), 1)-1 -> 3 | C1: =_xlfn.CEILING.MATH(LOG(A1, 2), 1)-1 -> 3 | I1: January | Z1: Seeding | AA1: Date | AB1: Poster | AC1: Average | AD1: STDEV | AE1: Song | AF1: Artist | AG1: Expected | AI1: Result | AJ1: Song Title | AK1: Diff | AL1: Shift
A2: Description | B2: Num | C2: Round | D2: Max Seed | E2: Top Seed | F2: Low Seed | G2: Initial 1 | H2: Initial 2 | I2: J | J2: D | K2: L | L2: S | M2: H | N2: Song 1 | O2: Score 1 | P2: Winner | Q2: Score 2 | R2: Song 2 | S2: H | T2: S | U2: L | V2: D | W2: J | X2: Remaining | Z2: =IF(AC2>0, COUNTIF(AC$2:AC$17, "<"&AC2) + COUNTIFS(AC$2:AC$17, AC2, AD$2:AD$17, "<"&AD2) + COUNTIFS(AC$2:AC$17, AC2, AD$2:AD$17, AD2, AA$2:AA$17, "<"&AA2) + 1, "TBD") -> 6 | AA2: {=_xlfn._xlws.FILTER(Data[Date]:Data[Artist], (Data[Date]>=DATE(2026,1,1))*(Data[Date]<=DATE(2026,1,31))*(Data[Winner]=TRUE()), "TBD")} -> 46027 | AB2: samuelbattista | AC2: 2 | AD2: 0.89442719 | AE2: Layla | AF2: Derek & The Dominos | AG2: =IF(Z2>1, 2^FLOOR(LOG(Z2-1, 2), 1)+1, 1) -> 5 | AI2: 1 | AJ2: =P3 -> BABY SAID (Sam) | AK2: =IFERROR(VLOOKUP(Jan_2025_Results48[[#This Row],[Song Title]], $AE$2:$AG$17, 3, FALSE)-Jan_2025_Results48[[#This Row],[Result]], "TBD") -> 8 | AL2: =IF(AK2<0,"↓",IF(AK2=0,"-","↑")) -> ↑
A3: =_xlfn.CONCAT("Seed ", Jan_2026_SotM[[#This Row],[Top Seed]], " vs ",Jan_2026_SotM[[#This Row],[Low Seed]]) -> Seed 1 vs 2 | B3: 1 | C3: =FLOOR(LOG(Jan_2026_SotM[[#This Row],[Num]], 2), 1) -> 0 | D3: =2^(Jan_2026_SotM[[#This Row],[Round]]+1) -> 2 | E3: =Jan_2026_SotM[[#This Row],[Max Seed]]-Jan_2026_SotM[[#This Row],[Num]] -> 1 | F3: =Jan_2026_SotM[[#This Row],[Max Seed]]-Jan_2026_SotM[[#This Row],[Top Seed]]+1 -> 2 | G3: =IF(Jan_2026_SotM[[#This Row],[Round]]=$C$1, TRUE(), IF(Jan_2026_SotM[[#This Row],[Round]]=$B$1, Jan_2026_SotM[[#This Row],[Top Seed]]<=2*Jan_2026_SotM[[#This Row],[Max Seed]]-$A$1, FALSE())) -> FALSE | H3: =IF(Jan_2026_SotM[[#This Row],[Round]]=$C$1, TRUE(), IF(Jan_2026_SotM[[#This Row],[Round]]=$B$1, Jan_2026_SotM[[#This Row],[Low Seed]]<=2*Jan_2026_SotM[[#This Row],[Max Seed]]-$A$1, FALSE())) -> FALSE | I3: x | L3: x | N3: =IF(Jan_2026_SotM[[#This Row],[Num]]>=$A$1, "-", IF(Jan_2026_SotM[[#This Row],[Initial 1]], VLOOKUP(Jan_2026_SotM[[#This Row],[Top Seed]], $Z$2:$AE$17, 6, FALSE), OFFSET(Jan_2026_SotM[[#This Row],[Winner]], Jan_2026_SotM[[#This Row],[Max Seed]], 0))) -> Hey Jude | O3: =COUNTIF(Jan_2026_SotM[[#This Row],[J]:[H]],"x") -> 2 | P3: =IF(Jan_2026_SotM[[#This Row],[Num]]>=$A$1, "-", IF(Jan_2026_SotM[[#This Row],[Score 1]]>=3, Jan_2026_SotM[[#This Row],[Song 1]], IF(Jan_2026_SotM[[#This Row],[Score 2]]>=3, Jan_2026_SotM[[#This Row],[Song 2]], "TBD"))) -> BABY SAID (Sam) | Q3: =COUNTIF(Jan_2026_SotM[[#This Row],[H ]:[J ]],"x") -> 3 | R3: =IF(Jan_2026_SotM[[#This Row],[Num]]>=$A$1, "-", IF(Jan_2026_SotM[[#This Row],[Initial 2]], VLOOKUP(Jan_2026_SotM[[#This Row],[Low Seed]], $Z$2:$AE$17, 6, FALSE), OFFSET(Jan_2026_SotM[[#This Row],[Winner]], 2*(Jan_2026_SotM[[#This Row],[Max Seed]]-Jan_2026_SotM[[#This Row],[Low Seed]])+1, 0))) -> BABY SAID (Sam) | S3: x | U3: x | V3: x | X3: =IF(OR(Jan_2026_SotM[[#This Row],[Song 1]]="TBD", Jan_2026_SotM[[#This Row],[Song 2]]="TBD"), "TBD", _xlfn.CONCAT(IF(_xlfn.XOR(ISBLANK(Jan_2026_SotM[[#This Row],[J]]), ISBLANK(Jan_2026_SotM[[#This Row],[J ]])), "", "J "), IF(_xlfn.XOR(ISBLANK(Jan_2026_SotM[[#This Row],[D]]), ISBLANK(Jan_2026_SotM[[#This Row],[D ]])), "", "D "), IF(_xlfn.XOR(ISBLANK(Jan_2026_SotM[[#This Row],[L]]), ISBLANK(Jan_2026_SotM[[#This Row],[L ]])), "", "L "), IF(_xlfn.XOR(ISBLANK(Jan_2026_SotM[[#This Row],[S]]), ISBLANK(Jan_2026_SotM[[#This Row],[S ]])), "", "S "), IF(_xlfn.XOR(ISBLANK(Jan_2026_SotM[[#This Row],[H]]), ISBLANK(Jan_2026_SotM[[#This Row],[H ]])), "", "H "))) | Z3: =IF(AC3>0, COUNTIF(AC$2:AC$17, "<"&AC3) + COUNTIFS(AC$2:AC$17, AC3, AD$2:AD$17, "<"&AD3) + COUNTIFS(AC$2:AC$17, AC3, AD$2:AD$17, AD3, AA$2:AA$17, "<"&AA3) + 1, "TBD") -> 2 | AA3: 46028 | AB3: alappatjoe | AC3: 1.6 | AD3: 0.48989795 | AE3: Fly | AF3: Tone Stith | AG3: =IF(Z3>1, 2^FLOOR(LOG(Z3-1, 2), 1)+1, 1) -> 2 | AI3: =Jan_2026_SotM[[#This Row],[Max Seed]]/2 + 1 -> 2 | AJ3: =IF(Jan_2026_SotM[[#This Row],[Num]]>=$A$1, "-", IF(Jan_2026_SotM[[#This Row],[Score 1]]>=3, Jan_2026_SotM[[#This Row],[Song 2]], IF(Jan_2026_SotM[[#This Row],[Score 2]]>=3, Jan_2026_SotM[[#This Row],[Song 1]], "TBD"))) -> Hey Jude | AK3: =IFERROR(VLOOKUP(Jan_2025_Results48[[#This Row],[Song Title]], $AE$2:$AG$17, 3, FALSE)-Jan_2025_Results48[[#This Row],[Result]], "TBD") -> 3 | AL3: =IF(AK3<0,"↓",IF(AK3=0,"-","↑")) -> ↑
A4: =_xlfn.CONCAT("Seed ", Jan_2026_SotM[[#This Row],[Top Seed]], " vs ",Jan_2026_SotM[[#This Row],[Low Seed]]) -> Seed 2 vs 3 | B4: 2 | C4: =FLOOR(LOG(Jan_2026_SotM[[#This Row],[Num]], 2), 1) -> 1 | D4: =2^(Jan_2026_SotM[[#This Row],[Round]]+1) -> 4 | E4: =Jan_2026_SotM[[#This Row],[Max Seed]]-Jan_2026_SotM[[#This Row],[Num]] -> 2 | F4: =Jan_2026_SotM[[#This Row],[Max Seed]]-Jan_2026_SotM[[#This Row],[Top Seed]]+1 -> 3 | G4: =IF(Jan_2026_SotM[[#This Row],[Round]]=$C$1, TRUE(), IF(Jan_2026_SotM[[#This Row],[Round]]=$B$1, Jan_2026_SotM[[#This Row],[Top Seed]]<=2*Jan_2026_SotM[[#This Row],[Max Seed]]-$A$1, FALSE())) -> FALSE | H4: =IF(Jan_2026_SotM[[#This Row],[Round]]=$C$1, TRUE(), IF(Jan_2026_SotM[[#This Row],[Round]]=$B$1, Jan_2026_SotM[[#This Row],[Low Seed]]<=2*Jan_2026_SotM[[#This Row],[Max Seed]]-$A$1, FALSE())) -> FALSE | I4: x | J4: x | K4: x | L4: x | M4: x | N4: =IF(Jan_2026_SotM[[#This Row],[Num]]>=$A$1, "-", IF(Jan_2026_SotM[[#This Row],[Initial 1]], VLOOKUP(Jan_2026_SotM[[#This Row],[Top Seed]], $Z$2:$AE$17, 6, FALSE), OFFSET(Jan_2026_SotM[[#This Row],[Winner]], Jan_2026_SotM[[#This Row],[Max Seed]], 0))) -> BABY SAID (Sam) | O4: =COUNTIF(Jan_2026_SotM[[#This Row],[J]:[H]],"x") -> 5 | P4: =IF(Jan_2026_SotM[[#This Row],[Num]]>=$A$1, "-", IF(Jan_2026_SotM[[#This Row],[Score 1]]>=3, Jan_2026_SotM[[#This Row],[Song 1]], IF(Jan_2026_SotM[[#This Row],[Score 2]]>=3, Jan_2026_SotM[[#This Row],[Song 2]], "TBD"))) -> BABY SAID (Sam) | Q4: =COUNTIF(Jan_2026_SotM[[#This Row],[H ]:[J ]],"x") -> 0 | R4: =IF(Jan_2026_SotM[[#This Row],[Num]]>=$A$1, "-", IF(Jan_2026_SotM[[#This Row],[Initial 2]], VLOOKUP(Jan_2026_SotM[[#This Row],[Low Seed]], $Z$2:$AE$17, 6, FALSE), OFFSET(Jan_2026_SotM[[#This Row],[Winner]], 2*(Jan_2026_SotM[[#This Row],[Max Seed]]-Jan_2026_SotM[[#This Row],[Low Seed]])+1, 0))) -> luv stuck | X4: =IF(OR(Jan_2026_SotM[[#This Row],[Song 1]]="TBD", Jan_2026_SotM[[#This Row],[Song 2]]="TBD"), "TBD", _xlfn.CONCAT(IF(_xlfn.XOR(ISBLANK(Jan_2026_SotM[[#This Row],[J]]), ISBLANK(Jan_2026_SotM[[#This Row],[J ]])), "", "J "), IF(_xlfn.XOR(ISBLANK(Jan_2026_SotM[[#This Row],[D]]), ISBLANK(Jan_2026_SotM[[#This Row],[D ]])), "", "D "), IF(_xlfn.XOR(ISBLANK(Jan_2026_SotM[[#This Row],[L]]), ISBLANK(Jan_2026_SotM[[#This Row],[L ]])), "", "L "), IF(_xlfn.XOR(ISBLANK(Jan_2026_SotM[[#This Row],[S]]), ISBLANK(Jan_2026_SotM[[#This Row],[S ]])), "", "S "), IF(_xlfn.XOR(ISBLANK(Jan_2026_SotM[[#This Row],[H]]), ISBLANK(Jan_2026_SotM[[#This Row],[H ]])), "", "H "))) | Z4: =IF(AC4>0, COUNTIF(AC$2:AC$17, "<"&AC4) + COUNTIFS(AC$2:AC$17, AC4, AD$2:AD$17, "<"&AD4) + COUNTIFS(AC$2:AC$17, AC4, AD$2:AD$17, AD4, AA$2:AA$17, "<"&AA4) + 1, "TBD") -> 16 | AA4: 46029 | AB4: loganworsdell | AC4: 2.4 | AD4: 1.356466 | AE4: RABBITHOLE | AF4: Emei | AG4: =IF(Z4>1, 2^FLOOR(LOG(Z4-1, 2), 1)+1, 1) -> 9 | AI4: =Jan_2026_SotM[[#This Row],[Max Seed]]/2 + 1 -> 3 | AJ4: =IF(Jan_2026_SotM[[#This Row],[Num]]>=$A$1, "-", IF(Jan_2026_SotM[[#This Row],[Score 1]]>=3, Jan_2026_SotM[[#This Row],[Song 2]], IF(Jan_2026_SotM[[#This Row],[Score 2]]>=3, Jan_2026_SotM[[#This Row],[Song 1]], "TBD"))) -> luv stuck | AK4: =IFERROR(VLOOKUP(Jan_2025_Results48[[#This Row],[Song Title]], $AE$2:$AG$17, 3, FALSE)-Jan_2025_Results48[[#This Row],[Result]], "TBD") -> 6 | AL4: =IF(AK4<0,"↓",IF(AK4=0,"-","↑")) -> ↑
A5: =_xlfn.CONCAT("Seed ", Jan_2026_SotM[[#This Row],[Top Seed]], " vs ",Jan_2026_SotM[[#This Row],[Low Seed]]) -> Seed 1 vs 4 | B5: 3 | C5: =FLOOR(LOG(Jan_2026_SotM[[#This Row],[Num]], 2), 1) -> 1 | D5: =2^(Jan_2026_SotM[[#This Row],[Round]]+1) -> 4 | E5: =Jan_2026_SotM[[#This Row],[Max Seed]]-Jan_2026_SotM[[#This Row],[Num]] -> 1 | F5: =Jan_2026_SotM[[#This Row],[Max Seed]]-Jan_2026_SotM[[#This Row],[Top Seed]]+1 -> 4 | G5: =IF(Jan_2026_SotM[[#This Row],[Round]]=$C$1, TRUE(), IF(Jan_2026_SotM[[#This Row],[Round]]=$B$1, Jan_2026_SotM[[#This Row],[Top Seed]]<=2*Jan_2026_SotM[[#This Row],[Max Seed]]-$A$1, FALSE())) -> FALSE | H5: =IF(Jan_2026_SotM[[#This Row],[Round]]=$C$1, TRUE(), IF(Jan_2026_SotM[[#This Row],[Round]]=$B$1, Jan_2026_SotM[[#This Row],[Low Seed]]<=2*Jan_2026_SotM[[#This Row],[Max Seed]]-$A$1, FALSE())) -> FALSE | J5: x | M5: x | N5: =IF(Jan_2026_SotM[[#This Row],[Num]]>=$A$1, "-", IF(Jan_2026_SotM[[#This Row],[Initial 1]], VLOOKUP(Jan_2026_SotM[[#This Row],[Top Seed]], $Z$2:$AE$17, 6, FALSE), OFFSET(Jan_2026_SotM[[#This Row],[Winner]], Jan_2026_SotM[[#This Row],[Max Seed]], 0))) -> In Da Club | O5: =COUNTIF(Jan_2026_SotM[[#This Row],[J]:[H]],"x") -> 2 | P5: =IF(Jan_2026_SotM[[#This Row],[Num]]>=$A$1, "-", IF(Jan_2026_SotM[[#This Row],[Score 1]]>=3, Jan_2026_SotM[[#This Row],[Song 1]], IF(Jan_2026_SotM[[#This Row],[Score 2]]>=3, Jan_2026_SotM[[#This Row],[Song 2]], "TBD"))) -> Hey Jude | Q5: =COUNTIF(Jan_2026_SotM[[#This Row],[H ]:[J ]],"x") -> 3 | R5: =IF(Jan_2026_SotM[[#This Row],[Num]]>=$A$1, "-", IF(Jan_2026_SotM[[#This Row],[Initial 2]], VLOOKUP(Jan_2026_SotM[[#This Row],[Low Seed]], $Z$2:$AE$17, 6, FALSE), OFFSET(Jan_2026_SotM[[#This Row],[Winner]], 2*(Jan_2026_SotM[[#This Row],[Max Seed]]-Jan_2026_SotM[[#This Row],[Low Seed]])+1, 0))) -> Hey Jude | T5: x | U5: x | W5: x | X5: =IF(OR(Jan_2026_SotM[[#This Row],[Song 1]]="TBD", Jan_2026_SotM[[#This Row],[Song 2]]="TBD"), "TBD", _xlfn.CONCAT(IF(_xlfn.XOR(ISBLANK(Jan_2026_SotM[[#This Row],[J]]), ISBLANK(Jan_2026_SotM[[#This Row],[J ]])), "", "J "), IF(_xlfn.XOR(ISBLANK(Jan_2026_SotM[[#This Row],[D]]), ISBLANK(Jan_2026_SotM[[#This Row],[D ]])), "", "D "), IF(_xlfn.XOR(ISBLANK(Jan_2026_SotM[[#This Row],[L]]), ISBLANK(Jan_2026_SotM[[#This Row],[L ]])), "", "L "), IF(_xlfn.XOR(ISBLANK(Jan_2026_SotM[[#This Row],[S]]), ISBLANK(Jan_2026_SotM[[#This Row],[S ]])), "", "S "), IF(_xlfn.XOR(ISBLANK(Jan_2026_SotM[[#This Row],[H]]), ISBLANK(Jan_2026_SotM[[#This Row],[H ]])), "", "H "))) | Z5: =IF(AC5>0, COUNTIF(AC$2:AC$17, "<"&AC5) + COUNTIFS(AC$2:AC$17, AC5, AD$2:AD$17, "<"&AD5) + COUNTIFS(AC$2:AC$17, AC5, AD$2:AD$17, AD5, AA$2:AA$17, "<"&AA5) + 1, "TBD") -> 5 | AA5: 46030 | AB5: alappatjoe | AC5: 1.8 | AD5: 1.1661904 | AE5: Hey Jude | AF5: The Beatles | AG5: =IF(Z5>1, 2^FLOOR(LOG(Z5-1, 2), 1)+1, 1) -> 5 | AI5: =Jan_2026_SotM[[#This Row],[Max Seed]]/2 + 1 -> 3 | AJ5: =IF(Jan_2026_SotM[[#This Row],[Num]]>=$A$1, "-", IF(Jan_2026_SotM[[#This Row],[Score 1]]>=3, Jan_2026_SotM[[#This Row],[Song 2]], IF(Jan_2026_SotM[[#This Row],[Score 2]]>=3, Jan_2026_SotM[[#This Row],[Song 1]], "TBD"))) -> In Da Club | AK5: =IFERROR(VLOOKUP(Jan_2025_Results48[[#This Row],[Song Title]], $AE$2:$AG$17, 3, FALSE)-Jan_2025_Results48[[#This Row],[Result]], "TBD") -> -2 | AL5: =IF(AK5<0,"↓",IF(AK5=0,"-","↑")) -> ↓
A6: =_xlfn.CONCAT("Seed ", Jan_2026_SotM[[#This Row],[Top Seed]], " vs ",Jan_2026_SotM[[#This Row],[Low Seed]]) -> Seed 4 vs 5 | B6: 4 | C6: =FLOOR(LOG(Jan_2026_SotM[[#This Row],[Num]], 2), 1) -> 2 | D6: =2^(Jan_2026_SotM[[#This Row],[Round]]+1) -> 8 | E6: =Jan_2026_SotM[[#This Row],[Max Seed]]-Jan_2026_SotM[[#This Row],[Num]] -> 4 | F6: =Jan_2026_SotM[[#This Row],[Max Seed]]-Jan_2026_SotM[[#This Row],[Top Seed]]+1 -> 5 | G6: =IF(Jan_2026_SotM[[#This Row],[Round]]=$C$1, TRUE(), IF(Jan_2026_SotM[[#This Row],[Round]]=$B$1, Jan_2026_SotM[[#This Row],[Top Seed]]<=2*Jan_2026_SotM[[#This Row],[Max Seed]]-$A$1, FALSE())) -> FALSE | H6: =IF(Jan_2026_SotM[[#This Row],[Round]]=$C$1, TRUE(), IF(Jan_2026_SotM[[#This Row],[Round]]=$B$1, Jan_2026_SotM[[#This Row],[Low Seed]]<=2*Jan_2026_SotM[[#This Row],[Max Seed]]-$A$1, FALSE())) -> FALSE | K6: x | M6: x | N6: =IF(Jan_2026_SotM[[#This Row],[Num]]>=$A$1, "-", IF(Jan_2026_SotM[[#This Row],[Initial 1]], VLOOKUP(Jan_2026_SotM[[#This Row],[Top Seed]], $Z$2:$AE$17, 6, FALSE), OFFSET(Jan_2026_SotM[[#This Row],[Winner]], Jan_2026_SotM[[#This Row],[Max Seed]], 0))) -> NERVOUS | O6: =COUNTIF(Jan_2026_SotM[[#This Row],[J]:[H]],"x") -> 2 | P6: =IF(Jan_2026_SotM[[#This Row],[Num]]>=$A$1, "-", IF(Jan_2026_SotM[[#This Row],[Score 1]]>=3, Jan_2026_SotM[[#This Row],[Song 1]], IF(Jan_2026_SotM[[#This Row],[Score 2]]>=3, Jan_2026_SotM[[#This Row],[Song 2]], "TBD"))) -> Hey Jude | Q6: =COUNTIF(Jan_2026_SotM[[#This Row],[H ]:[J ]],"x") -> 3 | R6: =IF(Jan_2026_SotM[[#This Row],[Num]]>=$A$1, "-", IF(Jan_2026_SotM[[#This Row],[Initial 2]], VLOOKUP(Jan_2026_SotM[[#This Row],[Low Seed]], $Z$2:$AE$17, 6, FALSE), OFFSET(Jan_2026_SotM[[#This Row],[Winner]], 2*(Jan_2026_SotM[[#This Row],[Max Seed]]-Jan_2026_SotM[[#This Row],[Low Seed]])+1, 0))) -> Hey Jude | T6: x | V6: x | W6: x | X6: =IF(OR(Jan_2026_SotM[[#This Row],[Song 1]]="TBD", Jan_2026_SotM[[#This Row],[Song 2]]="TBD"), "TBD", _xlfn.CONCAT(IF(_xlfn.XOR(ISBLANK(Jan_2026_SotM[[#This Row],[J]]), ISBLANK(Jan_2026_SotM[[#This Row],[J ]])), "", "J "), IF(_xlfn.XOR(ISBLANK(Jan_2026_SotM[[#This Row],[D]]), ISBLANK(Jan_2026_SotM[[#This Row],[D ]])), "", "D "), IF(_xlfn.XOR(ISBLANK(Jan_2026_SotM[[#This Row],[L]]), ISBLANK(Jan_2026_SotM[[#This Row],[L ]])), "", "L "), IF(_xlfn.XOR(ISBLANK(Jan_2026_SotM[[#This Row],[S]]), ISBLANK(Jan_2026_SotM[[#This Row],[S ]])), "", "S "), IF(_xlfn.XOR(ISBLANK(Jan_2026_SotM[[#This Row],[H]]), ISBLANK(Jan_2026_SotM[[#This Row],[H ]])), "", "H "))) | Z6: =IF(AC6>0, COUNTIF(AC$2:AC$17, "<"&AC6) + COUNTIFS(AC$2:AC$17, AC6, AD$2:AD$17, "<"&AD6) + COUNTIFS(AC$2:AC$17, AC6, AD$2:AD$17, AD6, AA$2:AA$17, "<"&AA6) + 1, "TBD") -> 15 | AA6: 46034 | AB6: currydestroyer27 | AC6: 2.4 | AD6: 1.0198039 | AE6: Messages from the Stars | AF6: Dabeull, Rude Jude, HolyBrune | AG6: =IF(Z6>1, 2^FLOOR(LOG(Z6-1, 2), 1)+1, 1) -> 9 | AI6: =Jan_2026_SotM[[#This Row],[Max Seed]]/2 + 1 -> 5 | AJ6: =IF(Jan_2026_SotM[[#This Row],[Num]]>=$A$1, "-", IF(Jan_2026_SotM[[#This Row],[Score 1]]>=3, Jan_2026_SotM[[#This Row],[Song 2]], IF(Jan_2026_SotM[[#This Row],[Score 2]]>=3, Jan_2026_SotM[[#This Row],[Song 1]], "TBD"))) -> NERVOUS | AK6: =IFERROR(VLOOKUP(Jan_2025_Results48[[#This Row],[Song Title]], $AE$2:$AG$17, 3, FALSE)-Jan_2025_Results48[[#This Row],[Result]], "TBD") -> -2 | AL6: =IF(AK6<0,"↓",IF(AK6=0,"-","↑")) -> ↓
A7: =_xlfn.CONCAT("Seed ", Jan_2026_SotM[[#This Row],[Top Seed]], " vs ",Jan_2026_SotM[[#This Row],[Low Seed]]) -> Seed 3 vs 6 | B7: 5 | C7: =FLOOR(LOG(Jan_2026_SotM[[#This Row],[Num]], 2), 1) -> 2 | D7: =2^(Jan_2026_SotM[[#This Row],[Round]]+1) -> 8 | E7: =Jan_2026_SotM[[#This Row],[Max Seed]]-Jan_2026_SotM[[#This Row],[Num]] -> 3 | F7: =Jan_2026_SotM[[#This Row],[Max Seed]]-Jan_2026_SotM[[#This Row],[Top Seed]]+1 -> 6 | G7: =IF(Jan_2026_SotM[[#This Row],[Round]]=$C$1, TRUE(), IF(Jan_2026_SotM[[#This Row],[Round]]=$B$1, Jan_2026_SotM[[#This Row],[Top Seed]]<=2*Jan_2026_SotM[[#This Row],[Max Seed]]-$A$1, FALSE())) -> FALSE | H7: =IF(Jan_2026_SotM[[#This Row],[Round]]=$C$1, TRUE(), IF(Jan_2026_SotM[[#This Row],[Round]]=$B$1, Jan_2026_SotM[[#This Row],[Low Seed]]<=2*Jan_2026_SotM[[#This Row],[Max Seed]]-$A$1, FALSE())) -> FALSE | J7: x | K7: x | L7: x | N7: =IF(Jan_2026_SotM[[#This Row],[Num]]>=$A$1, "-", IF(Jan_2026_SotM[[#This Row],[Initial 1]], VLOOKUP(Jan_2026_SotM[[#This Row],[Top Seed]], $Z$2:$AE$17, 6, FALSE), OFFSET(Jan_2026_SotM[[#This Row],[Winner]], Jan_2026_SotM[[#This Row],[Max Seed]], 0))) -> luv stuck | O7: =COUNTIF(Jan_2026_SotM[[#This Row],[J]:[H]],"x") -> 3 | P7: =IF(Jan_2026_SotM[[#This Row],[Num]]>=$A$1, "-", IF(Jan_2026_SotM[[#This Row],[Score 1]]>=3, Jan_2026_SotM[[#This Row],[Song 1]], IF(Jan_2026_SotM[[#This Row],[Score 2]]>=3, Jan_2026_SotM[[#This Row],[Song 2]], "TBD"))) -> luv stuck | Q7: =COUNTIF(Jan_2026_SotM[[#This Row],[H ]:[J ]],"x") -> 2 | R7: =IF(Jan_2026_SotM[[#This Row],[Num]]>=$A$1, "-", IF(Jan_2026_SotM[[#This Row],[Initial 2]], VLOOKUP(Jan_2026_SotM[[#This Row],[Low Seed]], $Z$2:$AE$17, 6, FALSE), OFFSET(Jan_2026_SotM[[#This Row],[Winner]], 2*(Jan_2026_SotM[[#This Row],[Max Seed]]-Jan_2026_SotM[[#This Row],[Low Seed]])+1, 0))) -> All Night Radio | S7: x | W7: x | X7: =IF(OR(Jan_2026_SotM[[#This Row],[Song 1]]="TBD", Jan_2026_SotM[[#This Row],[Song 2]]="TBD"), "TBD", _xlfn.CONCAT(IF(_xlfn.XOR(ISBLANK(Jan_2026_SotM[[#This Row],[J]]), ISBLANK(Jan_2026_SotM[[#This Row],[J ]])), "", "J "), IF(_xlfn.XOR(ISBLANK(Jan_2026_SotM[[#This Row],[D]]), ISBLANK(Jan_2026_SotM[[#This Row],[D ]])), "", "D "), IF(_xlfn.XOR(ISBLANK(Jan_2026_SotM[[#This Row],[L]]), ISBLANK(Jan_2026_SotM[[#This Row],[L ]])), "", "L "), IF(_xlfn.XOR(ISBLANK(Jan_2026_SotM[[#This Row],[S]]), ISBLANK(Jan_2026_SotM[[#This Row],[S ]])), "", "S "), IF(_xlfn.XOR(ISBLANK(Jan_2026_SotM[[#This Row],[H]]), ISBLANK(Jan_2026_SotM[[#This Row],[H ]])), "", "H "))) | Z7: =IF(AC7>0, COUNTIF(AC$2:AC$17, "<"&AC7) + COUNTIFS(AC$2:AC$17, AC7, AD$2:AD$17, "<"&AD7) + COUNTIFS(AC$2:AC$17, AC7, AD$2:AD$17, AD7, AA$2:AA$17, "<"&AA7) + 1, "TBD") -> 12 | AA7: 46035 | AB7: currydestroyer27 | AC7: 2.2 | AD7: 1.4696938 | AE7: SO BAD | AF7: STAYC | AG7: =IF(Z7>1, 2^FLOOR(LOG(Z7-1, 2), 1)+1, 1) -> 9 | AI7: =Jan_2026_SotM[[#This Row],[Max Seed]]/2 + 1 -> 5 | AJ7: =IF(Jan_2026_SotM[[#This Row],[Num]]>=$A$1, "-", IF(Jan_2026_SotM[[#This Row],[Score 1]]>=3, Jan_2026_SotM[[#This Row],[Song 2]], IF(Jan_2026_SotM[[#This Row],[Score 2]]>=3, Jan_2026_SotM[[#This Row],[Song 1]], "TBD"))) -> All Night Radio | AK7: =IFERROR(VLOOKUP(Jan_2025_Results48[[#This Row],[Song Title]], $AE$2:$AG$17, 3, FALSE)-Jan_2025_Results48[[#This Row],[Result]], "TBD") -> 4 | AL7: =IF(AK7<0,"↓",IF(AK7=0,"-","↑")) -> ↑
A8: =_xlfn.CONCAT("Seed ", Jan_2026_SotM[[#This Row],[Top Seed]], " vs ",Jan_2026_SotM[[#This Row],[Low Seed]]) -> Seed 2 vs 7 | B8: 6 | C8: =FLOOR(LOG(Jan_2026_SotM[[#This Row],[Num]], 2), 1) -> 2 | D8: =2^(Jan_2026_SotM[[#This Row],[Round]]+1) -> 8 | E8: =Jan_2026_SotM[[#This Row],[Max Seed]]-Jan_2026_SotM[[#This Row],[Num]] -> 2 | F8: =Jan_2026_SotM[[#This Row],[Max Seed]]-Jan_2026_SotM[[#This Row],[Top Seed]]+1 -> 7 | G8: =IF(Jan_2026_SotM[[#This Row],[Round]]=$C$1, TRUE(), IF(Jan_2026_SotM[[#This Row],[Round]]=$B$1, Jan_2026_SotM[[#This Row],[Top Seed]]<=2*Jan_2026_SotM[[#This Row],[Max Seed]]-$A$1, FALSE())) -> FALSE | H8: =IF(Jan_2026_SotM[[#This Row],[Round]]=$C$1, TRUE(), IF(Jan_2026_SotM[[#This Row],[Round]]=$B$1, Jan_2026_SotM[[#This Row],[Low Seed]]<=2*Jan_2026_SotM[[#This Row],[Max Seed]]-$A$1, FALSE())) -> FALSE | J8: x | N8: =IF(Jan_2026_SotM[[#This Row],[Num]]>=$A$1, "-", IF(Jan_2026_SotM[[#This Row],[Initial 1]], VLOOKUP(Jan_2026_SotM[[#This Row],[Top Seed]], $Z$2:$AE$17, 6, FALSE), OFFSET(Jan_2026_SotM[[#This Row],[Winner]], Jan_2026_SotM[[#This Row],[Max Seed]], 0))) -> Messages from the Stars | O8: =COUNTIF(Jan_2026_SotM[[#This Row],[J]:[H]],"x") -> 1 | P8: =IF(Jan_2026_SotM[[#This Row],[Num]]>=$A$1, "-", IF(Jan_2026_SotM[[#This Row],[Score 1]]>=3, Jan_2026_SotM[[#This Row],[Song 1]], IF(Jan_2026_SotM[[#This Row],[Score 2]]>=3, Jan_2026_SotM[[#This Row],[Song 2]], "TBD"))) -> BABY SAID (Sam) | Q8: =COUNTIF(Jan_2026_SotM[[#This Row],[H ]:[J ]],"x") -> 4 | R8: =IF(Jan_2026_SotM[[#This Row],[Num]]>=$A$1, "-", IF(Jan_2026_SotM[[#This Row],[Initial 2]], VLOOKUP(Jan_2026_SotM[[#This Row],[Low Seed]], $Z$2:$AE$17, 6, FALSE), OFFSET(Jan_2026_SotM[[#This Row],[Winner]], 2*(Jan_2026_SotM[[#This Row],[Max Seed]]-Jan_2026_SotM[[#This Row],[Low Seed]])+1, 0))) -> BABY SAID (Sam) | S8: x | T8: x | U8: x | W8: x | X8: =IF(OR(Jan_2026_SotM[[#This Row],[Song 1]]="TBD", Jan_2026_SotM[[#This Row],[Song 2]]="TBD"), "TBD", _xlfn.CONCAT(IF(_xlfn.XOR(ISBLANK(Jan_2026_SotM[[#This Row],[J]]), ISBLANK(Jan_2026_SotM[[#This Row],[J ]])), "", "J "), IF(_xlfn.XOR(ISBLANK(Jan_2026_SotM[[#This Row],[D]]), ISBLANK(Jan_2026_SotM[[#This Row],[D ]])), "", "D "), IF(_xlfn.XOR(ISBLANK(Jan_2026_SotM[[#This Row],[L]]), ISBLANK(Jan_2026_SotM[[#This Row],[L ]])), "", "L "), IF(_xlfn.XOR(ISBLANK(Jan_2026_SotM[[#This Row],[S]]), ISBLANK(Jan_2026_SotM[[#This Row],[S ]])), "", "S "), IF(_xlfn.XOR(ISBLANK(Jan_2026_SotM[[#This Row],[H]]), ISBLANK(Jan_2026_SotM[[#This Row],[H ]])), "", "H "))) | Z8: =IF(AC8>0, COUNTIF(AC$2:AC$17, "<"&AC8) + COUNTIFS(AC$2:AC$17, AC8, AD$2:AD$17, "<"&AD8) + COUNTIFS(AC$2:AC$17, AC8, AD$2:AD$17, AD8, AA$2:AA$17, "<"&AA8) + 1, "TBD") -> 11 | AA8: 46036 | AB8: alappatjoe | AC8: 2.2 | AD8: 0.9797959 | AE8: All Night Radio | AF8: Ado | AG8: =IF(Z8>1, 2^FLOOR(LOG(Z8-1, 2), 1)+1, 1) -> 9 | AI8: =Jan_2026_SotM[[#This Row],[Max Seed]]/2 + 1 -> 5 | AJ8: =IF(Jan_2026_SotM[[#This Row],[Num]]>=$A$1, "-", IF(Jan_2026_SotM[[#This Row],[Score 1]]>=3, Jan_2026_SotM[[#This Row],[Song 2]], IF(Jan_2026_SotM[[#This Row],[Score 2]]>=3, Jan_2026_SotM[[#This Row],[Song 1]], "TBD"))) -> Messages from the Stars | AK8: =IFERROR(VLOOKUP(Jan_2025_Results48[[#This Row],[Song Title]], $AE$2:$AG$17, 3, FALSE)-Jan_2025_Results48[[#This Row],[Result]], "TBD") -> 4 | AL8: =IF(AK8<0,"↓",IF(AK8=0,"-","↑")) -> ↑
A9: =_xlfn.CONCAT("Seed ", Jan_2026_SotM[[#This Row],[Top Seed]], " vs ",Jan_2026_SotM[[#This Row],[Low Seed]]) -> Seed 1 vs 8 | B9: 7 | C9: =FLOOR(LOG(Jan_2026_SotM[[#This Row],[Num]], 2), 1) -> 2 | D9: =2^(Jan_2026_SotM[[#This Row],[Round]]+1) -> 8 | E9: =Jan_2026_SotM[[#This Row],[Max Seed]]-Jan_2026_SotM[[#This Row],[Num]] -> 1 | F9: =Jan_2026_SotM[[#This Row],[Max Seed]]-Jan_2026_SotM[[#This Row],[Top Seed]]+1 -> 8 | G9: =IF(Jan_2026_SotM[[#This Row],[Round]]=$C$1, TRUE(), IF(Jan_2026_SotM[[#This Row],[Round]]=$B$1, Jan_2026_SotM[[#This Row],[Top Seed]]<=2*Jan_2026_SotM[[#This Row],[Max Seed]]-$A$1, FALSE())) -> FALSE | H9: =IF(Jan_2026_SotM[[#This Row],[Round]]=$C$1, TRUE(), IF(Jan_2026_SotM[[#This Row],[Round]]=$B$1, Jan_2026_SotM[[#This Row],[Low Seed]]<=2*Jan_2026_SotM[[#This Row],[Max Seed]]-$A$1, FALSE())) -> FALSE | I9: x | J9: x | L9: x | N9: =IF(Jan_2026_SotM[[#This Row],[Num]]>=$A$1, "-", IF(Jan_2026_SotM[[#This Row],[Initial 1]], VLOOKUP(Jan_2026_SotM[[#This Row],[Top Seed]], $Z$2:$AE$17, 6, FALSE), OFFSET(Jan_2026_SotM[[#This Row],[Winner]], Jan_2026_SotM[[#This Row],[Max Seed]], 0))) -> In Da Club | O9: =COUNTIF(Jan_2026_SotM[[#This Row],[J]:[H]],"x") -> 3 | P9: =IF(Jan_2026_SotM[[#This Row],[Num]]>=$A$1, "-", IF(Jan_2026_SotM[[#This Row],[Score 1]]>=3, Jan_2026_SotM[[#This Row],[Song 1]], IF(Jan_2026_SotM[[#This Row],[Score 2]]>=3, Jan_2026_SotM[[#This Row],[Song 2]], "TBD"))) -> In Da Club | Q9: =COUNTIF(Jan_2026_SotM[[#This Row],[H ]:[J ]],"x") -> 2 | R9: =IF(Jan_2026_SotM[[#This Row],[Num]]>=$A$1, "-", IF(Jan_2026_SotM[[#This Row],[Initial 2]], VLOOKUP(Jan_2026_SotM[[#This Row],[Low Seed]], $Z$2:$AE$17, 6, FALSE), OFFSET(Jan_2026_SotM[[#This Row],[Winner]], 2*(Jan_2026_SotM[[#This Row],[Max Seed]]-Jan_2026_SotM[[#This Row],[Low Seed]])+1, 0))) -> The Color Violet | S9: x | U9: x | X9: =IF(OR(Jan_2026_SotM[[#This Row],[Song 1]]="TBD", Jan_2026_SotM[[#This Row],[Song 2]]="TBD"), "TBD", _xlfn.CONCAT(IF(_xlfn.XOR(ISBLANK(Jan_2026_SotM[[#This Row],[J]]), ISBLANK(Jan_2026_SotM[[#This Row],[J ]])), "", "J "), IF(_xlfn.XOR(ISBLANK(Jan_2026_SotM[[#This Row],[D]]), ISBLANK(Jan_2026_SotM[[#This Row],[D ]])), "", "D "), IF(_xlfn.XOR(ISBLANK(Jan_2026_SotM[[#This Row],[L]]), ISBLANK(Jan_2026_SotM[[#This Row],[L ]])), "", "L "), IF(_xlfn.XOR(ISBLANK(Jan_2026_SotM[[#This Row],[S]]), ISBLANK(Jan_2026_SotM[[#This Row],[S ]])), "", "S "), IF(_xlfn.XOR(ISBLANK(Jan_2026_SotM[[#This Row],[H]]), ISBLANK(Jan_2026_SotM[[#This Row],[H ]])), "", "H "))) | Z9: =IF(AC9>0, COUNTIF(AC$2:AC$17, "<"&AC9) + COUNTIFS(AC$2:AC$17, AC9, AD$2:AD$17, "<"&AD9) + COUNTIFS(AC$2:AC$17, AC9, AD$2:AD$17, AD9, AA$2:AA$17, "<"&AA9) + 1, "TBD") -> 13 | AA9: 46037 | AB9: samuelbattista | AC9: 2.2 | AD9: 1.6 | AE9: Box In The Basement | AF9: nothing,nowhere. | AG9: =IF(Z9>1, 2^FLOOR(LOG(Z9-1, 2), 1)+1, 1) -> 9 | AI9: =Jan_2026_SotM[[#This Row],[Max Seed]]/2 + 1 -> 5 | AJ9: =IF(Jan_2026_SotM[[#This Row],[Num]]>=$A$1, "-", IF(Jan_2026_SotM[[#This Row],[Score 1]]>=3, Jan_2026_SotM[[#This Row],[Song 2]], IF(Jan_2026_SotM[[#This Row],[Score 2]]>=3, Jan_2026_SotM[[#This Row],[Song 1]], "TBD"))) -> The Color Violet | AK9: =IFERROR(VLOOKUP(Jan_2025_Results48[[#This Row],[Song Title]], $AE$2:$AG$17, 3, FALSE)-Jan_2025_Results48[[#This Row],[Result]], "TBD") -> 4 | AL9: =IF(AK9<0,"↓",IF(AK9=0,"-","↑")) -> ↑
A10: =_xlfn.CONCAT("Seed ", Jan_2026_SotM[[#This Row],[Top Seed]], " vs ",Jan_2026_SotM[[#This Row],[Low Seed]]) -> Seed 8 vs 9 | B10: 8 | C10: =FLOOR(LOG(Jan_2026_SotM[[#This Row],[Num]], 2), 1) -> 3 | D10: =2^(Jan_2026_SotM[[#This Row],[Round]]+1) -> 16 | E10: =Jan_2026_SotM[[#This Row],[Max Seed]]-Jan_2026_SotM[[#This Row],[Num]] -> 8 | F10: =Jan_2026_SotM[[#This Row],[Max Seed]]-Jan_2026_SotM[[#This Row],[Top Seed]]+1 -> 9 | G10: =IF(Jan_2026_SotM[[#This Row],[Round]]=$C$1, TRUE(), IF(Jan_2026_SotM[[#This Row],[Round]]=$B$1, Jan_2026_SotM[[#This Row],[Top Seed]]<=2*Jan_2026_SotM[[#This Row],[Max Seed]]-$A$1, FALSE())) -> TRUE | H10: =IF(Jan_2026_SotM[[#This Row],[Round]]=$C$1, TRUE(), IF(Jan_2026_SotM[[#This Row],[Round]]=$B$1, Jan_2026_SotM[[#This Row],[Low Seed]]<=2*Jan_2026_SotM[[#This Row],[Max Seed]]-$A$1, FALSE())) -> TRUE | I10: x | L10: x | N10: =IF(Jan_2026_SotM[[#This Row],[Num]]>=$A$1, "-", IF(Jan_2026_SotM[[#This Row],[Initial 1]], VLOOKUP(Jan_2026_SotM[[#This Row],[Top Seed]], $Z$2:$AE$17, 6, FALSE), OFFSET(Jan_2026_SotM[[#This Row],[Winner]], Jan_2026_SotM[[#This Row],[Max Seed]], 0))) -> Use Me | O10: =COUNTIF(Jan_2026_SotM[[#This Row],[J]:[H]],"x") -> 2 | P10: =IF(Jan_2026_SotM[[#This Row],[Num]]>=$A$1, "-", IF(Jan_2026_SotM[[#This Row],[Score 1]]>=3, Jan_2026_SotM[[#This Row],[Song 1]], IF(Jan_2026_SotM[[#This Row],[Score 2]]>=3, Jan_2026_SotM[[#This Row],[Song 2]], "TBD"))) -> The Color Violet | Q10: =COUNTIF(Jan_2026_SotM[[#This Row],[H ]:[J ]],"x") -> 3 | R10: =IF(Jan_2026_SotM[[#This Row],[Num]]>=$A$1, "-", IF(Jan_2026_SotM[[#This Row],[Initial 2]], VLOOKUP(Jan_2026_SotM[[#This Row],[Low Seed]], $Z$2:$AE$17, 6, FALSE), OFFSET(Jan_2026_SotM[[#This Row],[Winner]], 2*(Jan_2026_SotM[[#This Row],[Max Seed]]-Jan_2026_SotM[[#This Row],[Low Seed]])+1, 0))) -> The Color Violet | S10: x | U10: x | V10: x | X10: =IF(OR(Jan_2026_SotM[[#This Row],[Song 1]]="TBD", Jan_2026_SotM[[#This Row],[Song 2]]="TBD"), "TBD", _xlfn.CONCAT(IF(_xlfn.XOR(ISBLANK(Jan_2026_SotM[[#This Row],[J]]), ISBLANK(Jan_2026_SotM[[#This Row],[J ]])), "", "J "), IF(_xlfn.XOR(ISBLANK(Jan_2026_SotM[[#This Row],[D]]), ISBLANK(Jan_2026_SotM[[#This Row],[D ]])), "", "D "), IF(_xlfn.XOR(ISBLANK(Jan_2026_SotM[[#This Row],[L]]), ISBLANK(Jan_2026_SotM[[#This Row],[L ]])), "", "L "), IF(_xlfn.XOR(ISBLANK(Jan_2026_SotM[[#This Row],[S]]), ISBLANK(Jan_2026_SotM[[#This Row],[S ]])), "", "S "), IF(_xlfn.XOR(ISBLANK(Jan_2026_SotM[[#This Row],[H]]), ISBLANK(Jan_2026_SotM[[#This Row],[H ]])), "", "H "))) | Z10: =IF(AC10>0, COUNTIF(AC$2:AC$17, "<"&AC10) + COUNTIFS(AC$2:AC$17, AC10, AD$2:AD$17, "<"&AD10) + COUNTIFS(AC$2:AC$17, AC10, AD$2:AD$17, AD10, AA$2:AA$17, "<"&AA10) + 1, "TBD") -> 4 | AA10: 46041 | AB10: loganworsdell | AC10: 1.8 | AD10: 0.74833148 | AE10: NERVOUS | AF10: Sam Gellaitry | AG10: =IF(Z10>1, 2^FLOOR(LOG(Z10-1, 2), 1)+1, 1) -> 3 | AI10: =Jan_2026_SotM[[#This Row],[Max Seed]]/2 + 1 -> 9 | AJ10: =IF(Jan_2026_SotM[[#This Row],[Num]]>=$A$1, "-", IF(Jan_2026_SotM[[#This Row],[Score 1]]>=3, Jan_2026_SotM[[#This Row],[Song 2]], IF(Jan_2026_SotM[[#This Row],[Score 2]]>=3, Jan_2026_SotM[[#This Row],[Song 1]], "TBD"))) -> Use Me | AK10: =IFERROR(VLOOKUP(Jan_2025_Results48[[#This Row],[Song Title]], $AE$2:$AG$17, 3, FALSE)-Jan_2025_Results48[[#This Row],[Result]], "TBD") -> -4 | AL10: =IF(AK10<0,"↓",IF(AK10=0,"-","↑")) -> ↓
A11: =_xlfn.CONCAT("Seed ", Jan_2026_SotM[[#This Row],[Top Seed]], " vs ",Jan_2026_SotM[[#This Row],[Low Seed]]) -> Seed 7 vs 10 | B11: 9 | C11: =FLOOR(LOG(Jan_2026_SotM[[#This Row],[Num]], 2), 1) -> 3 | D11: =2^(Jan_2026_SotM[[#This Row],[Round]]+1) -> 16 | E11: =Jan_2026_SotM[[#This Row],[Max Seed]]-Jan_2026_SotM[[#This Row],[Num]] -> 7 | F11: =Jan_2026_SotM[[#This Row],[Max Seed]]-Jan_2026_SotM[[#This Row],[Top Seed]]+1 -> 10 | G11: =IF(Jan_2026_SotM[[#This Row],[Round]]=$C$1, TRUE(), IF(Jan_2026_SotM[[#This Row],[Round]]=$B$1, Jan_2026_SotM[[#This Row],[Top Seed]]<=2*Jan_2026_SotM[[#This Row],[Max Seed]]-$A$1, FALSE())) -> TRUE | H11: =IF(Jan_2026_SotM[[#This Row],[Round]]=$C$1, TRUE(), IF(Jan_2026_SotM[[#This Row],[Round]]=$B$1, Jan_2026_SotM[[#This Row],[Low Seed]]<=2*Jan_2026_SotM[[#This Row],[Max Seed]]-$A$1, FALSE())) -> TRUE | N11: =IF(Jan_2026_SotM[[#This Row],[Num]]>=$A$1, "-", IF(Jan_2026_SotM[[#This Row],[Initial 1]], VLOOKUP(Jan_2026_SotM[[#This Row],[Top Seed]], $Z$2:$AE$17, 6, FALSE), OFFSET(Jan_2026_SotM[[#This Row],[Winner]], Jan_2026_SotM[[#This Row],[Max Seed]], 0))) -> Possum Kingdom | O11: =COUNTIF(Jan_2026_SotM[[#This Row],[J]:[H]],"x") -> 0 | P11: =IF(Jan_2026_SotM[[#This Row],[Num]]>=$A$1, "-", IF(Jan_2026_SotM[[#This Row],[Score 1]]>=3, Jan_2026_SotM[[#This Row],[Song 1]], IF(Jan_2026_SotM[[#This Row],[Score 2]]>=3, Jan_2026_SotM[[#This Row],[Song 2]], "TBD"))) -> BABY SAID (Sam) | Q11: =COUNTIF(Jan_2026_SotM[[#This Row],[H ]:[J ]],"x") -> 5 | R11: =IF(Jan_2026_SotM[[#This Row],[Num]]>=$A$1, "-", IF(Jan_2026_SotM[[#This Row],[Initial 2]], VLOOKUP(Jan_2026_SotM[[#This Row],[Low Seed]], $Z$2:$AE$17, 6, FALSE), OFFSET(Jan_2026_SotM[[#This Row],[Winner]], 2*(Jan_2026_SotM[[#This Row],[Max Seed]]-Jan_2026_SotM[[#This Row],[Low Seed]])+1, 0))) -> BABY SAID (Sam) | S11: x | T11: x | U11: x | V11: x | W11: x | X11: =IF(OR(Jan_2026_SotM[[#This Row],[Song 1]]="TBD", Jan_2026_SotM[[#This Row],[Song 2]]="TBD"), "TBD", _xlfn.CONCAT(IF(_xlfn.XOR(ISBLANK(Jan_2026_SotM[[#This Row],[J]]), ISBLANK(Jan_2026_SotM[[#This Row],[J ]])), "", "J "), IF(_xlfn.XOR(ISBLANK(Jan_2026_SotM[[#This Row],[D]]), ISBLANK(Jan_2026_SotM[[#This Row],[D ]])), "", "D "), IF(_xlfn.XOR(ISBLANK(Jan_2026_SotM[[#This Row],[L]]), ISBLANK(Jan_2026_SotM[[#This Row],[L ]])), "", "L "), IF(_xlfn.XOR(ISBLANK(Jan_2026_SotM[[#This Row],[S]]), ISBLANK(Jan_2026_SotM[[#This Row],[S ]])), "", "S "), IF(_xlfn.XOR(ISBLANK(Jan_2026_SotM[[#This Row],[H]]), ISBLANK(Jan_2026_SotM[[#This Row],[H ]])), "", "H "))) | Z11: =IF(AC11>0, COUNTIF(AC$2:AC$17, "<"&AC11) + COUNTIFS(AC$2:AC$17, AC11, AD$2:AD$17, "<"&AD11) + COUNTIFS(AC$2:AC$17, AC11, AD$2:AD$17, AD11, AA$2:AA$17, "<"&AA11) + 1, "TBD") -> 7 | AA11: 46042 | AB11: samuelbattista | AC11: 2 | AD11: 0.89442719 | AE11: Possum Kingdom | AF11: Toadies | AG11: =IF(Z11>1, 2^FLOOR(LOG(Z11-1, 2), 1)+1, 1) -> 5 | AI11: =Jan_2026_SotM[[#This Row],[Max Seed]]/2 + 1 -> 9 | AJ11: =IF(Jan_2026_SotM[[#This Row],[Num]]>=$A$1, "-", IF(Jan_2026_SotM[[#This Row],[Score 1]]>=3, Jan_2026_SotM[[#This Row],[Song 2]], IF(Jan_2026_SotM[[#This Row],[Score 2]]>=3, Jan_2026_SotM[[#This Row],[Song 1]], "TBD"))) -> Possum Kingdom | AK11: =IFERROR(VLOOKUP(Jan_2025_Results48[[#This Row],[Song Title]], $AE$2:$AG$17, 3, FALSE)-Jan_2025_Results48[[#This Row],[Result]], "TBD") -> -4 | AL11: =IF(AK11<0,"↓",IF(AK11=0,"-","↑")) -> ↓
A12: =_xlfn.CONCAT("Seed ", Jan_2026_SotM[[#This Row],[Top Seed]], " vs ",Jan_2026_SotM[[#This Row],[Low Seed]]) -> Seed 6 vs 11 | B12: 10 | C12: =FLOOR(LOG(Jan_2026_SotM[[#This Row],[Num]], 2), 1) -> 3 | D12: =2^(Jan_2026_SotM[[#This Row],[Round]]+1) -> 16 | E12: =Jan_2026_SotM[[#This Row],[Max Seed]]-Jan_2026_SotM[[#This Row],[Num]] -> 6 | F12: =Jan_2026_SotM[[#This Row],[Max Seed]]-Jan_2026_SotM[[#This Row],[Top Seed]]+1 -> 11 | G12: =IF(Jan_2026_SotM[[#This Row],[Round]]=$C$1, TRUE(), IF(Jan_2026_SotM[[#This Row],[Round]]=$B$1, Jan_2026_SotM[[#This Row],[Top Seed]]<=2*Jan_2026_SotM[[#This Row],[Max Seed]]-$A$1, FALSE())) -> TRUE | H12: =IF(Jan_2026_SotM[[#This Row],[Round]]=$C$1, TRUE(), IF(Jan_2026_SotM[[#This Row],[Round]]=$B$1, Jan_2026_SotM[[#This Row],[Low Seed]]<=2*Jan_2026_SotM[[#This Row],[Max Seed]]-$A$1, FALSE())) -> TRUE | K12: x | L12: x | N12: =IF(Jan_2026_SotM[[#This Row],[Num]]>=$A$1, "-", IF(Jan_2026_SotM[[#This Row],[Initial 1]], VLOOKUP(Jan_2026_SotM[[#This Row],[Top Seed]], $Z$2:$AE$17, 6, FALSE), OFFSET(Jan_2026_SotM[[#This Row],[Winner]], Jan_2026_SotM[[#This Row],[Max Seed]], 0))) -> Layla | O12: =COUNTIF(Jan_2026_SotM[[#This Row],[J]:[H]],"x") -> 2 | P12: =IF(Jan_2026_SotM[[#This Row],[Num]]>=$A$1, "-", IF(Jan_2026_SotM[[#This Row],[Score 1]]>=3, Jan_2026_SotM[[#This Row],[Song 1]], IF(Jan_2026_SotM[[#This Row],[Score 2]]>=3, Jan_2026_SotM[[#This Row],[Song 2]], "TBD"))) -> All Night Radio | Q12: =COUNTIF(Jan_2026_SotM[[#This Row],[H ]:[J ]],"x") -> 3 | R12: =IF(Jan_2026_SotM[[#This Row],[Num]]>=$A$1, "-", IF(Jan_2026_SotM[[#This Row],[Initial 2]], VLOOKUP(Jan_2026_SotM[[#This Row],[Low Seed]], $Z$2:$AE$17, 6, FALSE), OFFSET(Jan_2026_SotM[[#This Row],[Winner]], 2*(Jan_2026_SotM[[#This Row],[Max Seed]]-Jan_2026_SotM[[#This Row],[Low Seed]])+1, 0))) -> All Night Radio | S12: x | V12: x | W12: x | X12: =IF(OR(Jan_2026_SotM[[#This Row],[Song 1]]="TBD", Jan_2026_SotM[[#This Row],[Song 2]]="TBD"), "TBD", _xlfn.CONCAT(IF(_xlfn.XOR(ISBLANK(Jan_2026_SotM[[#This Row],[J]]), ISBLANK(Jan_2026_SotM[[#This Row],[J ]])), "", "J "), IF(_xlfn.XOR(ISBLANK(Jan_2026_SotM[[#This Row],[D]]), ISBLANK(Jan_2026_SotM[[#This Row],[D ]])), "", "D "), IF(_xlfn.XOR(ISBLANK(Jan_2026_SotM[[#This Row],[L]]), ISBLANK(Jan_2026_SotM[[#This Row],[L ]])), "", "L "), IF(_xlfn.XOR(ISBLANK(Jan_2026_SotM[[#This Row],[S]]), ISBLANK(Jan_2026_SotM[[#This Row],[S ]])), "", "S "), IF(_xlfn.XOR(ISBLANK(Jan_2026_SotM[[#This Row],[H]]), ISBLANK(Jan_2026_SotM[[#This Row],[H ]])), "", "H "))) | Z12: =IF(AC12>0, COUNTIF(AC$2:AC$17, "<"&AC12) + COUNTIFS(AC$2:AC$17, AC12, AD$2:AD$17, "<"&AD12) + COUNTIFS(AC$2:AC$17, AC12, AD$2:AD$17, AD12, AA$2:AA$17, "<"&AA12) + 1, "TBD") -> 8 | AA12: 46043 | AB12: samuelbattista | AC12: 2 | AD12: 0.89442719 | AE12: Use Me | AF12: Bill Withers | AG12: =IF(Z12>1, 2^FLOOR(LOG(Z12-1, 2), 1)+1, 1) -> 5 | AI12: =Jan_2026_SotM[[#This Row],[Max Seed]]/2 + 1 -> 9 | AJ12: =IF(Jan_2026_SotM[[#This Row],[Num]]>=$A$1, "-", IF(Jan_2026_SotM[[#This Row],[Score 1]]>=3, Jan_2026_SotM[[#This Row],[Song 2]], IF(Jan_2026_SotM[[#This Row],[Score 2]]>=3, Jan_2026_SotM[[#This Row],[Song 1]], "TBD"))) -> Layla | AK12: =IFERROR(VLOOKUP(Jan_2025_Results48[[#This Row],[Song Title]], $AE$2:$AG$17, 3, FALSE)-Jan_2025_Results48[[#This Row],[Result]], "TBD") -> -4 | AL12: =IF(AK12<0,"↓",IF(AK12=0,"-","↑")) -> ↓
A13: =_xlfn.CONCAT("Seed ", Jan_2026_SotM[[#This Row],[Top Seed]], " vs ",Jan_2026_SotM[[#This Row],[Low Seed]]) -> Seed 5 vs 12 | B13: 11 | C13: =FLOOR(LOG(Jan_2026_SotM[[#This Row],[Num]], 2), 1) -> 3 | D13: =2^(Jan_2026_SotM[[#This Row],[Round]]+1) -> 16 | E13: =Jan_2026_SotM[[#This Row],[Max Seed]]-Jan_2026_SotM[[#This Row],[Num]] -> 5 | F13: =Jan_2026_SotM[[#This Row],[Max Seed]]-Jan_2026_SotM[[#This Row],[Top Seed]]+1 -> 12 | G13: =IF(Jan_2026_SotM[[#This Row],[Round]]=$C$1, TRUE(), IF(Jan_2026_SotM[[#This Row],[Round]]=$B$1, Jan_2026_SotM[[#This Row],[Top Seed]]<=2*Jan_2026_SotM[[#This Row],[Max Seed]]-$A$1, FALSE())) -> TRUE | H13: =IF(Jan_2026_SotM[[#This Row],[Round]]=$C$1, TRUE(), IF(Jan_2026_SotM[[#This Row],[Round]]=$B$1, Jan_2026_SotM[[#This Row],[Low Seed]]<=2*Jan_2026_SotM[[#This Row],[Max Seed]]-$A$1, FALSE())) -> TRUE | I13: x | J13: x | K13: x | L13: x | N13: =IF(Jan_2026_SotM[[#This Row],[Num]]>=$A$1, "-", IF(Jan_2026_SotM[[#This Row],[Initial 1]], VLOOKUP(Jan_2026_SotM[[#This Row],[Top Seed]], $Z$2:$AE$17, 6, FALSE), OFFSET(Jan_2026_SotM[[#This Row],[Winner]], Jan_2026_SotM[[#This Row],[Max Seed]], 0))) -> Hey Jude | O13: =COUNTIF(Jan_2026_SotM[[#This Row],[J]:[H]],"x") -> 4 | P13: =IF(Jan_2026_SotM[[#This Row],[Num]]>=$A$1, "-", IF(Jan_2026_SotM[[#This Row],[Score 1]]>=3, Jan_2026_SotM[[#This Row],[Song 1]], IF(Jan_2026_SotM[[#This Row],[Score 2]]>=3, Jan_2026_SotM[[#This Row],[Song 2]], "TBD"))) -> Hey Jude | Q13: =COUNTIF(Jan_2026_SotM[[#This Row],[H ]:[J ]],"x") -> 1 | R13: =IF(Jan_2026_SotM[[#This Row],[Num]]>=$A$1, "-", IF(Jan_2026_SotM[[#This Row],[Initial 2]], VLOOKUP(Jan_2026_SotM[[#This Row],[Low Seed]], $Z$2:$AE$17, 6, FALSE), OFFSET(Jan_2026_SotM[[#This Row],[Winner]], 2*(Jan_2026_SotM[[#This Row],[Max Seed]]-Jan_2026_SotM[[#This Row],[Low Seed]])+1, 0))) -> SO BAD | S13: x | X13: =IF(OR(Jan_2026_SotM[[#This Row],[Song 1]]="TBD", Jan_2026_SotM[[#This Row],[Song 2]]="TBD"), "TBD", _xlfn.CONCAT(IF(_xlfn.XOR(ISBLANK(Jan_2026_SotM[[#This Row],[J]]), ISBLANK(Jan_2026_SotM[[#This Row],[J ]])), "", "J "), IF(_xlfn.XOR(ISBLANK(Jan_2026_SotM[[#This Row],[D]]), ISBLANK(Jan_2026_SotM[[#This Row],[D ]])), "", "D "), IF(_xlfn.XOR(ISBLANK(Jan_2026_SotM[[#This Row],[L]]), ISBLANK(Jan_2026_SotM[[#This Row],[L ]])), "", "L "), IF(_xlfn.XOR(ISBLANK(Jan_2026_SotM[[#This Row],[S]]), ISBLANK(Jan_2026_SotM[[#This Row],[S ]])), "", "S "), IF(_xlfn.XOR(ISBLANK(Jan_2026_SotM[[#This Row],[H]]), ISBLANK(Jan_2026_SotM[[#This Row],[H ]])), "", "H "))) | Z13: =IF(AC13>0, COUNTIF(AC$2:AC$17, "<"&AC13) + COUNTIFS(AC$2:AC$17, AC13, AD$2:AD$17, "<"&AD13) + COUNTIFS(AC$2:AC$17, AC13, AD$2:AD$17, AD13, AA$2:AA$17, "<"&AA13) + 1, "TBD") -> 10 | AA13: 46044 | AB13: currydestroyer27 | AC13: 2.2 | AD13: 0.74833148 | AE13: BABY SAID (Sam) | AF13: Maneskin | AG13: =IF(Z13>1, 2^FLOOR(LOG(Z13-1, 2), 1)+1, 1) -> 9 | AI13: =Jan_2026_SotM[[#This Row],[Max Seed]]/2 + 1 -> 9 | AJ13: =IF(Jan_2026_SotM[[#This Row],[Num]]>=$A$1, "-", IF(Jan_2026_SotM[[#This Row],[Score 1]]>=3, Jan_2026_SotM[[#This Row],[Song 2]], IF(Jan_2026_SotM[[#This Row],[Score 2]]>=3, Jan_2026_SotM[[#This Row],[Song 1]], "TBD"))) -> SO BAD | AK13: =IFERROR(VLOOKUP(Jan_2025_Results48[[#This Row],[Song Title]], $AE$2:$AG$17, 3, FALSE)-Jan_2025_Results48[[#This Row],[Result]], "TBD") -> 0 | AL13: =IF(AK13<0,"↓",IF(AK13=0,"-","↑")) -> -
A14: =_xlfn.CONCAT("Seed ", Jan_2026_SotM[[#This Row],[Top Seed]], " vs ",Jan_2026_SotM[[#This Row],[Low Seed]]) -> Seed 4 vs 13 | B14: 12 | C14: =FLOOR(LOG(Jan_2026_SotM[[#This Row],[Num]], 2), 1) -> 3 | D14: =2^(Jan_2026_SotM[[#This Row],[Round]]+1) -> 16 | E14: =Jan_2026_SotM[[#This Row],[Max Seed]]-Jan_2026_SotM[[#This Row],[Num]] -> 4 | F14: =Jan_2026_SotM[[#This Row],[Max Seed]]-Jan_2026_SotM[[#This Row],[Top Seed]]+1 -> 13 | G14: =IF(Jan_2026_SotM[[#This Row],[Round]]=$C$1, TRUE(), IF(Jan_2026_SotM[[#This Row],[Round]]=$B$1, Jan_2026_SotM[[#This Row],[Top Seed]]<=2*Jan_2026_SotM[[#This Row],[Max Seed]]-$A$1, FALSE())) -> TRUE | H14: =IF(Jan_2026_SotM[[#This Row],[Round]]=$C$1, TRUE(), IF(Jan_2026_SotM[[#This Row],[Round]]=$B$1, Jan_2026_SotM[[#This Row],[Low Seed]]<=2*Jan_2026_SotM[[#This Row],[Max Seed]]-$A$1, FALSE())) -> TRUE | I14: x | J14: x | K14: x | L14: x | M14: x | N14: =IF(Jan_2026_SotM[[#This Row],[Num]]>=$A$1, "-", IF(Jan_2026_SotM[[#This Row],[Initial 1]], VLOOKUP(Jan_2026_SotM[[#This Row],[Top Seed]], $Z$2:$AE$17, 6, FALSE), OFFSET(Jan_2026_SotM[[#This Row],[Winner]], Jan_2026_SotM[[#This Row],[Max Seed]], 0))) -> NERVOUS | O14: =COUNTIF(Jan_2026_SotM[[#This Row],[J]:[H]],"x") -> 5 | P14: =IF(Jan_2026_SotM[[#This Row],[Num]]>=$A$1, "-", IF(Jan_2026_SotM[[#This Row],[Score 1]]>=3, Jan_2026_SotM[[#This Row],[Song 1]], IF(Jan_2026_SotM[[#This Row],[Score 2]]>=3, Jan_2026_SotM[[#This Row],[Song 2]], "TBD"))) -> NERVOUS | Q14: =COUNTIF(Jan_2026_SotM[[#This Row],[H ]:[J ]],"x") -> 0 | R14: =IF(Jan_2026_SotM[[#This Row],[Num]]>=$A$1, "-", IF(Jan_2026_SotM[[#This Row],[Initial 2]], VLOOKUP(Jan_2026_SotM[[#This Row],[Low Seed]], $Z$2:$AE$17, 6, FALSE), OFFSET(Jan_2026_SotM[[#This Row],[Winner]], 2*(Jan_2026_SotM[[#This Row],[Max Seed]]-Jan_2026_SotM[[#This Row],[Low Seed]])+1, 0))) -> Box In The Basement | X14: =IF(OR(Jan_2026_SotM[[#This Row],[Song 1]]="TBD", Jan_2026_SotM[[#This Row],[Song 2]]="TBD"), "TBD", _xlfn.CONCAT(IF(_xlfn.XOR(ISBLANK(Jan_2026_SotM[[#This Row],[J]]), ISBLANK(Jan_2026_SotM[[#This Row],[J ]])), "", "J "), IF(_xlfn.XOR(ISBLANK(Jan_2026_SotM[[#This Row],[D]]), ISBLANK(Jan_2026_SotM[[#This Row],[D ]])), "", "D "), IF(_xlfn.XOR(ISBLANK(Jan_2026_SotM[[#This Row],[L]]), ISBLANK(Jan_2026_SotM[[#This Row],[L ]])), "", "L "), IF(_xlfn.XOR(ISBLANK(Jan_2026_SotM[[#This Row],[S]]), ISBLANK(Jan_2026_SotM[[#This Row],[S ]])), "", "S "), IF(_xlfn.XOR(ISBLANK(Jan_2026_SotM[[#This Row],[H]]), ISBLANK(Jan_2026_SotM[[#This Row],[H ]])), "", "H "))) | Z14: =IF(AC14>0, COUNTIF(AC$2:AC$17, "<"&AC14) + COUNTIFS(AC$2:AC$17, AC14, AD$2:AD$17, "<"&AD14) + COUNTIFS(AC$2:AC$17, AC14, AD$2:AD$17, AD14, AA$2:AA$17, "<"&AA14) + 1, "TBD") -> 3 | AA14: 46048 | AB14: alappatjoe | AC14: 1.8 | AD14: 0.4 | AE14: Sweet Disposition | AF14: The Temper Trap | AG14: =IF(Z14>1, 2^FLOOR(LOG(Z14-1, 2), 1)+1, 1) -> 3 | AI14: =Jan_2026_SotM[[#This Row],[Max Seed]]/2 + 1 -> 9 | AJ14: =IF(Jan_2026_SotM[[#This Row],[Num]]>=$A$1, "-", IF(Jan_2026_SotM[[#This Row],[Score 1]]>=3, Jan_2026_SotM[[#This Row],[Song 2]], IF(Jan_2026_SotM[[#This Row],[Score 2]]>=3, Jan_2026_SotM[[#This Row],[Song 1]], "TBD"))) -> Box In The Basement | AK14: =IFERROR(VLOOKUP(Jan_2025_Results48[[#This Row],[Song Title]], $AE$2:$AG$17, 3, FALSE)-Jan_2025_Results48[[#This Row],[Result]], "TBD") -> 0 | AL14: =IF(AK14<0,"↓",IF(AK14=0,"-","↑")) -> -
A15: =_xlfn.CONCAT("Seed ", Jan_2026_SotM[[#This Row],[Top Seed]], " vs ",Jan_2026_SotM[[#This Row],[Low Seed]]) -> Seed 3 vs 14 | B15: 13 | C15: =FLOOR(LOG(Jan_2026_SotM[[#This Row],[Num]], 2), 1) -> 3 | D15: =2^(Jan_2026_SotM[[#This Row],[Round]]+1) -> 16 | E15: =Jan_2026_SotM[[#This Row],[Max Seed]]-Jan_2026_SotM[[#This Row],[Num]] -> 3 | F15: =Jan_2026_SotM[[#This Row],[Max Seed]]-Jan_2026_SotM[[#This Row],[Top Seed]]+1 -> 14 | G15: =IF(Jan_2026_SotM[[#This Row],[Round]]=$C$1, TRUE(), IF(Jan_2026_SotM[[#This Row],[Round]]=$B$1, Jan_2026_SotM[[#This Row],[Top Seed]]<=2*Jan_2026_SotM[[#This Row],[Max Seed]]-$A$1, FALSE())) -> TRUE | H15: =IF(Jan_2026_SotM[[#This Row],[Round]]=$C$1, TRUE(), IF(Jan_2026_SotM[[#This Row],[Round]]=$B$1, Jan_2026_SotM[[#This Row],[Low Seed]]<=2*Jan_2026_SotM[[#This Row],[Max Seed]]-$A$1, FALSE())) -> TRUE | I15: x | M15: x | N15: =IF(Jan_2026_SotM[[#This Row],[Num]]>=$A$1, "-", IF(Jan_2026_SotM[[#This Row],[Initial 1]], VLOOKUP(Jan_2026_SotM[[#This Row],[Top Seed]], $Z$2:$AE$17, 6, FALSE), OFFSET(Jan_2026_SotM[[#This Row],[Winner]], Jan_2026_SotM[[#This Row],[Max Seed]], 0))) -> Sweet Disposition | O15: =COUNTIF(Jan_2026_SotM[[#This Row],[J]:[H]],"x") -> 2 | P15: =IF(Jan_2026_SotM[[#This Row],[Num]]>=$A$1, "-", IF(Jan_2026_SotM[[#This Row],[Score 1]]>=3, Jan_2026_SotM[[#This Row],[Song 1]], IF(Jan_2026_SotM[[#This Row],[Score 2]]>=3, Jan_2026_SotM[[#This Row],[Song 2]], "TBD"))) -> luv stuck | Q15: =COUNTIF(Jan_2026_SotM[[#This Row],[H ]:[J ]],"x") -> 3 | R15: =IF(Jan_2026_SotM[[#This Row],[Num]]>=$A$1, "-", IF(Jan_2026_SotM[[#This Row],[Initial 2]], VLOOKUP(Jan_2026_SotM[[#This Row],[Low Seed]], $Z$2:$AE$17, 6, FALSE), OFFSET(Jan_2026_SotM[[#This Row],[Winner]], 2*(Jan_2026_SotM[[#This Row],[Max Seed]]-Jan_2026_SotM[[#This Row],[Low Seed]])+1, 0))) -> luv stuck | T15: x | U15: x | V15: x | X15: =IF(OR(Jan_2026_SotM[[#This Row],[Song 1]]="TBD", Jan_2026_SotM[[#This Row],[Song 2]]="TBD"), "TBD", _xlfn.CONCAT(IF(_xlfn.XOR(ISBLANK(Jan_2026_SotM[[#This Row],[J]]), ISBLANK(Jan_2026_SotM[[#This Row],[J ]])), "", "J "), IF(_xlfn.XOR(ISBLANK(Jan_2026_SotM[[#This Row],[D]]), ISBLANK(Jan_2026_SotM[[#This Row],[D ]])), "", "D "), IF(_xlfn.XOR(ISBLANK(Jan_2026_SotM[[#This Row],[L]]), ISBLANK(Jan_2026_SotM[[#This Row],[L ]])), "", "L "), IF(_xlfn.XOR(ISBLANK(Jan_2026_SotM[[#This Row],[S]]), ISBLANK(Jan_2026_SotM[[#This Row],[S ]])), "", "S "), IF(_xlfn.XOR(ISBLANK(Jan_2026_SotM[[#This Row],[H]]), ISBLANK(Jan_2026_SotM[[#This Row],[H ]])), "", "H "))) | Z15: =IF(AC15>0, COUNTIF(AC$2:AC$17, "<"&AC15) + COUNTIFS(AC$2:AC$17, AC15, AD$2:AD$17, "<"&AD15) + COUNTIFS(AC$2:AC$17, AC15, AD$2:AD$17, AD15, AA$2:AA$17, "<"&AA15) + 1, "TBD") -> 14 | AA15: 46049 | AB15: loganworsdell | AC15: 2.4 | AD15: 0.8 | AE15: luv stuck | AF15: salute, piri | AG15: =IF(Z15>1, 2^FLOOR(LOG(Z15-1, 2), 1)+1, 1) -> 9 | AI15: =Jan_2026_SotM[[#This Row],[Max Seed]]/2 + 1 -> 9 | AJ15: =IF(Jan_2026_SotM[[#This Row],[Num]]>=$A$1, "-", IF(Jan_2026_SotM[[#This Row],[Score 1]]>=3, Jan_2026_SotM[[#This Row],[Song 2]], IF(Jan_2026_SotM[[#This Row],[Score 2]]>=3, Jan_2026_SotM[[#This Row],[Song 1]], "TBD"))) -> Sweet Disposition | AK15: =IFERROR(VLOOKUP(Jan_2025_Results48[[#This Row],[Song Title]], $AE$2:$AG$17, 3, FALSE)-Jan_2025_Results48[[#This Row],[Result]], "TBD") -> -6 | AL15: =IF(AK15<0,"↓",IF(AK15=0,"-","↑")) -> ↓
A16: =_xlfn.CONCAT("Seed ", Jan_2026_SotM[[#This Row],[Top Seed]], " vs ",Jan_2026_SotM[[#This Row],[Low Seed]]) -> Seed 2 vs 15 | B16: 14 | C16: =FLOOR(LOG(Jan_2026_SotM[[#This Row],[Num]], 2), 1) -> 3 | D16: =2^(Jan_2026_SotM[[#This Row],[Round]]+1) -> 16 | E16: =Jan_2026_SotM[[#This Row],[Max Seed]]-Jan_2026_SotM[[#This Row],[Num]] -> 2 | F16: =Jan_2026_SotM[[#This Row],[Max Seed]]-Jan_2026_SotM[[#This Row],[Top Seed]]+1 -> 15 | G16: =IF(Jan_2026_SotM[[#This Row],[Round]]=$C$1, TRUE(), IF(Jan_2026_SotM[[#This Row],[Round]]=$B$1, Jan_2026_SotM[[#This Row],[Top Seed]]<=2*Jan_2026_SotM[[#This Row],[Max Seed]]-$A$1, FALSE())) -> TRUE | H16: =IF(Jan_2026_SotM[[#This Row],[Round]]=$C$1, TRUE(), IF(Jan_2026_SotM[[#This Row],[Round]]=$B$1, Jan_2026_SotM[[#This Row],[Low Seed]]<=2*Jan_2026_SotM[[#This Row],[Max Seed]]-$A$1, FALSE())) -> TRUE | I16: x | N16: =IF(Jan_2026_SotM[[#This Row],[Num]]>=$A$1, "-", IF(Jan_2026_SotM[[#This Row],[Initial 1]], VLOOKUP(Jan_2026_SotM[[#This Row],[Top Seed]], $Z$2:$AE$17, 6, FALSE), OFFSET(Jan_2026_SotM[[#This Row],[Winner]], Jan_2026_SotM[[#This Row],[Max Seed]], 0))) -> Fly | O16: =COUNTIF(Jan_2026_SotM[[#This Row],[J]:[H]],"x") -> 1 | P16: =IF(Jan_2026_SotM[[#This Row],[Num]]>=$A$1, "-", IF(Jan_2026_SotM[[#This Row],[Score 1]]>=3, Jan_2026_SotM[[#This Row],[Song 1]], IF(Jan_2026_SotM[[#This Row],[Score 2]]>=3, Jan_2026_SotM[[#This Row],[Song 2]], "TBD"))) -> Messages from the Stars | Q16: =COUNTIF(Jan_2026_SotM[[#This Row],[H ]:[J ]],"x") -> 4 | R16: =IF(Jan_2026_SotM[[#This Row],[Num]]>=$A$1, "-", IF(Jan_2026_SotM[[#This Row],[Initial 2]], VLOOKUP(Jan_2026_SotM[[#This Row],[Low Seed]], $Z$2:$AE$17, 6, FALSE), OFFSET(Jan_2026_SotM[[#This Row],[Winner]], 2*(Jan_2026_SotM[[#This Row],[Max Seed]]-Jan_2026_SotM[[#This Row],[Low Seed]])+1, 0))) -> Messages from the Stars | S16: x | T16: x | U16: x | V16: x | X16: =IF(OR(Jan_2026_SotM[[#This Row],[Song 1]]="TBD", Jan_2026_SotM[[#This Row],[Song 2]]="TBD"), "TBD", _xlfn.CONCAT(IF(_xlfn.XOR(ISBLANK(Jan_2026_SotM[[#This Row],[J]]), ISBLANK(Jan_2026_SotM[[#This Row],[J ]])), "", "J "), IF(_xlfn.XOR(ISBLANK(Jan_2026_SotM[[#This Row],[D]]), ISBLANK(Jan_2026_SotM[[#This Row],[D ]])), "", "D "), IF(_xlfn.XOR(ISBLANK(Jan_2026_SotM[[#This Row],[L]]), ISBLANK(Jan_2026_SotM[[#This Row],[L ]])), "", "L "), IF(_xlfn.XOR(ISBLANK(Jan_2026_SotM[[#This Row],[S]]), ISBLANK(Jan_2026_SotM[[#This Row],[S ]])), "", "S "), IF(_xlfn.XOR(ISBLANK(Jan_2026_SotM[[#This Row],[H]]), ISBLANK(Jan_2026_SotM[[#This Row],[H ]])), "", "H "))) | Z16: =IF(AC16>0, COUNTIF(AC$2:AC$17, "<"&AC16) + COUNTIFS(AC$2:AC$17, AC16, AD$2:AD$17, "<"&AD16) + COUNTIFS(AC$2:AC$17, AC16, AD$2:AD$17, AD16, AA$2:AA$17, "<"&AA16) + 1, "TBD") -> 9 | AA16: 46050 | AB16: currydestroyer27 | AC16: 2 | AD16: 1.2649111 | AE16: The Color Violet | AF16: Tory Lanez | AG16: =IF(Z16>1, 2^FLOOR(LOG(Z16-1, 2), 1)+1, 1) -> 9 | AI16: =Jan_2026_SotM[[#This Row],[Max Seed]]/2 + 1 -> 9 | AJ16: =IF(Jan_2026_SotM[[#This Row],[Num]]>=$A$1, "-", IF(Jan_2026_SotM[[#This Row],[Score 1]]>=3, Jan_2026_SotM[[#This Row],[Song 2]], IF(Jan_2026_SotM[[#This Row],[Score 2]]>=3, Jan_2026_SotM[[#This Row],[Song 1]], "TBD"))) -> Fly | AK16: =IFERROR(VLOOKUP(Jan_2025_Results48[[#This Row],[Song Title]], $AE$2:$AG$17, 3, FALSE)-Jan_2025_Results48[[#This Row],[Result]], "TBD") -> -7 | AL16: =IF(AK16<0,"↓",IF(AK16=0,"-","↑")) -> ↓
A17: =_xlfn.CONCAT("Seed ", Jan_2026_SotM[[#This Row],[Top Seed]], " vs ",Jan_2026_SotM[[#This Row],[Low Seed]]) -> Seed 1 vs 16 | B17: 15 | C17: =FLOOR(LOG(Jan_2026_SotM[[#This Row],[Num]], 2), 1) -> 3 | D17: =2^(Jan_2026_SotM[[#This Row],[Round]]+1) -> 16 | E17: =Jan_2026_SotM[[#This Row],[Max Seed]]-Jan_2026_SotM[[#This Row],[Num]] -> 1 | F17: =Jan_2026_SotM[[#This Row],[Max Seed]]-Jan_2026_SotM[[#This Row],[Top Seed]]+1 -> 16 | G17: =IF(Jan_2026_SotM[[#This Row],[Round]]=$C$1, TRUE(), IF(Jan_2026_SotM[[#This Row],[Round]]=$B$1, Jan_2026_SotM[[#This Row],[Top Seed]]<=2*Jan_2026_SotM[[#This Row],[Max Seed]]-$A$1, FALSE())) -> TRUE | H17: =IF(Jan_2026_SotM[[#This Row],[Round]]=$C$1, TRUE(), IF(Jan_2026_SotM[[#This Row],[Round]]=$B$1, Jan_2026_SotM[[#This Row],[Low Seed]]<=2*Jan_2026_SotM[[#This Row],[Max Seed]]-$A$1, FALSE())) -> TRUE | J17: x | K17: x | L17: x | M17: x | N17: =IF(Jan_2026_SotM[[#This Row],[Num]]>=$A$1, "-", IF(Jan_2026_SotM[[#This Row],[Initial 1]], VLOOKUP(Jan_2026_SotM[[#This Row],[Top Seed]], $Z$2:$AE$17, 6, FALSE), OFFSET(Jan_2026_SotM[[#This Row],[Winner]], Jan_2026_SotM[[#This Row],[Max Seed]], 0))) -> In Da Club | O17: =COUNTIF(Jan_2026_SotM[[#This Row],[J]:[H]],"x") -> 4 | P17: =IF(Jan_2026_SotM[[#This Row],[Num]]>=$A$1, "-", IF(Jan_2026_SotM[[#This Row],[Score 1]]>=3, Jan_2026_SotM[[#This Row],[Song 1]], IF(Jan_2026_SotM[[#This Row],[Score 2]]>=3, Jan_2026_SotM[[#This Row],[Song 2]], "TBD"))) -> In Da Club | Q17: =COUNTIF(Jan_2026_SotM[[#This Row],[H ]:[J ]],"x") -> 1 | R17: =IF(Jan_2026_SotM[[#This Row],[Num]]>=$A$1, "-", IF(Jan_2026_SotM[[#This Row],[Initial 2]], VLOOKUP(Jan_2026_SotM[[#This Row],[Low Seed]], $Z$2:$AE$17, 6, FALSE), OFFSET(Jan_2026_SotM[[#This Row],[Winner]], 2*(Jan_2026_SotM[[#This Row],[Max Seed]]-Jan_2026_SotM[[#This Row],[Low Seed]])+1, 0))) -> RABBITHOLE | W17: x | X17: =IF(OR(Jan_2026_SotM[[#This Row],[Song 1]]="TBD", Jan_2026_SotM[[#This Row],[Song 2]]="TBD"), "TBD", _xlfn.CONCAT(IF(_xlfn.XOR(ISBLANK(Jan_2026_SotM[[#This Row],[J]]), ISBLANK(Jan_2026_SotM[[#This Row],[J ]])), "", "J "), IF(_xlfn.XOR(ISBLANK(Jan_2026_SotM[[#This Row],[D]]), ISBLANK(Jan_2026_SotM[[#This Row],[D ]])), "", "D "), IF(_xlfn.XOR(ISBLANK(Jan_2026_SotM[[#This Row],[L]]), ISBLANK(Jan_2026_SotM[[#This Row],[L ]])), "", "L "), IF(_xlfn.XOR(ISBLANK(Jan_2026_SotM[[#This Row],[S]]), ISBLANK(Jan_2026_SotM[[#This Row],[S ]])), "", "S "), IF(_xlfn.XOR(ISBLANK(Jan_2026_SotM[[#This Row],[H]]), ISBLANK(Jan_2026_SotM[[#This Row],[H ]])), "", "H "))) | Z17: =IF(AC17>0, COUNTIF(AC$2:AC$17, "<"&AC17) + COUNTIFS(AC$2:AC$17, AC17, AD$2:AD$17, "<"&AD17) + COUNTIFS(AC$2:AC$17, AC17, AD$2:AD$17, AD17, AA$2:AA$17, "<"&AA17) + 1, "TBD") -> 1 | AA17: 46051 | AB17: currydestroyer27 | AC17: 1.4 | AD17: 0.48989795 | AE17: In Da Club | AF17: 50 Cent | AG17: =IF(Z17>1, 2^FLOOR(LOG(Z17-1, 2), 1)+1, 1) -> 1 | AI17: =Jan_2026_SotM[[#This Row],[Max Seed]]/2 + 1 -> 9 | AJ17: =IF(Jan_2026_SotM[[#This Row],[Num]]>=$A$1, "-", IF(Jan_2026_SotM[[#This Row],[Score 1]]>=3, Jan_2026_SotM[[#This Row],[Song 2]], IF(Jan_2026_SotM[[#This Row],[Score 2]]>=3, Jan_2026_SotM[[#This Row],[Song 1]], "TBD"))) -> RABBITHOLE | AK17: =IFERROR(VLOOKUP(Jan_2025_Results48[[#This Row],[Song Title]], $AE$2:$AG$17, 3, FALSE)-Jan_2025_Results48[[#This Row],[Result]], "TBD") -> 0 | AL17: =IF(AK17<0,"↓",IF(AK17=0,"-","↑")) -> -
A19: =MAX(Z20:Z35) -> 16 | B19: =FLOOR(LOG(A19, 2), 1)-1 -> 3 | C19: =_xlfn.CEILING.MATH(LOG(A19, 2), 1)-1 -> 3 | I19: February | Z19: Seeding | AA19: Date | AB19: Poster | AC19: Average | AD19: STDEV | AE19: Song | AF19: Artist | AG19: Expected | AI19: Result | AJ19: Song Title | AK19: Diff | AL19: Shift
A20: Description | B20: Num | C20: Round | D20: Max Seed | E20: Top Seed | F20: Low Seed | G20: Initial 1 | H20: Initial 2 | I20: J | J20: D | K20: L | L20: S | M20: H | N20: Song 1 | O20: Score 1 | P20: Winner | Q20: Score 2 | R20: Song 2 | S20: H | T20: S | U20: L | V20: D | W20: J | X20: Remaining | Z20: =IF(AC20>0, COUNTIF(AC$20:AC$35, "<"&AC20) + COUNTIFS(AC$20:AC$35, AC20, AD$20:AD$35, "<"&AD20) + COUNTIFS(AC$20:AC$35, AC20, AD$20:AD$35, AD20, AA$20:AA$35, "<"&AA20) + 1, "TBD") -> 10 | AA20: {=_xlfn._xlws.FILTER(Data[Date]:Data[Artist], (Data[Date]>=DATE(2026,2,1))*(Data[Date]<=DATE(2026,2,28))*(Data[Winner]=TRUE()), "TBD")} -> 46055 | AB20: loganworsdell | AC20: 2.4 | AD20: 1.0198039 | AE20: diamonds are forever | AF20: bbno$ | AG20: =IF(Z20>1, 2^FLOOR(LOG(Z20-1, 2), 1)+1, 1) -> 9 | AI20: 1 | AJ20: =P21 -> あの空の向こうがわへ | AK20: =IFERROR(VLOOKUP(Feb_2025_Results50[[#This Row],[Song Title]], $AE$20:$AG$35, 3, FALSE)-Feb_2025_Results50[[#This Row],[Result]], "TBD") -> 8 | AL20: =IF(AK20<0,"↓",IF(AK20=0,"-","↑")) -> ↑
A21: =_xlfn.CONCAT("Seed ", Feb_2026_SotM[[#This Row],[Top Seed]], " vs ",Feb_2026_SotM[[#This Row],[Low Seed]]) -> Seed 1 vs 2 | B21: 1 | C21: =FLOOR(LOG(Feb_2026_SotM[[#This Row],[Num]], 2), 1) -> 0 | D21: =2^(Feb_2026_SotM[[#This Row],[Round]]+1) -> 2 | E21: =Feb_2026_SotM[[#This Row],[Max Seed]]-Feb_2026_SotM[[#This Row],[Num]] -> 1 | F21: =Feb_2026_SotM[[#This Row],[Max Seed]]-Feb_2026_SotM[[#This Row],[Top Seed]]+1 -> 2 | G21: =IF(Feb_2026_SotM[[#This Row],[Round]]=$C$19, TRUE(), IF(Feb_2026_SotM[[#This Row],[Round]]=$B$19, Feb_2026_SotM[[#This Row],[Top Seed]]<=2*Feb_2026_SotM[[#This Row],[Max Seed]]-$A$19, FALSE())) -> FALSE | H21: =IF(Feb_2026_SotM[[#This Row],[Round]]=$C$19, TRUE(), IF(Feb_2026_SotM[[#This Row],[Round]]=$B$19, Feb_2026_SotM[[#This Row],[Low Seed]]<=2*Feb_2026_SotM[[#This Row],[Max Seed]]-$A$19, FALSE())) -> FALSE | K21: x | N21: =IF(Feb_2026_SotM[[#This Row],[Num]]>=$A$19, "-", IF(Feb_2026_SotM[[#This Row],[Initial 1]], VLOOKUP(Feb_2026_SotM[[#This Row],[Top Seed]], $Z$20:$AE$35, 6, FALSE), OFFSET(Feb_2026_SotM[[#This Row],[Winner]], Feb_2026_SotM[[#This Row],[Max Seed]], 0))) -> GIRLLIKEYOU | O21: =COUNTIF(Feb_2026_SotM[[#This Row],[J]:[H]],"x") -> 1 | P21: =IF(Feb_2026_SotM[[#This Row],[Num]]>=$A$19, "-", IF(Feb_2026_SotM[[#This Row],[Score 1]]>=3, Feb_2026_SotM[[#This Row],[Song 1]], IF(Feb_2026_SotM[[#This Row],[Score 2]]>=3, Feb_2026_SotM[[#This Row],[Song 2]], "TBD"))) -> あの空の向こうがわへ | Q21: =COUNTIF(Feb_2026_SotM[[#This Row],[H ]:[J ]],"x") -> 4 | R21: =IF(Feb_2026_SotM[[#This Row],[Num]]>=$A$19, "-", IF(Feb_2026_SotM[[#This Row],[Initial 2]], VLOOKUP(Feb_2026_SotM[[#This Row],[Low Seed]], $Z$20:$AE$35, 6, FALSE), OFFSET(Feb_2026_SotM[[#This Row],[Winner]], 2*(Feb_2026_SotM[[#This Row],[Max Seed]]-Feb_2026_SotM[[#This Row],[Low Seed]])+1, 0))) -> あの空の向こうがわへ | S21: x | T21: x | V21: x | W21: x | X21: =IF(OR(Feb_2026_SotM[[#This Row],[Song 1]]="TBD", Feb_2026_SotM[[#This Row],[Song 2]]="TBD"), "TBD", _xlfn.CONCAT(IF(_xlfn.XOR(ISBLANK(Feb_2026_SotM[[#This Row],[J]]), ISBLANK(Feb_2026_SotM[[#This Row],[J ]])), "", "J "), IF(_xlfn.XOR(ISBLANK(Feb_2026_SotM[[#This Row],[D]]), ISBLANK(Feb_2026_SotM[[#This Row],[D ]])), "", "D "), IF(_xlfn.XOR(ISBLANK(Feb_2026_SotM[[#This Row],[L]]), ISBLANK(Feb_2026_SotM[[#This Row],[L ]])), "", "L "), IF(_xlfn.XOR(ISBLANK(Feb_2026_SotM[[#This Row],[S]]), ISBLANK(Feb_2026_SotM[[#This Row],[S ]])), "", "S "), IF(_xlfn.XOR(ISBLANK(Feb_2026_SotM[[#This Row],[H]]), ISBLANK(Feb_2026_SotM[[#This Row],[H ]])), "", "H "))) | Z21: =IF(AC21>0, COUNTIF(AC$20:AC$35, "<"&AC21) + COUNTIFS(AC$20:AC$35, AC21, AD$20:AD$35, "<"&AD21) + COUNTIFS(AC$20:AC$35, AC21, AD$20:AD$35, AD21, AA$20:AA$35, "<"&AA21) + 1, "TBD") -> 9 | AA21: 46056 | AB21: loganworsdell | AC21: 2.4 | AD21: 0.48989795 | AE21: Stoked | AF21: Weston Estate | AG21: =IF(Z21>1, 2^FLOOR(LOG(Z21-1, 2), 1)+1, 1) -> 9 | AI21: =Feb_2026_SotM[[#This Row],[Max Seed]]/2 + 1 -> 2 | AJ21: =IF(Feb_2026_SotM[[#This Row],[Num]]>=$A$19, "-", IF(Feb_2026_SotM[[#This Row],[Score 1]]>=3, Feb_2026_SotM[[#This Row],[Song 2]], IF(Feb_2026_SotM[[#This Row],[Score 2]]>=3, Feb_2026_SotM[[#This Row],[Song 1]], "TBD"))) -> GIRLLIKEYOU | AK21: =IFERROR(VLOOKUP(Feb_2025_Results50[[#This Row],[Song Title]], $AE$20:$AG$35, 3, FALSE)-Feb_2025_Results50[[#This Row],[Result]], "TBD") -> -1 | AL21: =IF(AK21<0,"↓",IF(AK21=0,"-","↑")) -> ↓
A22: =_xlfn.CONCAT("Seed ", Feb_2026_SotM[[#This Row],[Top Seed]], " vs ",Feb_2026_SotM[[#This Row],[Low Seed]]) -> Seed 2 vs 3 | B22: 2 | C22: =FLOOR(LOG(Feb_2026_SotM[[#This Row],[Num]], 2), 1) -> 1 | D22: =2^(Feb_2026_SotM[[#This Row],[Round]]+1) -> 4 | E22: =Feb_2026_SotM[[#This Row],[Max Seed]]-Feb_2026_SotM[[#This Row],[Num]] -> 2 | F22: =Feb_2026_SotM[[#This Row],[Max Seed]]-Feb_2026_SotM[[#This Row],[Top Seed]]+1 -> 3 | G22: =IF(Feb_2026_SotM[[#This Row],[Round]]=$C$19, TRUE(), IF(Feb_2026_SotM[[#This Row],[Round]]=$B$19, Feb_2026_SotM[[#This Row],[Top Seed]]<=2*Feb_2026_SotM[[#This Row],[Max Seed]]-$A$19, FALSE())) -> FALSE | H22: =IF(Feb_2026_SotM[[#This Row],[Round]]=$C$19, TRUE(), IF(Feb_2026_SotM[[#This Row],[Round]]=$B$19, Feb_2026_SotM[[#This Row],[Low Seed]]<=2*Feb_2026_SotM[[#This Row],[Max Seed]]-$A$19, FALSE())) -> FALSE | K22: x | N22: =IF(Feb_2026_SotM[[#This Row],[Num]]>=$A$19, "-", IF(Feb_2026_SotM[[#This Row],[Initial 1]], VLOOKUP(Feb_2026_SotM[[#This Row],[Top Seed]], $Z$20:$AE$35, 6, FALSE), OFFSET(Feb_2026_SotM[[#This Row],[Winner]], Feb_2026_SotM[[#This Row],[Max Seed]], 0))) -> diamonds are forever | O22: =COUNTIF(Feb_2026_SotM[[#This Row],[J]:[H]],"x") -> 1 | P22: =IF(Feb_2026_SotM[[#This Row],[Num]]>=$A$19, "-", IF(Feb_2026_SotM[[#This Row],[Score 1]]>=3, Feb_2026_SotM[[#This Row],[Song 1]], IF(Feb_2026_SotM[[#This Row],[Score 2]]>=3, Feb_2026_SotM[[#This Row],[Song 2]], "TBD"))) -> あの空の向こうがわへ | Q22: =COUNTIF(Feb_2026_SotM[[#This Row],[H ]:[J ]],"x") -> 4 | R22: =IF(Feb_2026_SotM[[#This Row],[Num]]>=$A$19, "-", IF(Feb_2026_SotM[[#This Row],[Initial 2]], VLOOKUP(Feb_2026_SotM[[#This Row],[Low Seed]], $Z$20:$AE$35, 6, FALSE), OFFSET(Feb_2026_SotM[[#This Row],[Winner]], 2*(Feb_2026_SotM[[#This Row],[Max Seed]]-Feb_2026_SotM[[#This Row],[Low Seed]])+1, 0))) -> あの空の向こうがわへ | S22: x | T22: x | V22: x | W22: x | X22: =IF(OR(Feb_2026_SotM[[#This Row],[Song 1]]="TBD", Feb_2026_SotM[[#This Row],[Song 2]]="TBD"), "TBD", _xlfn.CONCAT(IF(_xlfn.XOR(ISBLANK(Feb_2026_SotM[[#This Row],[J]]), ISBLANK(Feb_2026_SotM[[#This Row],[J ]])), "", "J "), IF(_xlfn.XOR(ISBLANK(Feb_2026_SotM[[#This Row],[D]]), ISBLANK(Feb_2026_SotM[[#This Row],[D ]])), "", "D "), IF(_xlfn.XOR(ISBLANK(Feb_2026_SotM[[#This Row],[L]]), ISBLANK(Feb_2026_SotM[[#This Row],[L ]])), "", "L "), IF(_xlfn.XOR(ISBLANK(Feb_2026_SotM[[#This Row],[S]]), ISBLANK(Feb_2026_SotM[[#This Row],[S ]])), "", "S "), IF(_xlfn.XOR(ISBLANK(Feb_2026_SotM[[#This Row],[H]]), ISBLANK(Feb_2026_SotM[[#This Row],[H ]])), "", "H "))) | Z22: =IF(AC22>0, COUNTIF(AC$20:AC$35, "<"&AC22) + COUNTIFS(AC$20:AC$35, AC22, AD$20:AD$35, "<"&AD22) + COUNTIFS(AC$20:AC$35, AC22, AD$20:AD$35, AD22, AA$20:AA$35, "<"&AA22) + 1, "TBD") -> 1 | AA22: 46057 | AB22: currydestroyer27 | AC22: 1.4 | AD22: 0.48989795 | AE22: GIRLLIKEYOU | AF22: 3ee, aria., karinovaa | AG22: =IF(Z22>1, 2^FLOOR(LOG(Z22-1, 2), 1)+1, 1) -> 1 | AI22: =Feb_2026_SotM[[#This Row],[Max Seed]]/2 + 1 -> 3 | AJ22: =IF(Feb_2026_SotM[[#This Row],[Num]]>=$A$19, "-", IF(Feb_2026_SotM[[#This Row],[Score 1]]>=3, Feb_2026_SotM[[#This Row],[Song 2]], IF(Feb_2026_SotM[[#This Row],[Score 2]]>=3, Feb_2026_SotM[[#This Row],[Song 1]], "TBD"))) -> diamonds are forever | AK22: =IFERROR(VLOOKUP(Feb_2025_Results50[[#This Row],[Song Title]], $AE$20:$AG$35, 3, FALSE)-Feb_2025_Results50[[#This Row],[Result]], "TBD") -> 6 | AL22: =IF(AK22<0,"↓",IF(AK22=0,"-","↑")) -> ↑
